Workbook

Sheet RAW DATA - DO NOT EDIT
A1: Enrollment_ID | B1: Enrollment_Date | C1: Company | D1: Course_Category | E1: Course_Name | F1: City | G1: State | H1: City_Tier | I1: Gender | J1: Age_Group | K1: Referral_Source | L1: Payment_Mode | M1: Device_Type | N1: Original_Price_INR | O1: Discount_% | P1: Discount_Amount_INR | Q1: Final_Price_INR | R1: GST_Amount_INR | S1: Net_Revenue_INR | T1: Platform_Cost_INR | U1: Gross_Profit_INR | V1: Gross_Margin_% | W1: Course_Completed | X1: Student_Rating | Y1: Refund_Issued | Z1: Support_Tickets_Raised
A2: EDU00524 | B2: 08-11-2023 | C2: Embibe | D2: Coding & Tech | E2: Python for Beginners | F2: Jodhpur | G2: Rajasthan | H2: Tier 3 | I2: Male | J2: 25-34 | K2: Google Ads | L2: Debit Card | M2: Desktop | N2: 7999 | O2: 40 | P2: 3199.6 | Q2: 4799.4 | R2: 863.89 | S2: 3935.51 | T2: 2203.97 | U2: 1731.54 | V2: 44 | W2: Yes | X2: 4.6 | Y2: No | Z2: 1
A3: EDU00061 | B3: 05-12-2023 | C3: Meritnation | D3: Test Preparation | E3: GRE Verbal+Quant | F3: Mangaluru | G3: Karnataka | H3: Tier 3 | I3: Male | J3: 25-34 | K3: Instagram | L3: Wallet | M3: Tablet | N3: 11999 | O3: 10 | P3: 1199.9 | Q3: 10799.1 | R3: 1943.84 | S3: 8855.26 | T3: 3836.62 | U3: 5018.64 | V3: 56.67 | W3: Yes | X3: 4 | Y3: No | Z3: 0
A4: EDU00457 | B4: 15-12-2024 | C4: Embibe | D4: Higher Education | E4: MBA Finance Prep | F4: Ghaziabad | G4: Delhi NCR | H4: Tier 2 | I4: Other | J4: 18-24 | K4: Word of Mouth | L4: Credit Card | M4: Mobile | N4: 11999 | O4: 25 | P4: 2999.75 | Q4: 8999.25 | R4: 1619.87 | S4: 7379.38 | T4: 3191.83 | U4: 4187.55 | V4: 56.75 | W4: Yes | X4: 3.6 | Y4: No | Z4: 0
A5: EDU01052 | B5: 29-08-2024 | C5: Toppr | D5: Test Preparation | E5: SAT Complete Prep | F5: Ahmedabad | G5: Gujarat | H5: Tier 1 | I5: Male | J5: 13-17 | K5: YouTube | L5: Credit Card | M5: Mobile | N5: 12999 | O5: 0 | P5: 0 | Q5: 12999 | R5: 2339.82 | S5: 10659.18 | T5: 3738.71 | U5: 6920.47 | V5: 64.92 | W5: Yes | X5: 3.7 | Y5: No | Z5: 1
A6: EDU00891 | B6: 09-02-2023 | C6: Vedantu | D6: Test Preparation | E6: SAT Complete Prep | F6: Kolkata | G6: West Bengal | H6: Tier 1 | I6: Other | J6: 35-44 | K6: Google Ads | L6: Debit Card | M6: Desktop | N6: 12999 | O6: 40 | P6: 5199.6 | Q6: 7799.4 | R6: 1403.89 | S6: 6395.51 | T6: 3376.69 | U6: 3018.82 | V6: 47.2 | W6: Yes | X6: 3.6 | Y6: No | Z6: 0
A7: EDU01966 | B7: 12-01-2023 | C7: Toppr | D7: Professional Upskilling | E7: Digital Marketing Pro | F7: Gurugram | G7: Delhi NCR | H7: Tier 1 | I7: Female | J7: 25-34 | K7: WhatsApp | L7: EMI | M7: Mobile | N7: 12999 | O7: 0 | P7: 0 | Q7: 12999 | R7: 2339.82 | S7: 10659.18 | T7: 3264.37 | U7: 7394.81 | V7: 69.38 | W7: Yes | X7: 4.5 | Y7: No | Z7: 1
A8: EDU00027 | B8: 03-11-2023 | C8: BYJU'S | D8: Higher Education | E8: MBA Finance Prep | F8: Vadodara | G8: Gujarat | H8: Tier 3 | I8: Male | J8: 25-34 | K8: School/College Partnership | L8: EMI | M8: Mobile | N8: 11999 | O8: 0 | P8: 0 | Q8: 11999 | R8: 2159.82 | S8: 9839.18 | T8: 4348.29 | U8: 5490.89 | V8: 55.81 | W8: No | Y8: No | Z8: 1
A9: EDU00427 | B9: 18-01-2024 | C9: upGrad | D9: Creative Arts | E9: Video Editing Basics | F9: Pune | G9: Maharashtra | H9: Tier 1 | I9: Female | J9: 35-44 | K9: Word of Mouth | L9: Debit Card | M9: Mobile | N9: 6999 | O9: 5 | P9: 349.95 | Q9: 6649.05 | R9: 1196.83 | S9: 5452.22 | T9: 2206.78 | U9: 3245.44 | V9: 59.53 | W9: Yes | X9: 2.9 | Y9: No | Z9: 2
A10: EDU01634 | B10: 16-01-2023 | C10: Physics Wallah | D10: Creative Arts | E10: UI/UX Design | F10: Warangal | G10: Telangana | H10: Tier 3 | I10: Male | J10: 35-44 | K10: Direct/Organic | L10: EMI | M10: Mobile | N10: 14999 | O10: 25 | P10: 3749.75 | Q10: 11249.25 | R10: 2024.87 | S10: 9224.38 | T10: 4357.82 | U10: 4866.56 | V10: 52.76 | W10: No | Y10: No | Z10: 1
A11: EDU00833 | B11: 03-11-2024 | C11: Vedantu | D11: Higher Education | E11: MBA Finance Prep | F11: Madurai | G11: Tamil Nadu | H11: Tier 3 | I11: Other | J11: 18-24 | K11: Instagram | L11: Credit Card | M11: Desktop | N11: 11999 | O11: 50 | P11: 5999.5 | Q11: 5999.5 | R11: 1079.91 | S11: 4919.59 | T11: 2534.61 | U11: 2384.98 | V11: 48.48 | W11: No | Y11: No | Z11: 0
A12: EDU02161 | B12: 15-11-2023 | C12: Toppr | D12: Test Preparation | E12: SAT Complete Prep | F12: NOIDA | G12: Delhi NCR | H12: Tier 1 | I12: Male | J12: 18-24 | K12: Email Campaign | L12: UPI | M12: Mobile | N12: 12999 | O12: 40 | P12: 5199.6 | Q12: 7799.4 | R12: 1403.89 | S12: 6395.51 | T12: 2933.31 | U12: 3462.2 | V12: 54.13 | W12: No | Y12: Yes | Z12: 1
A13: EDU01493 | B13: 19-02-2024 | C13: Embibe | D13: Higher Education | E13: B.Tech CSE Support | F13: Warangal | G13: Telangana | H13: Tier 3 | I13: Male | J13: 13-17 | K13: YouTube | L13: Credit Card | M13: Mobile | N13: 9999 | O13: 10 | P13: 999.9 | Q13: 8999.1 | R13: 1619.84 | S13: 7379.26 | T13: 3528.47 | U13: 3850.79 | V13: 52.18 | W13: No | Y13: No | Z13: 1
A14: EDU02280 | B14: 14-10-2023 | C14: Simplilearn | D14: Professional Upskilling | E14: Digital Marketing Pro | F14: Mysuru | G14: Karnataka | H14: Tier 2 | I14: Female | J14: 25-34 | K14: WhatsApp | L14: EMI | M14: Desktop | N14: 12999 | O14: 20 | P14: 2599.8 | Q14: 10399.2 | R14: 1871.86 | S14: 8527.34 | T14: 3512.35 | U14: 5014.99 | V14: 58.81 | W14: No | Y14: No | Z14: 1
A15: EDU00700 | B15: 02-11-2023 | C15: BYJU'S | D15: Language Learning | E15: English Communication | F15: Chennai | G15: Tamil Nadu | H15: Tier 1 | I15: Male | J15: 13-17 | K15: Word of Mouth | L15: Credit Card | M15: Tablet | N15: 4999 | O15: 15 | P15: 749.85 | Q15: 4249.15 | R15: 764.85 | S15: 3484.3 | T15: 1347.82 | U15: 2136.48 | V15: 61.32 | W15: No | Y15: No | Z15: 3
A16: EDU02121 | B16: 21-12-2024 | C16: Great Learning | D16: Coding & Tech | E16: Full Stack Development | F16: Bengaluru | G16: Karnataka | H16: Tier 1 | I16: Female | J16: 45+ | K16: Direct/Organic | L16: UPI | M16: Tablet | N16: 29999 | O16: 40 | P16: 11999.6 | Q16: 17999.4 | R16: 3239.89 | S16: 14759.51 | T16: 6414.9 | U16: 8344.61 | V16: 56.54 | W16: Yes | X16: 4.2 | Y16: No | Z16: 0
A17: EDU00341 | B17: 10-11-2024 | C17: Doubtnut | D17: Creative Arts | E17: Graphic Design Pro | F17: Vadodara | G17: Gujarat | H17: Tier 3 | I17: Male | J17: 18-24 | K17: Direct/Organic | L17: Net Banking | M17: Mobile | N17: 9999 | O17: 25 | P17: 2499.75 | Q17: 7499.25 | R17: 1349.87 | S17: 6149.38 | T17: 2274.96 | U17: 3874.42 | V17: 63.01 | W17: No | Y17: No | Z17: 3
A18: EDU02148 | B18: 20-11-2023 | C18: Extramarks | D18: Test Preparation | E18: SAT Complete Prep | F18: Nashik | G18: Maharashtra | H18: Tier 2 | I18: Female | J18: 35-44 | K18: Email Campaign | L18: Wallet | M18: Desktop | N18: 12999 | O18: 40 | P18: 5199.6 | Q18: 7799.4 | R18: 1403.89 | S18: 6395.51 | T18: 3570.77 | U18: 2824.74 | V18: 44.17 | W18: No | Y18: No | Z18: 0
A19: EDU00152 | B19: 24-11-2023 | C19: Simplilearn | D19: Competitive Exams | E19: GATE CS Complete | F19: Vadodara | G19: Gujarat | H19: Tier 3 | I19: Male | J19: 18-24 | K19: Email Campaign | L19: EMI | M19: Mobile | N19: 12999 | O19: 25 | P19: 3249.75 | Q19: 9749.25 | R19: 1754.87 | S19: 7994.38 | T19: 3501.87 | U19: 4492.51 | V19: 56.2 | W19: Yes | Y19: No | Z19: 0
A20: EDU01163 | B20: 15-06-2024 | C20: BYJU'S | D20: Language Learning | E20: Business English | F20: Nashik | G20: Maharashtra | H20: Tier 2 | I20: Male | J20: 18-24 | K20: Direct/Organic | L20: UPI | M20: Mobile | N20: 6999 | O20: 40 | P20: 2799.6 | Q20: 4199.4 | R20: 755.89 | S20: 3443.51 | T20: 1857.34 | U20: 1586.17 | V20: 46.06 | W20: Yes | X20: 4 | Y20: No | Z20: 0
A21: EDU02226 | B21: 19-05-2023 | C21: BYJU'S | D21: Coding & Tech | E21: Python for Beginners | F21: Jaipur | G21: Rajasthan | H21: Tier 2 | I21: Male | J21: 18-24 | K21: Instagram | L21: Debit Card | M21: Mobile | N21: 7999 | O21: 0 | P21: 0 | Q21: 7999 | R21: 1439.82 | S21: 6559.18 | T21: 2831.55 | U21: 3727.63 | V21: 56.83 | W21: Yes | X21: 4.3 | Y21: No | Z21: 0
A22: EDU02334 | B22: 25-07-2024 | C22: BYJU'S | D22: Coding & Tech | E22: Full Stack Development | F22: Howrah | G22: West Bengal | H22: Tier 3 | I22: Female | J22: 25-34 | K22: Google Ads | L22: Wallet | M22: Mobile | N22: 29999 | O22: 40 | P22: 11999.6 | Q22: 17999.4 | R22: 3239.89 | S22: 14759.51 | T22: 7295.56 | U22: 7463.95 | V22: 50.57 | W22: Yes | Y22: No | Z22: 0
A23: EDU00808 | B23: 09-10-2023 | C23: Doubtnut | D23: Test Preparation | E23: GRE Verbal+Quant | F23: Surat | G23: Gujarat | H23: Tier 2 | I23: Female | J23: 45+ | K23: Word of Mouth | L23: UPI | M23: Tablet | N23: 11999 | O23: 0 | P23: 0 | Q23: 11999 | R23: 2159.82 | S23: 9839.18 | T23: 4634.06 | U23: 5205.12 | V23: 52.9 | W23: Yes | X23: 3.1 | Y23: No | Z23: 2
A24: EDU01261 | B24: 14-01-2024 | C24: Great Learning | D24: Competitive Exams | E24: IIT-JEE Advanced Prep | F24: Howrah | G24: West Bengal | H24: Tier 3 | I24: Female | J24: 18-24 | K24: Email Campaign | L24: Wallet | M24: Desktop | N24: 24999 | O24: 20 | P24: 4999.8 | Q24: 19999.2 | R24: 3599.86 | S24: 16399.34 | T24: 6763.99 | U24: 9635.35 | V24: 58.75 | W24: Yes | X24: 3.7 | Y24: No | Z24: 0
A25: EDU01083 | B25: 17-06-2023 | C25: Doubtnut | D25: Competitive Exams | E25: CAT Prep Masterclass | F25: Chennai | G25: Tamil Nadu | H25: Tier 1 | I25: Other | J25: 35-44 | K25: Google Ads | L25: Credit Card | M25: Desktop | N25: 14999 | O25: 0 | P25: 0 | Q25: 14999 | R25: 2699.82 | S25: 12299.18 | T25: 4245.97 | U25: 8053.21 | V25: 65.48 | W25: Yes | X25: 3.4 | Y25: No | Z25: 0
A26: EDU00326 | B26: 05-01-2023 | C26: Meritnation | D26: Professional Upskilling | E26: Digital Marketing Pro | F26: Surat | G26: Gujarat | H26: Tier 2 | I26: Male | J26: 35-44 | K26: School/College Partnership | L26: Credit Card | M26: Mobile | N26: 12999 | O26: 50 | P26: 6499.5 | Q26: 6499.5 | R26: 1169.91 | S26: 5329.59 | T26: 2783.75 | U26: 2545.84 | V26: 47.77 | W26: No | Y26: No | Z26: 1
A27: EDU00465 | B27: 27-05-2024 | C27: Scaler | D27: K-12 Academics | E27: Class 8-10 Science Pack | F27: Madurai | G27: Tamil Nadu | H27: Tier 3 | I27: Female | J27: 35-44 | K27: YouTube | L27: UPI | M27: Desktop | N27: 4999 | O27: 5 | P27: 249.95 | Q27: 4749.05 | R27: 854.83 | S27: 3894.22 | T27: 2019.87 | U27: 1874.35 | V27: 48.13 | W27: No | Y27: No | Z27: 1
A28: EDU00745 | B28: 12-05-2023 | C28: Meritnation | D28: K-12 Academics | E28: Foundation Course | F28: Bengaluru | G28: Karnataka | H28: Tier 1 | I28: Female | J28: 35-44 | K28: WhatsApp | L28: Wallet | M28: Tablet | N28: 6999 | O28: 40 | P28: 2799.6 | Q28: 4199.4 | R28: 755.89 | S28: 3443.51 | T28: 1688.9 | U28: 1754.61 | V28: 50.95 | W28: No | Y28: No | Z28: 1
A29: EDU02388 | B29: 27-06-2023 | C29: Embibe | D29: Professional Upskilling | E29: Data Analytics Bootcamp | F29: Gurugram | G29: Delhi NCR | H29: Tier 1 | I29: Other | J29: 35-44 | K29: Word of Mouth | L29: Net Banking | M29: Mobile | N29: 19999 | O29: 40 | P29: 7999.6 | Q29: 11999.4 | R29: 2159.89 | S29: 9839.51 | T29: 4786.15 | U29: 5053.36 | V29: 51.36 | W29: Yes | X29: 3.4 | Y29: No | Z29: 0
A30: EDU01927 | B30: 17-07-2024 | C30: Leverage Edu | D30: K-12 Academics | E30: Class 8-10 Science Pack | F30: Howrah | G30: West Bengal | H30: Tier 3 | I30: Male | J30: 18-24 | K30: School/College Partnership | L30: Net Banking | M30: Mobile | N30: 4999 | O30: 0 | P30: 0 | Q30: 4999 | R30: 899.82 | S30: 4099.18 | T30: 2251.19 | U30: 1847.99 | V30: 45.08 | W30: No | Y30: Yes | Z30: 2
A31: EDU00661 | B31: 10-04-2024 | C31: Great Learning | D31: Coding & Tech | E31: Data Science Masters | F31: Vadodara | G31: Gujarat | H31: Tier 3 | I31: Other | J31: 25-34 | K31: Instagram | L31: Net Banking | M31: Tablet | N31: 34999 | O31: 0 | P31: 0 | Q31: 34999 | R31: 6299.82 | S31: 28699.18 | T31: 15004.71 | U31: 13694.47 | V31: 47.72 | W31: Yes | X31: 4.2 | Y31: No | Z31: 0
A32: EDU01751 | B32: 27-06-2023 | C32: Extramarks | D32: Test Preparation | E32: SAT Complete Prep | F32: Faridabad | G32: Delhi NCR | H32: Tier 2 | I32: Other | J32: 25-34 | K32: Word of Mouth | L32: Debit Card | M32: Tablet | N32: 12999 | O32: 20 | P32: 2599.8 | Q32: 10399.2 | R32: 1871.86 | S32: 8527.34 | T32: 4283.93 | U32: 4243.41 | V32: 49.76 | W32: Yes | X32: 3.5 | Y32: No | Z32: 1
A33: EDU00116 | B33: 16-03-2024 | C33: Vedantu | D33: Creative Arts | E33: UI/UX Design | F33: Mumbai | G33: Maharashtra | H33: Tier 1 | I33: Other | J33: 25-34 | K33: Instagram | L33: Net Banking | M33: Tablet | N33: 14999 | O33: 50 | P33: 7499.5 | Q33: 7499.5 | R33: 1349.91 | S33: 6149.59 | T33: 3376.6 | U33: 2772.99 | V33: 45.09 | W33: Yes | X33: 3.7 | Y33: No | Z33: 0
A34: EDU01438 | B34: 02-06-2023 | C34: Scaler | D34: Professional Upskilling | E34: Financial Modelling | F34: Nashik | G34: Maharashtra | H34: Tier 2 | I34: Male | J34: 45+ | K34: WhatsApp | L34: Wallet | M34: Mobile | N34: 15999 | O34: 10 | P34: 1599.9 | Q34: 14399.1 | R34: 2591.84 | S34: 11807.26 | T34: 5560.38 | U34: 6246.88 | V34: 52.91 | W34: Yes | X34: 2.7 | Y34: No | Z34: 1
A35: EDU02469 | B35: 12-10-2023 | C35: Doubtnut | D35: Professional Upskilling | E35: HR Management | F35: Hyderabad | G35: Telangana | H35: Tier 1 | I35: Male | J35: 25-34 | K35: Instagram | L35: Credit Card | M35: Mobile | N35: 8999 | O35: 0 | P35: 0 | Q35: 8999 | R35: 1619.82 | S35: 7379.18 | T35: 2355.9 | U35: 5023.28 | V35: 68.07 | W35: No | Y35: Yes | Z35: 0
A36: EDU01030 | B36: 11-03-2024 | C36: Toppr | D36: K-12 Academics | E36: Class 11-12 PCB | F36: Chennai | G36: Tamil Nadu | H36: Tier 1 | I36: Male | J36: 25-34 | K36: Direct/Organic | L36: Net Banking | M36: Mobile | N36: 8499 | O36: 20 | P36: 1699.8 | Q36: 6799.2 | R36: 1223.86 | S36: 5575.34 | T36: 2362.25 | U36: 3213.09 | V36: 57.63 | W36: No | Y36: No | Z36: 1
A37: EDU00451 | B37: 20-07-2024 | C37: Scaler | D37: Higher Education | E37: B.Tech CSE Support | F37: Warangal | G37: Telangana | H37: Tier 3 | I37: Female | J37: 25-34 | K37: Word of Mouth | L37: Credit Card | M37: Desktop | N37: 9999 | O37: 0 | P37: 0 | Q37: 9999 | R37: 1799.82 | S37: 8199.18 | T37: 3293.48 | U37: 4905.7 | V37: 59.83 | W37: Yes | X37: 2.8 | Y37: No | Z37: 1
A38: EDU01690 | B38: 21-08-2024 | C38: Leverage Edu | D38: Professional Upskilling | E38: Digital Marketing Pro | F38: Faridabad | G38: Delhi NCR | H38: Tier 2 | I38: Other | J38: 13-17 | K38: WhatsApp | L38: Wallet | M38: Tablet | N38: 12999 | O38: 0 | P38: 0 | Q38: 12999 | R38: 2339.82 | S38: 10659.18 | T38: 5160.76 | U38: 5498.42 | V38: 51.58 | W38: No | Y38: No | Z38: 0
A39: EDU00493 | B39: 28-11-2023 | C39: BYJU'S | D39: Language Learning | E39: Business English | F39: New Delhi | G39: Delhi NCR | H39: Tier 1 | I39: Male | J39: 18-24 | K39: Word of Mouth | L39: Debit Card | M39: Desktop | N39: 6999 | O39: 15 | P39: 1049.85 | Q39: 5949.15 | R39: 1070.85 | S39: 4878.3 | T39: 2141.47 | U39: 2736.83 | V39: 56.1 | W39: No | Y39: No | Z39: 0
A40: EDU01138 | B40: 08-12-2023 | C40: Doubtnut | D40: Coding & Tech | E40: Data Science Masters | F40: Pune | G40: Maharashtra | H40: Tier 1 | I40: Male | J40: 35-44 | K40: WhatsApp | L40: Net Banking | M40: Desktop | N40: 34999 | O40: 30 | P40: 10499.7 | Q40: 24499.3 | R40: 4409.87 | S40: 20089.43 | T40: 5458.37 | U40: 14631.06 | V40: 72.83 | W40: No | Y40: Yes | Z40: 0
A41: EDU01309 | B41: 08-03-2024 | C41: BYJU'S | D41: Competitive Exams | E41: UPSC GS Foundation | F41: Noida | G41: Delhi NCR | H41: Tier 1 | I41: Male | J41: 18-24 | K41: Instagram | L41: UPI | M41: Mobile | N41: 18999 | O41: 40 | P41: 7599.6 | Q41: 11399.4 | R41: 2051.89 | S41: 9347.51 | T41: 4563.59 | U41: 4783.92 | V41: 51.18 | W41: Yes | X41: 4.4 | Y41: No | Z41: 0
A42: EDU02068 | B42: 01-01-2024 | C42: Great Learning | D42: Professional Upskilling | E42: Digital Marketing Pro | F42: Noida | G42: Delhi NCR | H42: Tier 1 | I42: Female | J42: 35-44 | K42: Word of Mouth | L42: Debit Card | M42: Mobile | N42: 12999 | O42: 25 | P42: 3249.75 | Q42: 9749.25 | R42: 1754.87 | S42: 7994.38 | T42: 3183.21 | U42: 4811.17 | V42: 60.18 | W42: Yes | X42: 3.8 | Y42: No | Z42: 1
A43: EDU02259 | B43: 16-08-2023 | C43: Simplilearn | D43: Higher Education | E43: BBA Business Basics | F43: Noida | G43: Delhi NCR | H43: Tier 1 | I43: Male | J43: 45+ | K43: WhatsApp | L43: Net Banking | M43: Mobile | N43: 7499 | O43: 15 | P43: 1124.85 | Q43: 6374.15 | R43: 1147.35 | S43: 5226.8 | T43: 1637.16 | U43: 3589.64 | V43: 68.68 | W43: Yes | Y43: No | Z43: 0
A44: EDU01792 | B44: 13-05-2023 | C44: Toppr | D44: Higher Education | E44: B.Tech CSE Support | F44: Pune | G44: Maharashtra | H44: Tier 1 | I44: Male | J44: 18-24 | K44: Instagram | L44: Credit Card | M44: Mobile | N44: 9999 | O44: 30 | P44: 2999.7 | Q44: 6999.3 | R44: 1259.87 | S44: 5739.43 | T44: 2404.81 | U44: 3334.62 | V44: 58.1 | W44: Yes | X44: 4.2 | Y44: No | Z44: 0
A45: EDU00545 | B45: 31-10-2024 | C45: Scaler | D45: Test Preparation | E45: GMAT Focus Edition | F45: Vadodara | G45: Gujarat | H45: Tier 3 | I45: Male | J45: 13-17 | K45: YouTube | L45: Net Banking | M45: Tablet | N45: 16999 | O45: 25 | P45: 4249.75 | Q45: 12749.25 | R45: 2294.86 | S45: 10454.39 | T45: 5448.17 | U45: 5006.22 | V45: 47.89 | W45: Yes | X45: 4.2 | Y45: No | Z45: 1
A46: EDU00396 | B46: 06-11-2024 | C46: Meritnation | D46: Professional Upskilling | E46: HR Management | F46: Faridabad | G46: Delhi NCR | H46: Tier 2 | I46: Other | J46: 35-44 | K46: Email Campaign | L46: EMI | M46: Tablet | N46: 8999 | O46: 50 | P46: 4499.5 | Q46: 4499.5 | R46: 809.91 | S46: 3689.59 | T46: 2052.6 | U46: 1636.99 | V46: 44.37 | W46: No | Y46: Yes | Z46: 1
A47: EDU00640 | B47: 21-05-2024 | C47: Vedantu | D47: Creative Arts | E47: Graphic Design Pro | F47: Chennai | G47: Tamil Nadu | H47: Tier 1 | I47: Other | J47: 18-24 | K47: WhatsApp | L47: Credit Card | M47: Desktop | N47: 9999 | O47: 30 | P47: 2999.7 | Q47: 6999.3 | R47: 1259.87 | S47: 5739.43 | T47: 2797.85 | U47: 2941.58 | V47: 51.25 | W47: Yes | X47: 3.1 | Y47: No | Z47: 0
A48: EDU01671 | B48: 12-08-2023 | C48: Doubtnut | D48: Language Learning | E48: English Communication | F48: Mumbai | G48: Maharashtra | H48: Tier 1 | I48: Female | J48: 25-34 | K48: YouTube | L48: Net Banking | M48: Mobile | N48: 4999 | O48: 0 | P48: 0 | Q48: 4999 | R48: 899.82 | S48: 4099.18 | T48: 1743.29 | U48: 2355.89 | V48: 57.47 | W48: Yes | X48: 3.1 | Y48: No | Z48: 0
A49: EDU01426 | B49: 26-06-2023 | C49: Extramarks | D49: Test Preparation | E49: GRE Verbal+Quant | F49: Ahmedabad | G49: Gujarat | H49: Tier 1 | I49: Other | J49: 13-17 | K49: Word of Mouth | L49: Net Banking | M49: Desktop | N49: 11999 | O49: 10 | P49: 1199.9 | Q49: 10799.1 | R49: 1943.84 | S49: 8855.26 | T49: 4140.28 | U49: 4714.98 | V49: 53.24 | W49: Yes | Y49: No | Z49: 0
A50: EDU02418 | B50: 21-12-2024 | C50: Meritnation | D50: Professional Upskilling | E50: HR Management | F50: Mumbai | G50: Maharashtra | H50: Tier 1 | I50: Male | J50: 45+ | K50: School/College Partnership | L50: Debit Card | M50: Desktop | N50: 8999 | O50: 0 | P50: 0 | Q50: 8999 | R50: 1619.82 | S50: 7379.18 | T50: 3259.12 | U50: 4120.06 | V50: 55.83 | W50: Yes | X50: 4.5 | Y50: No | Z50: 0
A51: EDU02069 | B51: 11-09-2024 | C51: Scaler | D51: Language Learning | E51: IELTS Preparation | F51: NOIDA | G51: Delhi NCR | H51: Tier 1 | I51: Male | J51: 13-17 | K51: Email Campaign | L51: Net Banking | M51: Desktop | N51: 8999 | O51: 0 | P51: 0 | Q51: 8999 | R51: 1619.82 | S51: 7379.18 | T51: 2457.09 | U51: 4922.09 | V51: 66.7 | W51: Yes | X51: 3.8 | Y51: No | Z51: 0
A52: EDU02322 | B52: 16-09-2023 | C52: Physics Wallah | D52: Creative Arts | E52: UI/UX Design | F52: Chennai | G52: Tamil Nadu | H52: Tier 1 | I52: Male | J52: 18-24 | K52: Google Ads | L52: Credit Card | M52: Mobile | N52: 14999 | O52: 15 | P52: 2249.85 | Q52: 12749.15 | R52: 2294.85 | S52: 10454.3 | T52: 3767.51 | U52: 6686.79 | V52: 63.96 | W52: No | Y52: No | Z52: 0
A53: EDU01252 | B53: 01-04-2024 | C53: Meritnation | D53: Competitive Exams | E53: UPSC GS Foundation | F53: New Delhi | G53: Delhi NCR | H53: Tier 1 | I53: Other | J53: 45+ | K53: Instagram | L53: EMI | M53: Desktop | N53: 18999 | O53: 30 | P53: 5699.7 | Q53: 13299.3 | R53: 2393.87 | S53: 10905.43 | T53: 3801 | U53: 7104.43 | V53: 65.15 | W53: No | Y53: No | Z53: 0
A54: EDU00064 | B54: 15-10-2024 | C54: BYJU'S | D54: K-12 Academics | E54: Class 11-12 PCB | F54: Hyderabad | G54: Telangana | H54: Tier 1 | I54: Male | J54: 25-34 | K54: Direct/Organic | L54: UPI | M54: Mobile | N54: 8499 | O54: 20 | P54: 1699.8 | Q54: 6799.2 | R54: 1223.86 | S54: 5575.34 | T54: 2054.91 | U54: 3520.43 | V54: 63.14 | W54: Yes | X54: 3.6 | Y54: No | Z54: 0
A55: EDU01716 | B55: 05-11-2023 | C55: Leverage Edu | D55: Competitive Exams | E55: NEET Complete Course | F55: Nagpur | G55: Maharashtra | H55: Tier 2 | I55: Male | J55: 35-44 | K55: YouTube | L55: UPI | M55: Mobile | N55: 22999 | O55: 15 | P55: 3449.85 | Q55: 19549.15 | R55: 3518.85 | S55: 16030.3 | T55: 7740.39 | U55: 8289.91 | V55: 51.71 | W55: Yes | X55: 4.5 | Y55: No | Z55: 0
A56: EDU00859 | B56: 09-07-2024 | C56: Extramarks | D56: Language Learning | E56: IELTS Preparation | F56: Jodhpur | G56: Rajasthan | H56: Tier 3 | I56: Other | J56: 35-44 | K56: YouTube | L56: Debit Card | M56: Desktop | N56: 8999 | O56: 0 | P56: 0 | Q56: 8999 | R56: 1619.82 | S56: 7379.18 | T56: 3525.06 | U56: 3854.12 | V56: 52.23 | W56: Yes | X56: 3.3 | Y56: No | Z56: 0
A57: EDU00948 | B57: 11-07-2024 | C57: WhiteHat Jr | D57: Higher Education | E57: MBA Finance Prep | F57: Madurai | G57: Tamil Nadu | H57: Tier 3 | I57: Other | J57: 35-44 | K57: School/College Partnership | L57: Debit Card | M57: Mobile | N57: 11999 | O57: 40 | P57: 4799.6 | Q57: 7199.4 | R57: 1295.89 | S57: 5903.51 | T57: 3463.78 | U57: 2439.73 | V57: 41.33 | W57: Yes | X57: 3.3 | Y57: No | Z57: 0
A58: EDU02145 | B58: 03-04-2023 | C58: Scaler | D58: Higher Education | E58: MBA Finance Prep | F58: Madurai | G58: Tamil Nadu | H58: Tier 3 | I58: Female | J58: 45+ | K58: School/College Partnership | L58: Net Banking | M58: Tablet | N58: 11999 | O58: 0 | P58: 0 | Q58: 11999 | R58: 2159.82 | S58: 9839.18 | T58: 4296.21 | U58: 5542.97 | V58: 56.34 | W58: No | Y58: No | Z58: 0
A59: EDU00357 | B59: 15-09-2023 | C59: Leverage Edu | D59: Test Preparation | E59: SAT Complete Prep | F59: Pune | G59: Maharashtra | H59: Tier 1 | I59: Other | J59: 45+ | K59: Word of Mouth | L59: Wallet | M59: Mobile | N59: 12999 | O59: 40 | P59: 5199.6 | Q59: 7799.4 | R59: 1403.89 | S59: 6395.51 | T59: 3096.5 | U59: 3299.01 | V59: 51.58 | W59: No | Y59: No | Z59: 0
A60: EDU00271 | B60: 04-11-2024 | C60: Extramarks | D60: Coding & Tech | E60: Python for Beginners | F60: Chennai | G60: Tamil Nadu | H60: Tier 1 | I60: Female | J60: 13-17 | K60: YouTube | L60: Wallet | M60: Desktop | N60: 7999 | O60: 5 | P60: 399.95 | Q60: 7599.05 | R60: 1367.83 | S60: 6231.22 | T60: 2645.48 | U60: 3585.74 | V60: 57.54 | W60: Yes | X60: 4.5 | Y60: No | Z60: 0
A61: EDU02112 | B61: 23-06-2023 | C61: Scaler | D61: Coding & Tech | E61: Full Stack Development | F61: Ahmedabad | G61: Gujarat | H61: Tier 1 | I61: Male | J61: 35-44 | K61: School/College Partnership | L61: Wallet | M61: Mobile | N61: 29999 | O61: 40 | P61: 11999.6 | Q61: 17999.4 | R61: 3239.89 | S61: 14759.51 | T61: 8037.87 | U61: 6721.64 | V61: 45.54 | W61: Yes | X61: 3.6 | Y61: No | Z61: 0
A62: EDU01938 | B62: 07-12-2024 | C62: Physics Wallah | D62: Language Learning | E62: IELTS Preparation | F62: Faridabad | G62: Delhi NCR | H62: Tier 2 | I62: Male | J62: 25-34 | K62: Google Ads | L62: Wallet | M62: Mobile | N62: 8999 | O62: 50 | P62: 4499.5 | Q62: 4499.5 | R62: 809.91 | S62: 3689.59 | T62: 1907.33 | U62: 1782.26 | V62: 48.31 | W62: No | Y62: No | Z62: 1
A63: EDU00807 | B63: 11-02-2024 | C63: Toppr | D63: Higher Education | E63: BBA Business Basics | F63: Hyderabad | G63: Telangana | H63: Tier 1 | I63: Other | J63: 13-17 | K63: Direct/Organic | L63: Wallet | M63: Desktop | N63: 7499 | O63: 50 | P63: 3749.5 | Q63: 3749.5 | R63: 674.91 | S63: 3074.59 | T63: 1257.82 | U63: 1816.77 | V63: 59.09 | W63: Yes | X63: 3.7 | Y63: No | Z63: 0
A64: EDU00504 | B64: 07-07-2024 | C64: Unacademy | D64: Higher Education | E64: B.Tech CSE Support | F64: Madurai | G64: Tamil Nadu | H64: Tier 3 | I64: Female | J64: 13-17 | K64: Instagram | L64: Net Banking | M64: Desktop | N64: 9999 | O64: 20 | P64: 1999.8 | Q64: 7999.2 | R64: 1439.86 | S64: 6559.34 | T64: 2560.13 | U64: 3999.21 | V64: 60.97 | W64: No | Y64: Yes | Z64: 1
A65: EDU00122 | B65: 25-04-2024 | C65: Doubtnut | D65: Coding & Tech | E65: Data Science Masters | F65: Madurai | G65: Tamil Nadu | H65: Tier 3 | I65: Female | J65: 35-44 | K65: Direct/Organic | L65: UPI | M65: Mobile | N65: 34999 | O65: 30 | P65: 10499.7 | Q65: 24499.3 | R65: 4409.87 | S65: 20089.43 | T65: 7641.14 | U65: 12448.29 | V65: 61.96 | W65: Yes | X65: 3.9 | Y65: No | Z65: 0
A66: EDU00197 | B66: 15-08-2023 | C66: Toppr | D66: Coding & Tech | E66: Python for Beginners | F66: Coimbatore | G66: Tamil Nadu | H66: Tier 2 | I66: Male | J66: 35-44 | K66: Direct/Organic | L66: UPI | M66: Desktop | N66: 7999 | O66: 25 | P66: 1999.75 | Q66: 5999.25 | R66: 1079.87 | S66: 4919.38 | T66: 1713.33 | U66: 3206.05 | V66: 65.17 | W66: No | Y66: No | Z66: 0
A67: EDU01654 | B67: 03-11-2023 | C67: Scaler | D67: Professional Upskilling | E67: Financial Modelling | F67: Kolkata | G67: West Bengal | H67: Tier 1 | I67: Other | J67: 25-34 | K67: WhatsApp | L67: Credit Card | M67: Tablet | N67: 15999 | O67: 0 | P67: 0 | Q67: 15999 | R67: 2879.82 | S67: 13119.18 | T67: 4948.23 | U67: 8170.95 | V67: 62.28 | W67: Yes | X67: 4.5 | Y67: No | Z67: 0
A68: EDU01140 | B68: 08-12-2023 | C68: BYJU'S | D68: Competitive Exams | E68: GATE CS Complete | F68: Surat | G68: Gujarat | H68: Tier 2 | I68: Other | J68: 18-24 | K68: Instagram | L68: EMI | M68: Desktop | N68: 12999 | O68: 0 | P68: 0 | Q68: 12999 | R68: 2339.82 | S68: 10659.18 | T68: 3905.05 | U68: 6754.13 | V68: 63.36 | W68: No | Y68: No | Z68: 3
A69: EDU01344 | B69: 18-04-2024 | C69: Great Learning | D69: Higher Education | E69: BBA Business Basics | F69: Nagpur | G69: Maharashtra | H69: Tier 2 | I69: Other | J69: 13-17 | K69: Instagram | L69: Net Banking | M69: Mobile | N69: 7499 | O69: 0 | P69: 0 | Q69: 7499 | R69: 1349.82 | S69: 6149.18 | T69: 2922.4 | U69: 3226.78 | V69: 52.47 | W69: Yes | X69: 3.8 | Y69: No | Z69: 1
A70: EDU00588 | B70: 12-08-2024 | C70: Extramarks | D70: Coding & Tech | E70: Full Stack Development | F70: New Delhi | G70: Delhi NCR | H70: Tier 1 | I70: Other | J70: 18-24 | K70: Email Campaign | L70: Credit Card | M70: Mobile | N70: 29999 | O70: 30 | P70: 8999.7 | Q70: 20999.3 | R70: 3779.87 | S70: 17219.43 | T70: 5854.24 | U70: 11365.19 | V70: 66 | W70: Yes | X70: 3.7 | Y70: No | Z70: 0
A71: EDU00733 | B71: 14-05-2023 | C71: Physics Wallah | D71: Creative Arts | E71: UI/UX Design | F71: Pune | G71: Maharashtra | H71: Tier 1 | I71: Other | J71: 18-24 | K71: Google Ads | L71: EMI | M71: Tablet | N71: 14999 | O71: 10 | P71: 1499.9 | Q71: 13499.1 | R71: 2429.84 | S71: 11069.26 | T71: 3872 | U71: 7197.26 | V71: 65.02 | W71: Yes | Y71: No | Z71: 0
A72: EDU01607 | B72: 20-07-2023 | C72: Vedantu | D72: Language Learning | E72: Business English | F72: Noida | G72: Delhi NCR | H72: Tier 1 | I72: Male | J72: 35-44 | K72: School/College Partnership | L72: Credit Card | M72: Tablet | N72: 6999 | O72: 0 | P72: 0 | Q72: 6999 | R72: 1259.82 | S72: 5739.18 | T72: 2961.7 | U72: 2777.48 | V72: 48.4 | W72: No | Y72: No | Z72: 1
A73: EDU01390 | B73: 26-10-2024 | C73: upGrad | D73: K-12 Academics | E73: Class 11-12 PCB | F73: Mysuru | G73: Karnataka | H73: Tier 2 | I73: Other | J73: 45+ | K73: Instagram | L73: EMI | M73: Mobile | N73: 8499 | O73: 20 | P73: 1699.8 | Q73: 6799.2 | R73: 1223.86 | S73: 5575.34 | T73: 2840.94 | U73: 2734.4 | V73: 49.04 | W73: Yes | X73: 4.2 | Y73: No | Z73: 0
A74: EDU01076 | B74: 14-05-2023 | C74: Simplilearn | D74: K-12 Academics | E74: Class 8-10 Science Pack | F74: Vadodara | G74: Gujarat | H74: Tier 3 | I74: Female | J74: 35-44 | K74: WhatsApp | L74: Credit Card | M74: Desktop | N74: 4999 | O74: 10 | P74: 499.9 | Q74: 4499.1 | R74: 809.84 | S74: 3689.26 | T74: 1459.22 | U74: 2230.04 | V74: 60.45 | W74: No | Y74: Yes | Z74: 0
A75: EDU01766 | B75: 19-10-2024 | C75: Physics Wallah | D75: K-12 Academics | E75: Class 8-10 Science Pack | F75: MANGALURU | G75: Karnataka | H75: Tier 3 | I75: Other | J75: 25-34 | K75: Direct/Organic | L75: Credit Card | M75: Mobile | N75: 4999 | O75: 0 | P75: 0 | Q75: 4999 | R75: 899.82 | S75: 4099.18 | T75: 1644.12 | U75: 2455.06 | V75: 59.89 | W75: No | Y75: No | Z75: 0
A76: EDU00242 | B76: 31-10-2024 | C76: Toppr | D76: K-12 Academics | E76: Foundation Course | F76: Nagpur | G76: Maharashtra | H76: Tier 2 | I76: Female | J76: 13-17 | K76: Word of Mouth | L76: Credit Card | M76: Tablet | N76: 6999 | O76: 10 | P76: 699.9 | Q76: 6299.1 | R76: 1133.84 | S76: 5165.26 | T76: 2396.43 | U76: 2768.83 | V76: 53.6 | W76: Yes | X76: 3.9 | Y76: No | Z76: 0
A77: EDU00279 | B77: 08-03-2023 | C77: WhiteHat Jr | D77: Test Preparation | E77: SAT Complete Prep | F77: Pune | G77: Maharashtra | H77: Tier 1 | I77: Female | J77: 13-17 | K77: Google Ads | L77: Net Banking | M77: Mobile | N77: 12999 | O77: 0 | P77: 0 | Q77: 12999 | R77: 2339.82 | S77: 10659.18 | T77: 4236.8 | U77: 6422.38 | V77: 60.25 | W77: No | Y77: No | Z77: 1
A78: EDU01932 | B78: 04-01-2023 | C78: Vedantu | D78: Test Preparation | E78: GMAT Focus Edition | F78: Hyderabad | G78: Telangana | H78: Tier 1 | I78: Female | J78: 13-17 | K78: WhatsApp | L78: UPI | M78: Tablet | N78: 16999 | O78: 0 | P78: 0 | Q78: 16999 | R78: 3059.82 | S78: 13939.18 | T78: 5518.11 | U78: 8421.07 | V78: 60.41 | W78: No | Y78: No | Z78: 1
A79: EDU02287 | B79: 26-10-2023 | C79: Doubtnut | D79: K-12 Academics | E79: Foundation Course | F79: Jaipur | G79: Rajasthan | H79: Tier 2 | I79: Other | J79: 18-24 | K79: Instagram | L79: Debit Card | M79: Desktop | N79: 6999 | O79: 0 | P79: 0 | Q79: 6999 | R79: 1259.82 | S79: 5739.18 | T79: 2768.27 | U79: 2970.91 | V79: 51.77 | W79: Yes | X79: 3 | Y79: No | Z79: 1
A80: EDU02382 | B80: 25-09-2024 | C80: BYJU'S | D80: Language Learning | E80: English Communication | F80: Jodhpur | G80: Rajasthan | H80: Tier 3 | I80: Male | J80: 18-24 | K80: Google Ads | L80: Credit Card | M80: Tablet | N80: 4999 | O80: 0 | P80: 0 | Q80: 4999 | R80: 899.82 | S80: 4099.18 | T80: 1718.76 | U80: 2380.42 | V80: 58.07 | W80: Yes | X80: 4.4 | Y80: No | Z80: 0
A81: EDU02054 | B81: 08-06-2023 | C81: upGrad | D81: K-12 Academics | E81: Class 8-10 Science Pack | F81: Ghaziabad | G81: Delhi NCR | H81: Tier 2 | I81: Male | J81: 35-44 | K81: WhatsApp | L81: Credit Card | M81: Tablet | N81: 4999 | O81: 0 | P81: 0 | Q81: 4999 | R81: 899.82 | S81: 4099.18 | T81: 1761.8 | U81: 2337.38 | V81: 57.02 | W81: No | Y81: No | Z81: 0
A82: EDU01839 | B82: 29-03-2024 | C82: upGrad | D82: Higher Education | E82: BBA Business Basics | F82: Jodhpur | G82: Rajasthan | H82: Tier 3 | I82: Female | J82: 18-24 | K82: Word of Mouth | L82: Net Banking | M82: Mobile | N82: 7499 | O82: 15 | P82: 1124.85 | Q82: 6374.15 | R82: 1147.35 | S82: 5226.8 | T82: 2015.98 | U82: 3210.82 | V82: 61.43 | W82: No | Y82: Yes | Z82: 1
A83: EDU00218 | B83: 29-12-2024 | C83: Vedantu | D83: Creative Arts | E83: Video Editing Basics | F83: Surat | G83: Gujarat | H83: Tier 2 | I83: Female | J83: 35-44 | K83: Email Campaign | L83: Debit Card | M83: Mobile | N83: 6999 | O83: 10 | P83: 699.9 | Q83: 6299.1 | R83: 1133.84 | S83: 5165.26 | T83: 2561.92 | U83: 2603.34 | V83: 50.4 | W83: Yes | Y83: Yes | Z83: 0
A84: EDU01537 | B84: 29-01-2023 | C84: Embibe | D84: Competitive Exams | E84: NEET Complete Course | F84: Vadodara | G84: Gujarat | H84: Tier 3 | I84: Male | J84: 45+ | K84: Word of Mouth | L84: Credit Card | M84: Mobile | N84: 22999 | O84: 10 | P84: 2299.9 | Q84: 20699.1 | R84: 3725.84 | S84: 16973.26 | T84: 7435.79 | U84: 9537.47 | V84: 56.19 | W84: Yes | X84: 2.6 | Y84: No | Z84: 1
A85: EDU01443 | B85: 30-10-2023 | C85: Vedantu | D85: Coding & Tech | E85: AI/ML Fundamentals | F85: Jodhpur | G85: Rajasthan | H85: Tier 3 | I85: Female | J85: 18-24 | K85: Email Campaign | L85: Wallet | M85: Tablet | N85: 24999 | O85: 10 | P85: 2499.9 | Q85: 22499.1 | R85: 4049.84 | S85: 18449.26 | T85: 6447.62 | U85: 12001.64 | V85: 65.05 | W85: Yes | X85: 3.9 | Y85: No | Z85: 0
A86: EDU01941 | B86: 23-10-2023 | C86: Extramarks | D86: Coding & Tech | E86: Python for Beginners | F86: Kolkata | G86: West Bengal | H86: Tier 1 | I86: Male | J86: 35-44 | K86: Instagram | L86: UPI | M86: Desktop | N86: 7999 | O86: 5 | P86: 399.95 | Q86: 7599.05 | R86: 1367.83 | S86: 6231.22 | T86: 2002.62 | U86: 4228.6 | V86: 67.86 | W86: Yes | Y86: No | Z86: 0
A87: EDU01498 | B87: 25-10-2024 | C87: Toppr | D87: Language Learning | E87: IELTS Preparation | F87: Ghaziabad | G87: Delhi NCR | H87: Tier 2 | I87: Other | J87: 13-17 | K87: School/College Partnership | L87: Debit Card | M87: Desktop | N87: 8999 | O87: 30 | P87: 2699.7 | Q87: 6299.3 | R87: 1133.87 | S87: 5165.43 | T87: 2326.66 | U87: 2838.77 | V87: 54.96 | W87: Yes | X87: 4.1 | Y87: No | Z87: 0
A88: EDU00464 | B88: 27-10-2023 | C88: upGrad | D88: Professional Upskilling | E88: HR Management | F88: Surat | G88: Gujarat | H88: Tier 2 | I88: Female | J88: 35-44 | K88: Instagram | L88: Credit Card | M88: Mobile | N88: 8999 | O88: 25 | P88: 2249.75 | Q88: 6749.25 | R88: 1214.87 | S88: 5534.38 | T88: 2300.11 | U88: 3234.27 | V88: 58.44 | W88: No | Y88: Yes | Z88: 1
A89: EDU01693 | B89: 13-05-2024 | C89: Scaler | D89: K-12 Academics | E89: Class 11-12 PCB | F89: New Delhi | G89: Delhi NCR | H89: Tier 1 | I89: Female | J89: 35-44 | K89: Direct/Organic | L89: UPI | M89: Desktop | N89: 8499 | O89: 15 | P89: 1274.85 | Q89: 7224.15 | R89: 1300.35 | S89: 5923.8 | T89: 2318.67 | U89: 3605.13 | V89: 60.86 | W89: Yes | X89: 3.9 | Y89: No | Z89: 0
A90: EDU00187 | B90: 06-06-2023 | C90: Meritnation | D90: Language Learning | E90: Business English | F90: Madurai | G90: Tamil Nadu | H90: Tier 3 | I90: Other | J90: 18-24 | K90: Word of Mouth | L90: Wallet | M90: Tablet | N90: 6999 | O90: 50 | P90: 3499.5 | Q90: 3499.5 | R90: 629.91 | S90: 2869.59 | T90: 1830.05 | U90: 1039.54 | V90: 36.23 | W90: No | Y90: No | Z90: 1
A91: EDU00749 | B91: 06-11-2024 | C91: BYJU'S | D91: Test Preparation | E91: SAT Complete Prep | F91: Warangal | G91: Telangana | H91: Tier 3 | I91: Female | J91: 35-44 | K91: YouTube | L91: UPI | M91: Mobile | N91: 12999 | O91: 10 | P91: 1299.9 | Q91: 11699.1 | R91: 2105.84 | S91: 9593.26 | T91: 4011.27 | U91: 5581.99 | V91: 58.19 | W91: Yes | X91: 2.7 | Y91: No | Z91: 0
A92: EDU00537 | B92: 07-02-2024 | C92: Doubtnut | D92: Test Preparation | E92: SAT Complete Prep | F92: Mumbai | G92: Maharashtra | H92: Tier 1 | I92: Other | J92: 13-17 | K92: Direct/Organic | L92: Wallet | M92: Desktop | N92: 12999 | O92: 0 | P92: 0 | Q92: 12999 | R92: 2339.82 | S92: 10659.18 | T92: 3286.58 | U92: 7372.6 | V92: 69.17 | W92: Yes | X92: 3.9 | Y92: No | Z92: 0
A93: EDU01959 | B93: 12-06-2023 | C93: Extramarks | D93: Competitive Exams | E93: GATE CS Complete | F93: Coimbatore | G93: Tamil Nadu | H93: Tier 2 | I93: Other | J93: 25-34 | K93: YouTube | L93: Credit Card | M93: Desktop | N93: 12999 | O93: 50 | P93: 6499.5 | Q93: 6499.5 | R93: 1169.91 | S93: 5329.59 | T93: 3156.68 | U93: 2172.91 | V93: 40.77 | W93: No | Y93: No | Z93: 0
A94: EDU02071 | B94: 21-02-2023 | C94: Unacademy | D94: Professional Upskilling | E94: Data Analytics Bootcamp | F94: BENGALURU | G94: Karnataka | H94: Tier 1 | I94: Male | J94: 45+ | K94: School/College Partnership | L94: UPI | M94: Mobile | N94: 19999 | O94: 50 | P94: 9999.5 | Q94: 9999.5 | R94: 1799.91 | S94: 8199.59 | T94: 4033.97 | U94: 4165.62 | V94: 50.8 | W94: Yes | X94: 4.2 | Y94: No | Z94: 0
A95: EDU01776 | B95: 26-05-2023 | C95: upGrad | D95: Coding & Tech | E95: Full Stack Development | F95: Hyderabad | G95: Telangana | H95: Tier 1 | I95: Male | J95: 25-34 | K95: School/College Partnership | L95: Credit Card | M95: Mobile | N95: 29999 | O95: 5 | P95: 1499.95 | Q95: 28499.05 | R95: 5129.83 | S95: 23369.22 | T95: 8074.25 | U95: 15294.97 | V95: 65.45 | W95: Yes | Y95: No | Z95: 0
A96: EDU00978 | B96: 07-09-2024 | C96: Simplilearn | D96: K-12 Academics | E96: Class 11-12 PCM | F96: Kolkata | G96: West Bengal | H96: Tier 1 | I96: Other | J96: 25-34 | K96: Instagram | L96: Credit Card | M96: Desktop | N96: 8999 | O96: 10 | P96: 899.9 | Q96: 8099.1 | R96: 1457.84 | S96: 6641.26 | T96: 2188.59 | U96: 4452.67 | V96: 67.05 | W96: No | Y96: No | Z96: 0
A97: EDU00515 | B97: 18-02-2024 | C97: Extramarks | D97: Coding & Tech | E97: Python for Beginners | F97: Ghaziabad | G97: Delhi NCR | H97: Tier 2 | I97: Male | J97: 45+ | K97: Email Campaign | L97: UPI | M97: Desktop | N97: 7999 | O97: 10 | P97: 799.9 | Q97: 7199.1 | R97: 1295.84 | S97: 5903.26 | T97: 2230.62 | U97: 3672.64 | V97: 62.21 | W97: No | Y97: No | Z97: 1
A98: EDU02158 | B98: 14-01-2023 | C98: Great Learning | D98: Professional Upskilling | E98: Data Analytics Bootcamp | F98: Hyderabad | G98: Telangana | H98: Tier 1 | I98: Male | J98: 13-17 | K98: Email Campaign | L98: Debit Card | M98: Desktop | N98: 19999 | O98: 0 | P98: 0 | Q98: 19999 | R98: 3599.82 | S98: 16399.18 | T98: 5756.67 | U98: 10642.51 | V98: 64.9 | W98: No | Y98: No | Z98: 1
A99: EDU00171 | B99: 20-08-2024 | C99: Vedantu | D99: Creative Arts | E99: Graphic Design Pro | F99: HYDERABAD | G99: Telangana | H99: Tier 1 | I99: Other | J99: 13-17 | K99: Word of Mouth | L99: UPI | M99: Desktop | N99: 9999 | O99: 40 | P99: 3999.6 | Q99: 5999.4 | R99: 1079.89 | S99: 4919.51 | T99: 2631 | U99: 2288.51 | V99: 46.52 | W99: Yes | Y99: No | Z99: 0
A100: EDU00984 | B100: 16-03-2024 | C100: upGrad | D100: Higher Education | E100: B.Tech CSE Support | F100: Jaipur | G100: Rajasthan | H100: Tier 2 | I100: Female | J100: 25-34 | K100: Word of Mouth | L100: Debit Card | M100: Desktop | N100: 9999 | O100: 20 | P100: 1999.8 | Q100: 7999.2 | R100: 1439.86 | S100: 6559.34 | T100: 2882.03 | U100: 3677.31 | V100: 56.06 | W100: Yes | X100: 3.7 | Y100: No | Z100: 2
...

Sheet Working Data
A1: Enrollment_ID | B1: Enrollment_Date | C1: Company | D1: Course_Category | E1: Course_Name | F1: City | G1: State | H1: City_Tier | I1: Gender | J1: Age_Group | K1: Referral_Source | L1: Payment_Mode | M1: Device_Type | N1: Original_Price_INR | O1: Discount_% | P1: Discount_Amount_INR | Q1: Final_Price_INR | R1: GST_Amount_INR | S1: Net_Revenue_INR | T1: Platform_Cost_INR | U1: Gross_Profit_INR | V1: Gross_Margin_% | W1: Course_Completed | X1: Student_Rating | Y1: Refund_Issued | Z1: Support_Tickets_Raised | AA1: Cleaned_City | AB1: Cleaned_Company | AC1: Discount_Category | AD1: Profit_Flag | AE1: Month_Year | AF1: Year | AG1: Quarter
A2: EDU00524 | B2: 08-11-2023 | C2: Embibe | D2: Coding & Tech | E2: Python for Beginners | F2: Jodhpur | G2: Rajasthan | H2: Tier 3 | I2: Male | J2: 25-34 | K2: Google Ads | L2: Debit Card | M2: Desktop | N2: 7999 | O2: 40 | P2: 3199.6 | Q2: 4799.4 | R2: 863.89 | S2: 3935.51 | T2: 2203.97 | U2: 1731.54 | V2: 44 | W2: Yes | X2: 4.6 | Y2: No | Z2: 1 | AA2: =TRIM(PROPER(F2)) -> Jodhpur | AB2: =TRIM(PROPER(C2)) -> Embibe | AC2: =IF(O2=0,"No Discount",IF(O2<=15,"Low (1-15%)",IF(O2<=30,"Medium (16-30%)","High (>30%)"))) -> High (>30%) | AD2: =IF(V2<0,"Loss Making",IF(V2<20,"Low Margin","Healthy Margin")) -> Healthy Margin | AE2: =TEXT(DATE(VALUE(RIGHT(B2,4)),VALUE(MID(B2,4,2)),VALUE(LEFT(B2,2))),"MMM-YYYY") -> Nov-2023 | AF2: =VALUE(RIGHT(B2,4)) -> 2023 | AG2: =CHOOSE(ROUNDUP(VALUE(MID(B2,4,2))/3,0),"Q1","Q2","Q3","Q4") -> Q4
A3: EDU00061 | B3: 05-12-2023 | C3: Meritnation | D3: Test Preparation | E3: GRE Verbal+Quant | F3: Mangaluru | G3: Karnataka | H3: Tier 3 | I3: Male | J3: 25-34 | K3: Instagram | L3: Wallet | M3: Tablet | N3: 11999 | O3: 10 | P3: 1199.9 | Q3: 10799.1 | R3: 1943.84 | S3: 8855.26 | T3: 3836.62 | U3: 5018.64 | V3: 56.67 | W3: Yes | X3: 4 | Y3: No | Z3: 0 | AA3: =TRIM(PROPER(F3)) -> Mangaluru | AB3: =TRIM(PROPER(C3)) -> Meritnation | AC3: =IF(O3=0,"No Discount",IF(O3<=15,"Low (1-15%)",IF(O3<=30,"Medium (16-30%)","High (>30%)"))) -> Low (1-15%) | AD3: =IF(V3<0,"Loss Making",IF(V3<20,"Low Margin","Healthy Margin")) -> Healthy Margin | AE3: =TEXT(DATE(VALUE(RIGHT(B3,4)),VALUE(MID(B3,4,2)),VALUE(LEFT(B3,2))),"MMM-YYYY") -> Dec-2023 | AF3: =VALUE(RIGHT(B3,4)) -> 2023 | AG3: =CHOOSE(ROUNDUP(VALUE(MID(B3,4,2))/3,0),"Q1","Q2","Q3","Q4") -> Q4
A4: EDU00457 | B4: 15-12-2024 | C4: Embibe | D4: Higher Education | E4: MBA Finance Prep | F4: Ghaziabad | G4: Delhi NCR | H4: Tier 2 | I4: Other | J4: 18-24 | K4: Word of Mouth | L4: Credit Card | M4: Mobile | N4: 11999 | O4: 25 | P4: 2999.75 | Q4: 8999.25 | R4: 1619.87 | S4: 7379.38 | T4: 3191.83 | U4: 4187.55 | V4: 56.75 | W4: Yes | X4: 3.6 | Y4: No | Z4: 0 | AA4: =TRIM(PROPER(F4)) -> Ghaziabad | AB4: =TRIM(PROPER(C4)) -> Embibe | AC4: =IF(O4=0,"No Discount",IF(O4<=15,"Low (1-15%)",IF(O4<=30,"Medium (16-30%)","High (>30%)"))) -> Medium (16-30%) | AD4: =IF(V4<0,"Loss Making",IF(V4<20,"Low Margin","Healthy Margin")) -> Healthy Margin | AE4: =TEXT(DATE(VALUE(RIGHT(B4,4)),VALUE(MID(B4,4,2)),VALUE(LEFT(B4,2))),"MMM-YYYY") -> Dec-2024 | AF4: =VALUE(RIGHT(B4,4)) -> 2024 | AG4: =CHOOSE(ROUNDUP(VALUE(MID(B4,4,2))/3,0),"Q1","Q2","Q3","Q4") -> Q4
A5: EDU01052 | B5: 29-08-2024 | C5: Toppr | D5: Test Preparation | E5: SAT Complete Prep | F5: Ahmedabad | G5: Gujarat | H5: Tier 1 | I5: Male | J5: 13-17 | K5: YouTube | L5: Credit Card | M5: Mobile | N5: 12999 | O5: 0 | P5: 0 | Q5: 12999 | R5: 2339.82 | S5: 10659.18 | T5: 3738.71 | U5: 6920.47 | V5: 64.92 | W5: Yes | X5: 3.7 | Y5: No | Z5: 1 | AA5: =TRIM(PROPER(F5)) -> Ahmedabad | AB5: =TRIM(PROPER(C5)) -> Toppr | AC5: =IF(O5=0,"No Discount",IF(O5<=15,"Low (1-15%)",IF(O5<=30,"Medium (16-30%)","High (>30%)"))) -> No Discount | AD5: =IF(V5<0,"Loss Making",IF(V5<20,"Low Margin","Healthy Margin")) -> Healthy Margin | AE5: =TEXT(DATE(VALUE(RIGHT(B5,4)),VALUE(MID(B5,4,2)),VALUE(LEFT(B5,2))),"MMM-YYYY") -> Aug-2024 | AF5: =VALUE(RIGHT(B5,4)) -> 2024 | AG5: =CHOOSE(ROUNDUP(VALUE(MID(B5,4,2))/3,0),"Q1","Q2","Q3","Q4") -> Q3
A6: EDU00891 | B6: 09-02-2023 | C6: Vedantu | D6: Test Preparation | E6: SAT Complete Prep | F6: Kolkata | G6: West Bengal | H6: Tier 1 | I6: Other | J6: 35-44 | K6: Google Ads | L6: Debit Card | M6: Desktop | N6: 12999 | O6: 40 | P6: 5199.6 | Q6: 7799.4 | R6: 1403.89 | S6: 6395.51 | T6: 3376.69 | U6: 3018.82 | V6: 47.2 | W6: Yes | X6: 3.6 | Y6: No | Z6: 0 | AA6: =TRIM(PROPER(F6)) -> Kolkata | AB6: =TRIM(PROPER(C6)) -> Vedantu | AC6: =IF(O6=0,"No Discount",IF(O6<=15,"Low (1-15%)",IF(O6<=30,"Medium (16-30%)","High (>30%)"))) -> High (>30%) | AD6: =IF(V6<0,"Loss Making",IF(V6<20,"Low Margin","Healthy Margin")) -> Healthy Margin | AE6: =TEXT(DATE(VALUE(RIGHT(B6,4)),VALUE(MID(B6,4,2)),VALUE(LEFT(B6,2))),"MMM-YYYY") -> Feb-2023 | AF6: =VALUE(RIGHT(B6,4)) -> 2023 | AG6: =CHOOSE(ROUNDUP(VALUE(MID(B6,4,2))/3,0),"Q1","Q2","Q3","Q4") -> Q1
A7: EDU01966 | B7: 12-01-2023 | C7: Toppr | D7: Professional Upskilling | E7: Digital Marketing Pro | F7: Gurugram | G7: Delhi NCR | H7: Tier 1 | I7: Female | J7: 25-34 | K7: WhatsApp | L7: EMI | M7: Mobile | N7: 12999 | O7: 0 | P7: 0 | Q7: 12999 | R7: 2339.82 | S7: 10659.18 | T7: 3264.37 | U7: 7394.81 | V7: 69.38 | W7: Yes | X7: 4.5 | Y7: No | Z7: 1 | AA7: =TRIM(PROPER(F7)) -> Gurugram | AB7: =TRIM(PROPER(C7)) -> Toppr | AC7: =IF(O7=0,"No Discount",IF(O7<=15,"Low (1-15%)",IF(O7<=30,"Medium (16-30%)","High (>30%)"))) -> No Discount | AD7: =IF(V7<0,"Loss Making",IF(V7<20,"Low Margin","Healthy Margin")) -> Healthy Margin | AE7: =TEXT(DATE(VALUE(RIGHT(B7,4)),VALUE(MID(B7,4,2)),VALUE(LEFT(B7,2))),"MMM-YYYY") -> Jan-2023 | AF7: =VALUE(RIGHT(B7,4)) -> 2023 | AG7: =CHOOSE(ROUNDUP(VALUE(MID(B7,4,2))/3,0),"Q1","Q2","Q3","Q4") -> Q1
A8: EDU00027 | B8: 03-11-2023 | C8: BYJU'S | D8: Higher Education | E8: MBA Finance Prep | F8: Vadodara | G8: Gujarat | H8: Tier 3 | I8: Male | J8: 25-34 | K8: School/College Partnership | L8: EMI | M8: Mobile | N8: 11999 | O8: 0 | P8: 0 | Q8: 11999 | R8: 2159.82 | S8: 9839.18 | T8: 4348.29 | U8: 5490.89 | V8: 55.81 | W8: No | Y8: No | Z8: 1 | AA8: =TRIM(PROPER(F8)) -> Vadodara | AB8: =TRIM(PROPER(C8)) -> Byju'S | AC8: =IF(O8=0,"No Discount",IF(O8<=15,"Low (1-15%)",IF(O8<=30,"Medium (16-30%)","High (>30%)"))) -> No Discount | AD8: =IF(V8<0,"Loss Making",IF(V8<20,"Low Margin","Healthy Margin")) -> Healthy Margin | AE8: =TEXT(DATE(VALUE(RIGHT(B8,4)),VALUE(MID(B8,4,2)),VALUE(LEFT(B8,2))),"MMM-YYYY") -> Nov-2023 | AF8: =VALUE(RIGHT(B8,4)) -> 2023 | AG8: =CHOOSE(ROUNDUP(VALUE(MID(B8,4,2))/3,0),"Q1","Q2","Q3","Q4") -> Q4
A9: EDU00427 | B9: 18-01-2024 | C9: upGrad | D9: Creative Arts | E9: Video Editing Basics | F9: Pune | G9: Maharashtra | H9: Tier 1 | I9: Female | J9: 35-44 | K9: Word of Mouth | L9: Debit Card | M9: Mobile | N9: 6999 | O9: 5 | P9: 349.95 | Q9: 6649.05 | R9: 1196.83 | S9: 5452.22 | T9: 2206.78 | U9: 3245.44 | V9: 59.53 | W9: Yes | X9: 2.9 | Y9: No | Z9: 2 | AA9: =TRIM(PROPER(F9)) -> Pune | AB9: =TRIM(PROPER(C9)) -> Upgrad | AC9: =IF(O9=0,"No Discount",IF(O9<=15,"Low (1-15%)",IF(O9<=30,"Medium (16-30%)","High (>30%)"))) -> Low (1-15%) | AD9: =IF(V9<0,"Loss Making",IF(V9<20,"Low Margin","Healthy Margin")) -> Healthy Margin | AE9: =TEXT(DATE(VALUE(RIGHT(B9,4)),VALUE(MID(B9,4,2)),VALUE(LEFT(B9,2))),"MMM-YYYY") -> Jan-2024 | AF9: =VALUE(RIGHT(B9,4)) -> 2024 | AG9: =CHOOSE(ROUNDUP(VALUE(MID(B9,4,2))/3,0),"Q1","Q2","Q3","Q4") -> Q1
A10: EDU01634 | B10: 16-01-2023 | C10: Physics Wallah | D10: Creative Arts | E10: UI/UX Design | F10: Warangal | G10: Telangana | H10: Tier 3 | I10: Male | J10: 35-44 | K10: Direct/Organic | L10: EMI | M10: Mobile | N10: 14999 | O10: 25 | P10: 3749.75 | Q10: 11249.25 | R10: 2024.87 | S10: 9224.38 | T10: 4357.82 | U10: 4866.56 | V10: 52.76 | W10: No | Y10: No | Z10: 1 | AA10: =TRIM(PROPER(F10)) -> Warangal | AB10: =TRIM(PROPER(C10)) -> Physics Wallah | AC10: =IF(O10=0,"No Discount",IF(O10<=15,"Low (1-15%)",IF(O10<=30,"Medium (16-30%)","High (>30%)"))) -> Medium (16-30%) | AD10: =IF(V10<0,"Loss Making",IF(V10<20,"Low Margin","Healthy Margin")) -> Healthy Margin | AE10: =TEXT(DATE(VALUE(RIGHT(B10,4)),VALUE(MID(B10,4,2)),VALUE(LEFT(B10,2))),"MMM-YYYY") -> Jan-2023 | AF10: =VALUE(RIGHT(B10,4)) -> 2023 | AG10: =CHOOSE(ROUNDUP(VALUE(MID(B10,4,2))/3,0),"Q1","Q2","Q3","Q4") -> Q1
A11: EDU00833 | B11: 03-11-2024 | C11: Vedantu | D11: Higher Education | E11: MBA Finance Prep | F11: Madurai | G11: Tamil Nadu | H11: Tier 3 | I11: Other | J11: 18-24 | K11: Instagram | L11: Credit Card | M11: Desktop | N11: 11999 | O11: 50 | P11: 5999.5 | Q11: 5999.5 | R11: 1079.91 | S11: 4919.59 | T11: 2534.61 | U11: 2384.98 | V11: 48.48 | W11: No | Y11: No | Z11: 0 | AA11: =TRIM(PROPER(F11)) -> Madurai | AB11: =TRIM(PROPER(C11)) -> Vedantu | AC11: =IF(O11=0,"No Discount",IF(O11<=15,"Low (1-15%)",IF(O11<=30,"Medium (16-30%)","High (>30%)"))) -> High (>30%) | AD11: =IF(V11<0,"Loss Making",IF(V11<20,"Low Margin","Healthy Margin")) -> Healthy Margin | AE11: =TEXT(DATE(VALUE(RIGHT(B11,4)),VALUE(MID(B11,4,2)),VALUE(LEFT(B11,2))),"MMM-YYYY") -> Nov-2024 | AF11: =VALUE(RIGHT(B11,4)) -> 2024 | AG11: =CHOOSE(ROUNDUP(VALUE(MID(B11,4,2))/3,0),"Q1","Q2","Q3","Q4") -> Q4
A12: EDU02161 | B12: 15-11-2023 | C12: Toppr | D12: Test Preparation | E12: SAT Complete Prep | F12: NOIDA | G12: Delhi NCR | H12: Tier 1 | I12: Male | J12: 18-24 | K12: Email Campaign | L12: UPI | M12: Mobile | N12: 12999 | O12: 40 | P12: 5199.6 | Q12: 7799.4 | R12: 1403.89 | S12: 6395.51 | T12: 2933.31 | U12: 3462.2 | V12: 54.13 | W12: No | Y12: Yes | Z12: 1 | AA12: =TRIM(PROPER(F12)) -> Noida | AB12: =TRIM(PROPER(C12)) -> Toppr | AC12: =IF(O12=0,"No Discount",IF(O12<=15,"Low (1-15%)",IF(O12<=30,"Medium (16-30%)","High (>30%)"))) -> High (>30%) | AD12: =IF(V12<0,"Loss Making",IF(V12<20,"Low Margin","Healthy Margin")) -> Healthy Margin | AE12: =TEXT(DATE(VALUE(RIGHT(B12,4)),VALUE(MID(B12,4,2)),VALUE(LEFT(B12,2))),"MMM-YYYY") -> Nov-2023 | AF12: =VALUE(RIGHT(B12,4)) -> 2023 | AG12: =CHOOSE(ROUNDUP(VALUE(MID(B12,4,2))/3,0),"Q1","Q2","Q3","Q4") -> Q4
A13: EDU01493 | B13: 19-02-2024 | C13: Embibe | D13: Higher Education | E13: B.Tech CSE Support | F13: Warangal | G13: Telangana | H13: Tier 3 | I13: Male | J13: 13-17 | K13: YouTube | L13: Credit Card | M13: Mobile | N13: 9999 | O13: 10 | P13: 999.9 | Q13: 8999.1 | R13: 1619.84 | S13: 7379.26 | T13: 3528.47 | U13: 3850.79 | V13: 52.18 | W13: No | Y13: No | Z13: 1 | AA13: =TRIM(PROPER(F13)) -> Warangal | AB13: =TRIM(PROPER(C13)) -> Embibe | AC13: =IF(O13=0,"No Discount",IF(O13<=15,"Low (1-15%)",IF(O13<=30,"Medium (16-30%)","High (>30%)"))) -> Low (1-15%) | AD13: =IF(V13<0,"Loss Making",IF(V13<20,"Low Margin","Healthy Margin")) -> Healthy Margin | AE13: =TEXT(DATE(VALUE(RIGHT(B13,4)),VALUE(MID(B13,4,2)),VALUE(LEFT(B13,2))),"MMM-YYYY") -> Feb-2024 | AF13: =VALUE(RIGHT(B13,4)) -> 2024 | AG13: =CHOOSE(ROUNDUP(VALUE(MID(B13,4,2))/3,0),"Q1","Q2","Q3","Q4") -> Q1
A14: EDU02280 | B14: 14-10-2023 | C14: Simplilearn | D14: Professional Upskilling | E14: Digital Marketing Pro | F14: Mysuru | G14: Karnataka | H14: Tier 2 | I14: Female | J14: 25-34 | K14: WhatsApp | L14: EMI | M14: Desktop | N14: 12999 | O14: 20 | P14: 2599.8 | Q14: 10399.2 | R14: 1871.86 | S14: 8527.34 | T14: 3512.35 | U14: 5014.99 | V14: 58.81 | W14: No | Y14: No | Z14: 1 | AA14: =TRIM(PROPER(F14)) -> Mysuru | AB14: =TRIM(PROPER(C14)) -> Simplilearn | AC14: =IF(O14=0,"No Discount",IF(O14<=15,"Low (1-15%)",IF(O14<=30,"Medium (16-30%)","High (>30%)"))) -> Medium (16-30%) | AD14: =IF(V14<0,"Loss Making",IF(V14<20,"Low Margin","Healthy Margin")) -> Healthy Margin | AE14: =TEXT(DATE(VALUE(RIGHT(B14,4)),VALUE(MID(B14,4,2)),VALUE(LEFT(B14,2))),"MMM-YYYY") -> Oct-2023 | AF14: =VALUE(RIGHT(B14,4)) -> 2023 | AG14: =CHOOSE(ROUNDUP(VALUE(MID(B14,4,2))/3,0),"Q1","Q2","Q3","Q4") -> Q4
A15: EDU00700 | B15: 02-11-2023 | C15: BYJU'S | D15: Language Learning | E15: English Communication | F15: Chennai | G15: Tamil Nadu | H15: Tier 1 | I15: Male | J15: 13-17 | K15: Word of Mouth | L15: Credit Card | M15: Tablet | N15: 4999 | O15: 15 | P15: 749.85 | Q15: 4249.15 | R15: 764.85 | S15: 3484.3 | T15: 1347.82 | U15: 2136.48 | V15: 61.32 | W15: No | Y15: No | Z15: 3 | AA15: =TRIM(PROPER(F15)) -> Chennai | AB15: =TRIM(PROPER(C15)) -> Byju'S | AC15: =IF(O15=0,"No Discount",IF(O15<=15,"Low (1-15%)",IF(O15<=30,"Medium (16-30%)","High (>30%)"))) -> Low (1-15%) | AD15: =IF(V15<0,"Loss Making",IF(V15<20,"Low Margin","Healthy Margin")) -> Healthy Margin | AE15: =TEXT(DATE(VALUE(RIGHT(B15,4)),VALUE(MID(B15,4,2)),VALUE(LEFT(B15,2))),"MMM-YYYY") -> Nov-2023 | AF15: =VALUE(RIGHT(B15,4)) -> 2023 | AG15: =CHOOSE(ROUNDUP(VALUE(MID(B15,4,2))/3,0),"Q1","Q2","Q3","Q4") -> Q4
A16: EDU02121 | B16: 21-12-2024 | C16: Great Learning | D16: Coding & Tech | E16: Full Stack Development | F16: Bengaluru | G16: Karnataka | H16: Tier 1 | I16: Female | J16: 45+ | K16: Direct/Organic | L16: UPI | M16: Tablet | N16: 29999 | O16: 40 | P16: 11999.6 | Q16: 17999.4 | R16: 3239.89 | S16: 14759.51 | T16: 6414.9 | U16: 8344.61 | V16: 56.54 | W16: Yes | X16: 4.2 | Y16: No | Z16: 0 | AA16: =TRIM(PROPER(F16)) -> Bengaluru | AB16: =TRIM(PROPER(C16)) -> Great Learning | AC16: =IF(O16=0,"No Discount",IF(O16<=15,"Low (1-15%)",IF(O16<=30,"Medium (16-30%)","High (>30%)"))) -> High (>30%) | AD16: =IF(V16<0,"Loss Making",IF(V16<20,"Low Margin","Healthy Margin")) -> Healthy Margin | AE16: =TEXT(DATE(VALUE(RIGHT(B16,4)),VALUE(MID(B16,4,2)),VALUE(LEFT(B16,2))),"MMM-YYYY") -> Dec-2024 | AF16: =VALUE(RIGHT(B16,4)) -> 2024 | AG16: =CHOOSE(ROUNDUP(VALUE(MID(B16,4,2))/3,0),"Q1","Q2","Q3","Q4") -> Q4
A17: EDU00341 | B17: 10-11-2024 | C17: Doubtnut | D17: Creative Arts | E17: Graphic Design Pro | F17: Vadodara | G17: Gujarat | H17: Tier 3 | I17: Male | J17: 18-24 | K17: Direct/Organic | L17: Net Banking | M17: Mobile | N17: 9999 | O17: 25 | P17: 2499.75 | Q17: 7499.25 | R17: 1349.87 | S17: 6149.38 | T17: 2274.96 | U17: 3874.42 | V17: 63.01 | W17: No | Y17: No | Z17: 3 | AA17: =TRIM(PROPER(F17)) -> Vadodara | AB17: =TRIM(PROPER(C17)) -> Doubtnut | AC17: =IF(O17=0,"No Discount",IF(O17<=15,"Low (1-15%)",IF(O17<=30,"Medium (16-30%)","High (>30%)"))) -> Medium (16-30%) | AD17: =IF(V17<0,"Loss Making",IF(V17<20,"Low Margin","Healthy Margin")) -> Healthy Margin | AE17: =TEXT(DATE(VALUE(RIGHT(B17,4)),VALUE(MID(B17,4,2)),VALUE(LEFT(B17,2))),"MMM-YYYY") -> Nov-2024 | AF17: =VALUE(RIGHT(B17,4)) -> 2024 | AG17: =CHOOSE(ROUNDUP(VALUE(MID(B17,4,2))/3,0),"Q1","Q2","Q3","Q4") -> Q4
A18: EDU02148 | B18: 20-11-2023 | C18: Extramarks | D18: Test Preparation | E18: SAT Complete Prep | F18: Nashik | G18: Maharashtra | H18: Tier 2 | I18: Female | J18: 35-44 | K18: Email Campaign | L18: Wallet | M18: Desktop | N18: 12999 | O18: 40 | P18: 5199.6 | Q18: 7799.4 | R18: 1403.89 | S18: 6395.51 | T18: 3570.77 | U18: 2824.74 | V18: 44.17 | W18: No | Y18: No | Z18: 0 | AA18: =TRIM(PROPER(F18)) -> Nashik | AB18: =TRIM(PROPER(C18)) -> Extramarks | AC18: =IF(O18=0,"No Discount",IF(O18<=15,"Low (1-15%)",IF(O18<=30,"Medium (16-30%)","High (>30%)"))) -> High (>30%) | AD18: =IF(V18<0,"Loss Making",IF(V18<20,"Low Margin","Healthy Margin")) -> Healthy Margin | AE18: =TEXT(DATE(VALUE(RIGHT(B18,4)),VALUE(MID(B18,4,2)),VALUE(LEFT(B18,2))),"MMM-YYYY") -> Nov-2023 | AF18: =VALUE(RIGHT(B18,4)) -> 2023 | AG18: =CHOOSE(ROUNDUP(VALUE(MID(B18,4,2))/3,0),"Q1","Q2","Q3","Q4") -> Q4
A19: EDU00152 | B19: 24-11-2023 | C19: Simplilearn | D19: Competitive Exams | E19: GATE CS Complete | F19: Vadodara | G19: Gujarat | H19: Tier 3 | I19: Male | J19: 18-24 | K19: Email Campaign | L19: EMI | M19: Mobile | N19: 12999 | O19: 25 | P19: 3249.75 | Q19: 9749.25 | R19: 1754.87 | S19: 7994.38 | T19: 3501.87 | U19: 4492.51 | V19: 56.2 | W19: Yes | Y19: No | Z19: 0 | AA19: =TRIM(PROPER(F19)) -> Vadodara | AB19: =TRIM(PROPER(C19)) -> Simplilearn | AC19: =IF(O19=0,"No Discount",IF(O19<=15,"Low (1-15%)",IF(O19<=30,"Medium (16-30%)","High (>30%)"))) -> Medium (16-30%) | AD19: =IF(V19<0,"Loss Making",IF(V19<20,"Low Margin","Healthy Margin")) -> Healthy Margin | AE19: =TEXT(DATE(VALUE(RIGHT(B19,4)),VALUE(MID(B19,4,2)),VALUE(LEFT(B19,2))),"MMM-YYYY") -> Nov-2023 | AF19: =VALUE(RIGHT(B19,4)) -> 2023 | AG19: =CHOOSE(ROUNDUP(VALUE(MID(B19,4,2))/3,0),"Q1","Q2","Q3","Q4") -> Q4
A20: EDU01163 | B20: 15-06-2024 | C20: BYJU'S | D20: Language Learning | E20: Business English | F20: Nashik | G20: Maharashtra | H20: Tier 2 | I20: Male | J20: 18-24 | K20: Direct/Organic | L20: UPI | M20: Mobile | N20: 6999 | O20: 40 | P20: 2799.6 | Q20: 4199.4 | R20: 755.89 | S20: 3443.51 | T20: 1857.34 | U20: 1586.17 | V20: 46.06 | W20: Yes | X20: 4 | Y20: No | Z20: 0 | AA20: =TRIM(PROPER(F20)) -> Nashik | AB20: =TRIM(PROPER(C20)) -> Byju'S | AC20: =IF(O20=0,"No Discount",IF(O20<=15,"Low (1-15%)",IF(O20<=30,"Medium (16-30%)","High (>30%)"))) -> High (>30%) | AD20: =IF(V20<0,"Loss Making",IF(V20<20,"Low Margin","Healthy Margin")) -> Healthy Margin | AE20: =TEXT(DATE(VALUE(RIGHT(B20,4)),VALUE(MID(B20,4,2)),VALUE(LEFT(B20,2))),"MMM-YYYY") -> Jun-2024 | AF20: =VALUE(RIGHT(B20,4)) -> 2024 | AG20: =CHOOSE(ROUNDUP(VALUE(MID(B20,4,2))/3,0),"Q1","Q2","Q3","Q4") -> Q2
A21: EDU02226 | B21: 19-05-2023 | C21: BYJU'S | D21: Coding & Tech | E21: Python for Beginners | F21: Jaipur | G21: Rajasthan | H21: Tier 2 | I21: Male | J21: 18-24 | K21: Instagram | L21: Debit Card | M21: Mobile | N21: 7999 | O21: 0 | P21: 0 | Q21: 7999 | R21: 1439.82 | S21: 6559.18 | T21: 2831.55 | U21: 3727.63 | V21: 56.83 | W21: Yes | X21: 4.3 | Y21: No | Z21: 0 | AA21: =TRIM(PROPER(F21)) -> Jaipur | AB21: =TRIM(PROPER(C21)) -> Byju'S | AC21: =IF(O21=0,"No Discount",IF(O21<=15,"Low (1-15%)",IF(O21<=30,"Medium (16-30%)","High (>30%)"))) -> No Discount | AD21: =IF(V21<0,"Loss Making",IF(V21<20,"Low Margin","Healthy Margin")) -> Healthy Margin | AE21: =TEXT(DATE(VALUE(RIGHT(B21,4)),VALUE(MID(B21,4,2)),VALUE(LEFT(B21,2))),"MMM-YYYY") -> May-2023 | AF21: =VALUE(RIGHT(B21,4)) -> 2023 | AG21: =CHOOSE(ROUNDUP(VALUE(MID(B21,4,2))/3,0),"Q1","Q2","Q3","Q4") -> Q2
A22: EDU02334 | B22: 25-07-2024 | C22: BYJU'S | D22: Coding & Tech | E22: Full Stack Development | F22: Howrah | G22: West Bengal | H22: Tier 3 | I22: Female | J22: 25-34 | K22: Google Ads | L22: Wallet | M22: Mobile | N22: 29999 | O22: 40 | P22: 11999.6 | Q22: 17999.4 | R22: 3239.89 | S22: 14759.51 | T22: 7295.56 | U22: 7463.95 | V22: 50.57 | W22: Yes | Y22: No | Z22: 0 | AA22: =TRIM(PROPER(F22)) -> Howrah | AB22: =TRIM(PROPER(C22)) -> Byju'S | AC22: =IF(O22=0,"No Discount",IF(O22<=15,"Low (1-15%)",IF(O22<=30,"Medium (16-30%)","High (>30%)"))) -> High (>30%) | AD22: =IF(V22<0,"Loss Making",IF(V22<20,"Low Margin","Healthy Margin")) -> Healthy Margin | AE22: =TEXT(DATE(VALUE(RIGHT(B22,4)),VALUE(MID(B22,4,2)),VALUE(LEFT(B22,2))),"MMM-YYYY") -> Jul-2024 | AF22: =VALUE(RIGHT(B22,4)) -> 2024 | AG22: =CHOOSE(ROUNDUP(VALUE(MID(B22,4,2))/3,0),"Q1","Q2","Q3","Q4") -> Q3
A23: EDU00808 | B23: 09-10-2023 | C23: Doubtnut | D23: Test Preparation | E23: GRE Verbal+Quant | F23: Surat | G23: Gujarat | H23: Tier 2 | I23: Female | J23: 45+ | K23: Word of Mouth | L23: UPI | M23: Tablet | N23: 11999 | O23: 0 | P23: 0 | Q23: 11999 | R23: 2159.82 | S23: 9839.18 | T23: 4634.06 | U23: 5205.12 | V23: 52.9 | W23: Yes | X23: 3.1 | Y23: No | Z23: 2 | AA23: =TRIM(PROPER(F23)) -> Surat | AB23: =TRIM(PROPER(C23)) -> Doubtnut | AC23: =IF(O23=0,"No Discount",IF(O23<=15,"Low (1-15%)",IF(O23<=30,"Medium (16-30%)","High (>30%)"))) -> No Discount | AD23: =IF(V23<0,"Loss Making",IF(V23<20,"Low Margin","Healthy Margin")) -> Healthy Margin | AE23: =TEXT(DATE(VALUE(RIGHT(B23,4)),VALUE(MID(B23,4,2)),VALUE(LEFT(B23,2))),"MMM-YYYY") -> Oct-2023 | AF23: =VALUE(RIGHT(B23,4)) -> 2023 | AG23: =CHOOSE(ROUNDUP(VALUE(MID(B23,4,2))/3,0),"Q1","Q2","Q3","Q4") -> Q4
A24: EDU01261 | B24: 14-01-2024 | C24: Great Learning | D24: Competitive Exams | E24: IIT-JEE Advanced Prep | F24: Howrah | G24: West Bengal | H24: Tier 3 | I24: Female | J24: 18-24 | K24: Email Campaign | L24: Wallet | M24: Desktop | N24: 24999 | O24: 20 | P24: 4999.8 | Q24: 19999.2 | R24: 3599.86 | S24: 16399.34 | T24: 6763.99 | U24: 9635.35 | V24: 58.75 | W24: Yes | X24: 3.7 | Y24: No | Z24: 0 | AA24: =TRIM(PROPER(F24)) -> Howrah | AB24: =TRIM(PROPER(C24)) -> Great Learning | AC24: =IF(O24=0,"No Discount",IF(O24<=15,"Low (1-15%)",IF(O24<=30,"Medium (16-30%)","High (>30%)"))) -> Medium (16-30%) | AD24: =IF(V24<0,"Loss Making",IF(V24<20,"Low Margin","Healthy Margin")) -> Healthy Margin | AE24: =TEXT(DATE(VALUE(RIGHT(B24,4)),VALUE(MID(B24,4,2)),VALUE(LEFT(B24,2))),"MMM-YYYY") -> Jan-2024 | AF24: =VALUE(RIGHT(B24,4)) -> 2024 | AG24: =CHOOSE(ROUNDUP(VALUE(MID(B24,4,2))/3,0),"Q1","Q2","Q3","Q4") -> Q1
A25: EDU01083 | B25: 17-06-2023 | C25: Doubtnut | D25: Competitive Exams | E25: CAT Prep Masterclass | F25: Chennai | G25: Tamil Nadu | H25: Tier 1 | I25: Other | J25: 35-44 | K25: Google Ads | L25: Credit Card | M25: Desktop | N25: 14999 | O25: 0 | P25: 0 | Q25: 14999 | R25: 2699.82 | S25: 12299.18 | T25: 4245.97 | U25: 8053.21 | V25: 65.48 | W25: Yes | X25: 3.4 | Y25: No | Z25: 0 | AA25: =TRIM(PROPER(F25)) -> Chennai | AB25: =TRIM(PROPER(C25)) -> Doubtnut | AC25: =IF(O25=0,"No Discount",IF(O25<=15,"Low (1-15%)",IF(O25<=30,"Medium (16-30%)","High (>30%)"))) -> No Discount | AD25: =IF(V25<0,"Loss Making",IF(V25<20,"Low Margin","Healthy Margin")) -> Healthy Margin | AE25: =TEXT(DATE(VALUE(RIGHT(B25,4)),VALUE(MID(B25,4,2)),VALUE(LEFT(B25,2))),"MMM-YYYY") -> Jun-2023 | AF25: =VALUE(RIGHT(B25,4)) -> 2023 | AG25: =CHOOSE(ROUNDUP(VALUE(MID(B25,4,2))/3,0),"Q1","Q2","Q3","Q4") -> Q2
A26: EDU00326 | B26: 05-01-2023 | C26: Meritnation | D26: Professional Upskilling | E26: Digital Marketing Pro | F26: Surat | G26: Gujarat | H26: Tier 2 | I26: Male | J26: 35-44 | K26: School/College Partnership | L26: Credit Card | M26: Mobile | N26: 12999 | O26: 50 | P26: 6499.5 | Q26: 6499.5 | R26: 1169.91 | S26: 5329.59 | T26: 2783.75 | U26: 2545.84 | V26: 47.77 | W26: No | Y26: No | Z26: 1 | AA26: =TRIM(PROPER(F26)) -> Surat | AB26: =TRIM(PROPER(C26)) -> Meritnation | AC26: =IF(O26=0,"No Discount",IF(O26<=15,"Low (1-15%)",IF(O26<=30,"Medium (16-30%)","High (>30%)"))) -> High (>30%) | AD26: =IF(V26<0,"Loss Making",IF(V26<20,"Low Margin","Healthy Margin")) -> Healthy Margin | AE26: =TEXT(DATE(VALUE(RIGHT(B26,4)),VALUE(MID(B26,4,2)),VALUE(LEFT(B26,2))),"MMM-YYYY") -> Jan-2023 | AF26: =VALUE(RIGHT(B26,4)) -> 2023 | AG26: =CHOOSE(ROUNDUP(VALUE(MID(B26,4,2))/3,0),"Q1","Q2","Q3","Q4") -> Q1
A27: EDU00465 | B27: 27-05-2024 | C27: Scaler | D27: K-12 Academics | E27: Class 8-10 Science Pack | F27: Madurai | G27: Tamil Nadu | H27: Tier 3 | I27: Female | J27: 35-44 | K27: YouTube | L27: UPI | M27: Desktop | N27: 4999 | O27: 5 | P27: 249.95 | Q27: 4749.05 | R27: 854.83 | S27: 3894.22 | T27: 2019.87 | U27: 1874.35 | V27: 48.13 | W27: No | Y27: No | Z27: 1 | AA27: =TRIM(PROPER(F27)) -> Madurai | AB27: =TRIM(PROPER(C27)) -> Scaler | AC27: =IF(O27=0,"No Discount",IF(O27<=15,"Low (1-15%)",IF(O27<=30,"Medium (16-30%)","High (>30%)"))) -> Low (1-15%) | AD27: =IF(V27<0,"Loss Making",IF(V27<20,"Low Margin","Healthy Margin")) -> Healthy Margin | AE27: =TEXT(DATE(VALUE(RIGHT(B27,4)),VALUE(MID(B27,4,2)),VALUE(LEFT(B27,2))),"MMM-YYYY") -> May-2024 | AF27: =VALUE(RIGHT(B27,4)) -> 2024 | AG27: =CHOOSE(ROUNDUP(VALUE(MID(B27,4,2))/3,0),"Q1","Q2","Q3","Q4") -> Q2
A28: EDU00745 | B28: 12-05-2023 | C28: Meritnation | D28: K-12 Academics | E28: Foundation Course | F28: Bengaluru | G28: Karnataka | H28: Tier 1 | I28: Female | J28: 35-44 | K28: WhatsApp | L28: Wallet | M28: Tablet | N28: 6999 | O28: 40 | P28: 2799.6 | Q28: 4199.4 | R28: 755.89 | S28: 3443.51 | T28: 1688.9 | U28: 1754.61 | V28: 50.95 | W28: No | Y28: No | Z28: 1 | AA28: =TRIM(PROPER(F28)) -> Bengaluru | AB28: =TRIM(PROPER(C28)) -> Meritnation | AC28: =IF(O28=0,"No Discount",IF(O28<=15,"Low (1-15%)",IF(O28<=30,"Medium (16-30%)","High (>30%)"))) -> High (>30%) | AD28: =IF(V28<0,"Loss Making",IF(V28<20,"Low Margin","Healthy Margin")) -> Healthy Margin | AE28: =TEXT(DATE(VALUE(RIGHT(B28,4)),VALUE(MID(B28,4,2)),VALUE(LEFT(B28,2))),"MMM-YYYY") -> May-2023 | AF28: =VALUE(RIGHT(B28,4)) -> 2023 | AG28: =CHOOSE(ROUNDUP(VALUE(MID(B28,4,2))/3,0),"Q1","Q2","Q3","Q4") -> Q2
A29: EDU02388 | B29: 27-06-2023 | C29: Embibe | D29: Professional Upskilling | E29: Data Analytics Bootcamp | F29: Gurugram | G29: Delhi NCR | H29: Tier 1 | I29: Other | J29: 35-44 | K29: Word of Mouth | L29: Net Banking | M29: Mobile | N29: 19999 | O29: 40 | P29: 7999.6 | Q29: 11999.4 | R29: 2159.89 | S29: 9839.51 | T29: 4786.15 | U29: 5053.36 | V29: 51.36 | W29: Yes | X29: 3.4 | Y29: No | Z29: 0 | AA29: =TRIM(PROPER(F29)) -> Gurugram | AB29: =TRIM(PROPER(C29)) -> Embibe | AC29: =IF(O29=0,"No Discount",IF(O29<=15,"Low (1-15%)",IF(O29<=30,"Medium (16-30%)","High (>30%)"))) -> High (>30%) | AD29: =IF(V29<0,"Loss Making",IF(V29<20,"Low Margin","Healthy Margin")) -> Healthy Margin | AE29: =TEXT(DATE(VALUE(RIGHT(B29,4)),VALUE(MID(B29,4,2)),VALUE(LEFT(B29,2))),"MMM-YYYY") -> Jun-2023 | AF29: =VALUE(RIGHT(B29,4)) -> 2023 | AG29: =CHOOSE(ROUNDUP(VALUE(MID(B29,4,2))/3,0),"Q1","Q2","Q3","Q4") -> Q2
A30: EDU01927 | B30: 17-07-2024 | C30: Leverage Edu | D30: K-12 Academics | E30: Class 8-10 Science Pack | F30: Howrah | G30: West Bengal | H30: Tier 3 | I30: Male | J30: 18-24 | K30: School/College Partnership | L30: Net Banking | M30: Mobile | N30: 4999 | O30: 0 | P30: 0 | Q30: 4999 | R30: 899.82 | S30: 4099.18 | T30: 2251.19 | U30: 1847.99 | V30: 45.08 | W30: No | Y30: Yes | Z30: 2 | AA30: =TRIM(PROPER(F30)) -> Howrah | AB30: =TRIM(PROPER(C30)) -> Leverage Edu | AC30: =IF(O30=0,"No Discount",IF(O30<=15,"Low (1-15%)",IF(O30<=30,"Medium (16-30%)","High (>30%)"))) -> No Discount | AD30: =IF(V30<0,"Loss Making",IF(V30<20,"Low Margin","Healthy Margin")) -> Healthy Margin | AE30: =TEXT(DATE(VALUE(RIGHT(B30,4)),VALUE(MID(B30,4,2)),VALUE(LEFT(B30,2))),"MMM-YYYY") -> Jul-2024 | AF30: =VALUE(RIGHT(B30,4)) -> 2024 | AG30: =CHOOSE(ROUNDUP(VALUE(MID(B30,4,2))/3,0),"Q1","Q2","Q3","Q4") -> Q3
A31: EDU00661 | B31: 10-04-2024 | C31: Great Learning | D31: Coding & Tech | E31: Data Science Masters | F31: Vadodara | G31: Gujarat | H31: Tier 3 | I31: Other | J31: 25-34 | K31: Instagram | L31: Net Banking | M31: Tablet | N31: 34999 | O31: 0 | P31: 0 | Q31: 34999 | R31: 6299.82 | S31: 28699.18 | T31: 15004.71 | U31: 13694.47 | V31: 47.72 | W31: Yes | X31: 4.2 | Y31: No | Z31: 0 | AA31: =TRIM(PROPER(F31)) -> Vadodara | AB31: =TRIM(PROPER(C31)) -> Great Learning | AC31: =IF(O31=0,"No Discount",IF(O31<=15,"Low (1-15%)",IF(O31<=30,"Medium (16-30%)","High (>30%)"))) -> No Discount | AD31: =IF(V31<0,"Loss Making",IF(V31<20,"Low Margin","Healthy Margin")) -> Healthy Margin | AE31: =TEXT(DATE(VALUE(RIGHT(B31,4)),VALUE(MID(B31,4,2)),VALUE(LEFT(B31,2))),"MMM-YYYY") -> Apr-2024 | AF31: =VALUE(RIGHT(B31,4)) -> 2024 | AG31: =CHOOSE(ROUNDUP(VALUE(MID(B31,4,2))/3,0),"Q1","Q2","Q3","Q4") -> Q2
A32: EDU01751 | B32: 27-06-2023 | C32: Extramarks | D32: Test Preparation | E32: SAT Complete Prep | F32: Faridabad | G32: Delhi NCR | H32: Tier 2 | I32: Other | J32: 25-34 | K32: Word of Mouth | L32: Debit Card | M32: Tablet | N32: 12999 | O32: 20 | P32: 2599.8 | Q32: 10399.2 | R32: 1871.86 | S32: 8527.34 | T32: 4283.93 | U32: 4243.41 | V32: 49.76 | W32: Yes | X32: 3.5 | Y32: No | Z32: 1 | AA32: =TRIM(PROPER(F32)) -> Faridabad | AB32: =TRIM(PROPER(C32)) -> Extramarks | AC32: =IF(O32=0,"No Discount",IF(O32<=15,"Low (1-15%)",IF(O32<=30,"Medium (16-30%)","High (>30%)"))) -> Medium (16-30%) | AD32: =IF(V32<0,"Loss Making",IF(V32<20,"Low Margin","Healthy Margin")) -> Healthy Margin | AE32: =TEXT(DATE(VALUE(RIGHT(B32,4)),VALUE(MID(B32,4,2)),VALUE(LEFT(B32,2))),"MMM-YYYY") -> Jun-2023 | AF32: =VALUE(RIGHT(B32,4)) -> 2023 | AG32: =CHOOSE(ROUNDUP(VALUE(MID(B32,4,2))/3,0),"Q1","Q2","Q3","Q4") -> Q2
A33: EDU00116 | B33: 16-03-2024 | C33: Vedantu | D33: Creative Arts | E33: UI/UX Design | F33: Mumbai | G33: Maharashtra | H33: Tier 1 | I33: Other | J33: 25-34 | K33: Instagram | L33: Net Banking | M33: Tablet | N33: 14999 | O33: 50 | P33: 7499.5 | Q33: 7499.5 | R33: 1349.91 | S33: 6149.59 | T33: 3376.6 | U33: 2772.99 | V33: 45.09 | W33: Yes | X33: 3.7 | Y33: No | Z33: 0 | AA33: =TRIM(PROPER(F33)) -> Mumbai | AB33: =TRIM(PROPER(C33)) -> Vedantu | AC33: =IF(O33=0,"No Discount",IF(O33<=15,"Low (1-15%)",IF(O33<=30,"Medium (16-30%)","High (>30%)"))) -> High (>30%) | AD33: =IF(V33<0,"Loss Making",IF(V33<20,"Low Margin","Healthy Margin")) -> Healthy Margin | AE33: =TEXT(DATE(VALUE(RIGHT(B33,4)),VALUE(MID(B33,4,2)),VALUE(LEFT(B33,2))),"MMM-YYYY") -> Mar-2024 | AF33: =VALUE(RIGHT(B33,4)) -> 2024 | AG33: =CHOOSE(ROUNDUP(VALUE(MID(B33,4,2))/3,0),"Q1","Q2","Q3","Q4") -> Q1
A34: EDU01438 | B34: 02-06-2023 | C34: Scaler | D34: Professional Upskilling | E34: Financial Modelling | F34: Nashik | G34: Maharashtra | H34: Tier 2 | I34: Male | J34: 45+ | K34: WhatsApp | L34: Wallet | M34: Mobile | N34: 15999 | O34: 10 | P34: 1599.9 | Q34: 14399.1 | R34: 2591.84 | S34: 11807.26 | T34: 5560.38 | U34: 6246.88 | V34: 52.91 | W34: Yes | X34: 2.7 | Y34: No | Z34: 1 | AA34: =TRIM(PROPER(F34)) -> Nashik | AB34: =TRIM(PROPER(C34)) -> Scaler | AC34: =IF(O34=0,"No Discount",IF(O34<=15,"Low (1-15%)",IF(O34<=30,"Medium (16-30%)","High (>30%)"))) -> Low (1-15%) | AD34: =IF(V34<0,"Loss Making",IF(V34<20,"Low Margin","Healthy Margin")) -> Healthy Margin | AE34: =TEXT(DATE(VALUE(RIGHT(B34,4)),VALUE(MID(B34,4,2)),VALUE(LEFT(B34,2))),"MMM-YYYY") -> Jun-2023 | AF34: =VALUE(RIGHT(B34,4)) -> 2023 | AG34: =CHOOSE(ROUNDUP(VALUE(MID(B34,4,2))/3,0),"Q1","Q2","Q3","Q4") -> Q2
A35: EDU02469 | B35: 12-10-2023 | C35: Doubtnut | D35: Professional Upskilling | E35: HR Management | F35: Hyderabad | G35: Telangana | H35: Tier 1 | I35: Male | J35: 25-34 | K35: Instagram | L35: Credit Card | M35: Mobile | N35: 8999 | O35: 0 | P35: 0 | Q35: 8999 | R35: 1619.82 | S35: 7379.18 | T35: 2355.9 | U35: 5023.28 | V35: 68.07 | W35: No | Y35: Yes | Z35: 0 | AA35: =TRIM(PROPER(F35)) -> Hyderabad | AB35: =TRIM(PROPER(C35)) -> Doubtnut | AC35: =IF(O35=0,"No Discount",IF(O35<=15,"Low (1-15%)",IF(O35<=30,"Medium (16-30%)","High (>30%)"))) -> No Discount | AD35: =IF(V35<0,"Loss Making",IF(V35<20,"Low Margin","Healthy Margin")) -> Healthy Margin | AE35: =TEXT(DATE(VALUE(RIGHT(B35,4)),VALUE(MID(B35,4,2)),VALUE(LEFT(B35,2))),"MMM-YYYY") -> Oct-2023 | AF35: =VALUE(RIGHT(B35,4)) -> 2023 | AG35: =CHOOSE(ROUNDUP(VALUE(MID(B35,4,2))/3,0),"Q1","Q2","Q3","Q4") -> Q4
A36: EDU01030 | B36: 11-03-2024 | C36: Toppr | D36: K-12 Academics | E36: Class 11-12 PCB | F36: Chennai | G36: Tamil Nadu | H36: Tier 1 | I36: Male | J36: 25-34 | K36: Direct/Organic | L36: Net Banking | M36: Mobile | N36: 8499 | O36: 20 | P36: 1699.8 | Q36: 6799.2 | R36: 1223.86 | S36: 5575.34 | T36: 2362.25 | U36: 3213.09 | V36: 57.63 | W36: No | Y36: No | Z36: 1 | AA36: =TRIM(PROPER(F36)) -> Chennai | AB36: =TRIM(PROPER(C36)) -> Toppr | AC36: =IF(O36=0,"No Discount",IF(O36<=15,"Low (1-15%)",IF(O36<=30,"Medium (16-30%)","High (>30%)"))) -> Medium (16-30%) | AD36: =IF(V36<0,"Loss Making",IF(V36<20,"Low Margin","Healthy Margin")) -> Healthy Margin | AE36: =TEXT(DATE(VALUE(RIGHT(B36,4)),VALUE(MID(B36,4,2)),VALUE(LEFT(B36,2))),"MMM-YYYY") -> Mar-2024 | AF36: =VALUE(RIGHT(B36,4)) -> 2024 | AG36: =CHOOSE(ROUNDUP(VALUE(MID(B36,4,2))/3,0),"Q1","Q2","Q3","Q4") -> Q1
A37: EDU00451 | B37: 20-07-2024 | C37: Scaler | D37: Higher Education | E37: B.Tech CSE Support | F37: Warangal | G37: Telangana | H37: Tier 3 | I37: Female | J37: 25-34 | K37: Word of Mouth | L37: Credit Card | M37: Desktop | N37: 9999 | O37: 0 | P37: 0 | Q37: 9999 | R37: 1799.82 | S37: 8199.18 | T37: 3293.48 | U37: 4905.7 | V37: 59.83 | W37: Yes | X37: 2.8 | Y37: No | Z37: 1 | AA37: =TRIM(PROPER(F37)) -> Warangal | AB37: =TRIM(PROPER(C37)) -> Scaler | AC37: =IF(O37=0,"No Discount",IF(O37<=15,"Low (1-15%)",IF(O37<=30,"Medium (16-30%)","High (>30%)"))) -> No Discount | AD37: =IF(V37<0,"Loss Making",IF(V37<20,"Low Margin","Healthy Margin")) -> Healthy Margin | AE37: =TEXT(DATE(VALUE(RIGHT(B37,4)),VALUE(MID(B37,4,2)),VALUE(LEFT(B37,2))),"MMM-YYYY") -> Jul-2024 | AF37: =VALUE(RIGHT(B37,4)) -> 2024 | AG37: =CHOOSE(ROUNDUP(VALUE(MID(B37,4,2))/3,0),"Q1","Q2","Q3","Q4") -> Q3
A38: EDU01690 | B38: 21-08-2024 | C38: Leverage Edu | D38: Professional Upskilling | E38: Digital Marketing Pro | F38: Faridabad | G38: Delhi NCR | H38: Tier 2 | I38: Other | J38: 13-17 | K38: WhatsApp | L38: Wallet | M38: Tablet | N38: 12999 | O38: 0 | P38: 0 | Q38: 12999 | R38: 2339.82 | S38: 10659.18 | T38: 5160.76 | U38: 5498.42 | V38: 51.58 | W38: No | Y38: No | Z38: 0 | AA38: =TRIM(PROPER(F38)) -> Faridabad | AB38: =TRIM(PROPER(C38)) -> Leverage Edu | AC38: =IF(O38=0,"No Discount",IF(O38<=15,"Low (1-15%)",IF(O38<=30,"Medium (16-30%)","High (>30%)"))) -> No Discount | AD38: =IF(V38<0,"Loss Making",IF(V38<20,"Low Margin","Healthy Margin")) -> Healthy Margin | AE38: =TEXT(DATE(VALUE(RIGHT(B38,4)),VALUE(MID(B38,4,2)),VALUE(LEFT(B38,2))),"MMM-YYYY") -> Aug-2024 | AF38: =VALUE(RIGHT(B38,4)) -> 2024 | AG38: =CHOOSE(ROUNDUP(VALUE(MID(B38,4,2))/3,0),"Q1","Q2","Q3","Q4") -> Q3
A39: EDU00493 | B39: 28-11-2023 | C39: BYJU'S | D39: Language Learning | E39: Business English | F39: New Delhi | G39: Delhi NCR | H39: Tier 1 | I39: Male | J39: 18-24 | K39: Word of Mouth | L39: Debit Card | M39: Desktop | N39: 6999 | O39: 15 | P39: 1049.85 | Q39: 5949.15 | R39: 1070.85 | S39: 4878.3 | T39: 2141.47 | U39: 2736.83 | V39: 56.1 | W39: No | Y39: No | Z39: 0 | AA39: =TRIM(PROPER(F39)) -> New Delhi | AB39: =TRIM(PROPER(C39)) -> Byju'S | AC39: =IF(O39=0,"No Discount",IF(O39<=15,"Low (1-15%)",IF(O39<=30,"Medium (16-30%)","High (>30%)"))) -> Low (1-15%) | AD39: =IF(V39<0,"Loss Making",IF(V39<20,"Low Margin","Healthy Margin")) -> Healthy Margin | AE39: =TEXT(DATE(VALUE(RIGHT(B39,4)),VALUE(MID(B39,4,2)),VALUE(LEFT(B39,2))),"MMM-YYYY") -> Nov-2023 | AF39: =VALUE(RIGHT(B39,4)) -> 2023 | AG39: =CHOOSE(ROUNDUP(VALUE(MID(B39,4,2))/3,0),"Q1","Q2","Q3","Q4") -> Q4
A40: EDU01138 | B40: 08-12-2023 | C40: Doubtnut | D40: Coding & Tech | E40: Data Science Masters | F40: Pune | G40: Maharashtra | H40: Tier 1 | I40: Male | J40: 35-44 | K40: WhatsApp | L40: Net Banking | M40: Desktop | N40: 34999 | O40: 30 | P40: 10499.7 | Q40: 24499.3 | R40: 4409.87 | S40: 20089.43 | T40: 5458.37 | U40: 14631.06 | V40: 72.83 | W40: No | Y40: Yes | Z40: 0 | AA40: =TRIM(PROPER(F40)) -> Pune | AB40: =TRIM(PROPER(C40)) -> Doubtnut | AC40: =IF(O40=0,"No Discount",IF(O40<=15,"Low (1-15%)",IF(O40<=30,"Medium (16-30%)","High (>30%)"))) -> Medium (16-30%) | AD40: =IF(V40<0,"Loss Making",IF(V40<20,"Low Margin","Healthy Margin")) -> Healthy Margin | AE40: =TEXT(DATE(VALUE(RIGHT(B40,4)),VALUE(MID(B40,4,2)),VALUE(LEFT(B40,2))),"MMM-YYYY") -> Dec-2023 | AF40: =VALUE(RIGHT(B40,4)) -> 2023 | AG40: =CHOOSE(ROUNDUP(VALUE(MID(B40,4,2))/3,0),"Q1","Q2","Q3","Q4") -> Q4
A41: EDU01309 | B41: 08-03-2024 | C41: BYJU'S | D41: Competitive Exams | E41: UPSC GS Foundation | F41: Noida | G41: Delhi NCR | H41: Tier 1 | I41: Male | J41: 18-24 | K41: Instagram | L41: UPI | M41: Mobile | N41: 18999 | O41: 40 | P41: 7599.6 | Q41: 11399.4 | R41: 2051.89 | S41: 9347.51 | T41: 4563.59 | U41: 4783.92 | V41: 51.18 | W41: Yes | X41: 4.4 | Y41: No | Z41: 0 | AA41: =TRIM(PROPER(F41)) -> Noida | AB41: =TRIM(PROPER(C41)) -> Byju'S | AC41: =IF(O41=0,"No Discount",IF(O41<=15,"Low (1-15%)",IF(O41<=30,"Medium (16-30%)","High (>30%)"))) -> High (>30%) | AD41: =IF(V41<0,"Loss Making",IF(V41<20,"Low Margin","Healthy Margin")) -> Healthy Margin | AE41: =TEXT(DATE(VALUE(RIGHT(B41,4)),VALUE(MID(B41,4,2)),VALUE(LEFT(B41,2))),"MMM-YYYY") -> Mar-2024 | AF41: =VALUE(RIGHT(B41,4)) -> 2024 | AG41: =CHOOSE(ROUNDUP(VALUE(MID(B41,4,2))/3,0),"Q1","Q2","Q3","Q4") -> Q1
A42: EDU02068 | B42: 01-01-2024 | C42: Great Learning | D42: Professional Upskilling | E42: Digital Marketing Pro | F42: Noida | G42: Delhi NCR | H42: Tier 1 | I42: Female | J42: 35-44 | K42: Word of Mouth | L42: Debit Card | M42: Mobile | N42: 12999 | O42: 25 | P42: 3249.75 | Q42: 9749.25 | R42: 1754.87 | S42: 7994.38 | T42: 3183.21 | U42: 4811.17 | V42: 60.18 | W42: Yes | X42: 3.8 | Y42: No | Z42: 1 | AA42: =TRIM(PROPER(F42)) -> Noida | AB42: =TRIM(PROPER(C42)) -> Great Learning | AC42: =IF(O42=0,"No Discount",IF(O42<=15,"Low (1-15%)",IF(O42<=30,"Medium (16-30%)","High (>30%)"))) -> Medium (16-30%) | AD42: =IF(V42<0,"Loss Making",IF(V42<20,"Low Margin","Healthy Margin")) -> Healthy Margin | AE42: =TEXT(DATE(VALUE(RIGHT(B42,4)),VALUE(MID(B42,4,2)),VALUE(LEFT(B42,2))),"MMM-YYYY") -> Jan-2024 | AF42: =VALUE(RIGHT(B42,4)) -> 2024 | AG42: =CHOOSE(ROUNDUP(VALUE(MID(B42,4,2))/3,0),"Q1","Q2","Q3","Q4") -> Q1
A43: EDU02259 | B43: 16-08-2023 | C43: Simplilearn | D43: Higher Education | E43: BBA Business Basics | F43: Noida | G43: Delhi NCR | H43: Tier 1 | I43: Male | J43: 45+ | K43: WhatsApp | L43: Net Banking | M43: Mobile | N43: 7499 | O43: 15 | P43: 1124.85 | Q43: 6374.15 | R43: 1147.35 | S43: 5226.8 | T43: 1637.16 | U43: 3589.64 | V43: 68.68 | W43: Yes | Y43: No | Z43: 0 | AA43: =TRIM(PROPER(F43)) -> Noida | AB43: =TRIM(PROPER(C43)) -> Simplilearn | AC43: =IF(O43=0,"No Discount",IF(O43<=15,"Low (1-15%)",IF(O43<=30,"Medium (16-30%)","High (>30%)"))) -> Low (1-15%) | AD43: =IF(V43<0,"Loss Making",IF(V43<20,"Low Margin","Healthy Margin")) -> Healthy Margin | AE43: =TEXT(DATE(VALUE(RIGHT(B43,4)),VALUE(MID(B43,4,2)),VALUE(LEFT(B43,2))),"MMM-YYYY") -> Aug-2023 | AF43: =VALUE(RIGHT(B43,4)) -> 2023 | AG43: =CHOOSE(ROUNDUP(VALUE(MID(B43,4,2))/3,0),"Q1","Q2","Q3","Q4") -> Q3
A44: EDU01792 | B44: 13-05-2023 | C44: Toppr | D44: Higher Education | E44: B.Tech CSE Support | F44: Pune | G44: Maharashtra | H44: Tier 1 | I44: Male | J44: 18-24 | K44: Instagram | L44: Credit Card | M44: Mobile | N44: 9999 | O44: 30 | P44: 2999.7 | Q44: 6999.3 | R44: 1259.87 | S44: 5739.43 | T44: 2404.81 | U44: 3334.62 | V44: 58.1 | W44: Yes | X44: 4.2 | Y44: No | Z44: 0 | AA44: =TRIM(PROPER(F44)) -> Pune | AB44: =TRIM(PROPER(C44)) -> Toppr | AC44: =IF(O44=0,"No Discount",IF(O44<=15,"Low (1-15%)",IF(O44<=30,"Medium (16-30%)","High (>30%)"))) -> Medium (16-30%) | AD44: =IF(V44<0,"Loss Making",IF(V44<20,"Low Margin","Healthy Margin")) -> Healthy Margin | AE44: =TEXT(DATE(VALUE(RIGHT(B44,4)),VALUE(MID(B44,4,2)),VALUE(LEFT(B44,2))),"MMM-YYYY") -> May-2023 | AF44: =VALUE(RIGHT(B44,4)) -> 2023 | AG44: =CHOOSE(ROUNDUP(VALUE(MID(B44,4,2))/3,0),"Q1","Q2","Q3","Q4") -> Q2
A45: EDU00545 | B45: 31-10-2024 | C45: Scaler | D45: Test Preparation | E45: GMAT Focus Edition | F45: Vadodara | G45: Gujarat | H45: Tier 3 | I45: Male | J45: 13-17 | K45: YouTube | L45: Net Banking | M45: Tablet | N45: 16999 | O45: 25 | P45: 4249.75 | Q45: 12749.25 | R45: 2294.86 | S45: 10454.39 | T45: 5448.17 | U45: 5006.22 | V45: 47.89 | W45: Yes | X45: 4.2 | Y45: No | Z45: 1 | AA45: =TRIM(PROPER(F45)) -> Vadodara | AB45: =TRIM(PROPER(C45)) -> Scaler | AC45: =IF(O45=0,"No Discount",IF(O45<=15,"Low (1-15%)",IF(O45<=30,"Medium (16-30%)","High (>30%)"))) -> Medium (16-30%) | AD45: =IF(V45<0,"Loss Making",IF(V45<20,"Low Margin","Healthy Margin")) -> Healthy Margin | AE45: =TEXT(DATE(VALUE(RIGHT(B45,4)),VALUE(MID(B45,4,2)),VALUE(LEFT(B45,2))),"MMM-YYYY") -> Oct-2024 | AF45: =VALUE(RIGHT(B45,4)) -> 2024 | AG45: =CHOOSE(ROUNDUP(VALUE(MID(B45,4,2))/3,0),"Q1","Q2","Q3","Q4") -> Q4
A46: EDU00396 | B46: 06-11-2024 | C46: Meritnation | D46: Professional Upskilling | E46: HR Management | F46: Faridabad | G46: Delhi NCR | H46: Tier 2 | I46: Other | J46: 35-44 | K46: Email Campaign | L46: EMI | M46: Tablet | N46: 8999 | O46: 50 | P46: 4499.5 | Q46: 4499.5 | R46: 809.91 | S46: 3689.59 | T46: 2052.6 | U46: 1636.99 | V46: 44.37 | W46: No | Y46: Yes | Z46: 1 | AA46: =TRIM(PROPER(F46)) -> Faridabad | AB46: =TRIM(PROPER(C46)) -> Meritnation | AC46: =IF(O46=0,"No Discount",IF(O46<=15,"Low (1-15%)",IF(O46<=30,"Medium (16-30%)","High (>30%)"))) -> High (>30%) | AD46: =IF(V46<0,"Loss Making",IF(V46<20,"Low Margin","Healthy Margin")) -> Healthy Margin | AE46: =TEXT(DATE(VALUE(RIGHT(B46,4)),VALUE(MID(B46,4,2)),VALUE(LEFT(B46,2))),"MMM-YYYY") -> Nov-2024 | AF46: =VALUE(RIGHT(B46,4)) -> 2024 | AG46: =CHOOSE(ROUNDUP(VALUE(MID(B46,4,2))/3,0),"Q1","Q2","Q3","Q4") -> Q4
A47: EDU00640 | B47: 21-05-2024 | C47: Vedantu | D47: Creative Arts | E47: Graphic Design Pro | F47: Chennai | G47: Tamil Nadu | H47: Tier 1 | I47: Other | J47: 18-24 | K47: WhatsApp | L47: Credit Card | M47: Desktop | N47: 9999 | O47: 30 | P47: 2999.7 | Q47: 6999.3 | R47: 1259.87 | S47: 5739.43 | T47: 2797.85 | U47: 2941.58 | V47: 51.25 | W47: Yes | X47: 3.1 | Y47: No | Z47: 0 | AA47: =TRIM(PROPER(F47)) -> Chennai | AB47: =TRIM(PROPER(C47)) -> Vedantu | AC47: =IF(O47=0,"No Discount",IF(O47<=15,"Low (1-15%)",IF(O47<=30,"Medium (16-30%)","High (>30%)"))) -> Medium (16-30%) | AD47: =IF(V47<0,"Loss Making",IF(V47<20,"Low Margin","Healthy Margin")) -> Healthy Margin | AE47: =TEXT(DATE(VALUE(RIGHT(B47,4)),VALUE(MID(B47,4,2)),VALUE(LEFT(B47,2))),"MMM-YYYY") -> May-2024 | AF47: =VALUE(RIGHT(B47,4)) -> 2024 | AG47: =CHOOSE(ROUNDUP(VALUE(MID(B47,4,2))/3,0),"Q1","Q2","Q3","Q4") -> Q2
A48: EDU01671 | B48: 12-08-2023 | C48: Doubtnut | D48: Language Learning | E48: English Communication | F48: Mumbai | G48: Maharashtra | H48: Tier 1 | I48: Female | J48: 25-34 | K48: YouTube | L48: Net Banking | M48: Mobile | N48: 4999 | O48: 0 | P48: 0 | Q48: 4999 | R48: 899.82 | S48: 4099.18 | T48: 1743.29 | U48: 2355.89 | V48: 57.47 | W48: Yes | X48: 3.1 | Y48: No | Z48: 0 | AA48: =TRIM(PROPER(F48)) -> Mumbai | AB48: =TRIM(PROPER(C48)) -> Doubtnut | AC48: =IF(O48=0,"No Discount",IF(O48<=15,"Low (1-15%)",IF(O48<=30,"Medium (16-30%)","High (>30%)"))) -> No Discount | AD48: =IF(V48<0,"Loss Making",IF(V48<20,"Low Margin","Healthy Margin")) -> Healthy Margin | AE48: =TEXT(DATE(VALUE(RIGHT(B48,4)),VALUE(MID(B48,4,2)),VALUE(LEFT(B48,2))),"MMM-YYYY") -> Aug-2023 | AF48: =VALUE(RIGHT(B48,4)) -> 2023 | AG48: =CHOOSE(ROUNDUP(VALUE(MID(B48,4,2))/3,0),"Q1","Q2","Q3","Q4") -> Q3
A49: EDU01426 | B49: 26-06-2023 | C49: Extramarks | D49: Test Preparation | E49: GRE Verbal+Quant | F49: Ahmedabad | G49: Gujarat | H49: Tier 1 | I49: Other | J49: 13-17 | K49: Word of Mouth | L49: Net Banking | M49: Desktop | N49: 11999 | O49: 10 | P49: 1199.9 | Q49: 10799.1 | R49: 1943.84 | S49: 8855.26 | T49: 4140.28 | U49: 4714.98 | V49: 53.24 | W49: Yes | Y49: No | Z49: 0 | AA49: =TRIM(PROPER(F49)) -> Ahmedabad | AB49: =TRIM(PROPER(C49)) -> Extramarks | AC49: =IF(O49=0,"No Discount",IF(O49<=15,"Low (1-15%)",IF(O49<=30,"Medium (16-30%)","High (>30%)"))) -> Low (1-15%) | AD49: =IF(V49<0,"Loss Making",IF(V49<20,"Low Margin","Healthy Margin")) -> Healthy Margin | AE49: =TEXT(DATE(VALUE(RIGHT(B49,4)),VALUE(MID(B49,4,2)),VALUE(LEFT(B49,2))),"MMM-YYYY") -> Jun-2023 | AF49: =VALUE(RIGHT(B49,4)) -> 2023 | AG49: =CHOOSE(ROUNDUP(VALUE(MID(B49,4,2))/3,0),"Q1","Q2","Q3","Q4") -> Q2
A50: EDU02418 | B50: 21-12-2024 | C50: Meritnation | D50: Professional Upskilling | E50: HR Management | F50: Mumbai | G50: Maharashtra | H50: Tier 1 | I50: Male | J50: 45+ | K50: School/College Partnership | L50: Debit Card | M50: Desktop | N50: 8999 | O50: 0 | P50: 0 | Q50: 8999 | R50: 1619.82 | S50: 7379.18 | T50: 3259.12 | U50: 4120.06 | V50: 55.83 | W50: Yes | X50: 4.5 | Y50: No | Z50: 0 | AA50: =TRIM(PROPER(F50)) -> Mumbai | AB50: =TRIM(PROPER(C50)) -> Meritnation | AC50: =IF(O50=0,"No Discount",IF(O50<=15,"Low (1-15%)",IF(O50<=30,"Medium (16-30%)","High (>30%)"))) -> No Discount | AD50: =IF(V50<0,"Loss Making",IF(V50<20,"Low Margin","Healthy Margin")) -> Healthy Margin | AE50: =TEXT(DATE(VALUE(RIGHT(B50,4)),VALUE(MID(B50,4,2)),VALUE(LEFT(B50,2))),"MMM-YYYY") -> Dec-2024 | AF50: =VALUE(RIGHT(B50,4)) -> 2024 | AG50: =CHOOSE(ROUNDUP(VALUE(MID(B50,4,2))/3,0),"Q1","Q2","Q3","Q4") -> Q4
A51: EDU02069 | B51: 11-09-2024 | C51: Scaler | D51: Language Learning | E51: IELTS Preparation | F51: NOIDA | G51: Delhi NCR | H51: Tier 1 | I51: Male | J51: 13-17 | K51: Email Campaign | L51: Net Banking | M51: Desktop | N51: 8999 | O51: 0 | P51: 0 | Q51: 8999 | R51: 1619.82 | S51: 7379.18 | T51: 2457.09 | U51: 4922.09 | V51: 66.7 | W51: Yes | X51: 3.8 | Y51: No | Z51: 0 | AA51: =TRIM(PROPER(F51)) -> Noida | AB51: =TRIM(PROPER(C51)) -> Scaler | AC51: =IF(O51=0,"No Discount",IF(O51<=15,"Low (1-15%)",IF(O51<=30,"Medium (16-30%)","High (>30%)"))) -> No Discount | AD51: =IF(V51<0,"Loss Making",IF(V51<20,"Low Margin","Healthy Margin")) -> Healthy Margin | AE51: =TEXT(DATE(VALUE(RIGHT(B51,4)),VALUE(MID(B51,4,2)),VALUE(LEFT(B51,2))),"MMM-YYYY") -> Sep-2024 | AF51: =VALUE(RIGHT(B51,4)) -> 2024 | AG51: =CHOOSE(ROUNDUP(VALUE(MID(B51,4,2))/3,0),"Q1","Q2","Q3","Q4") -> Q3
A52: EDU02322 | B52: 16-09-2023 | C52: Physics Wallah | D52: Creative Arts | E52: UI/UX Design | F52: Chennai | G52: Tamil Nadu | H52: Tier 1 | I52: Male | J52: 18-24 | K52: Google Ads | L52: Credit Card | M52: Mobile | N52: 14999 | O52: 15 | P52: 2249.85 | Q52: 12749.15 | R52: 2294.85 | S52: 10454.3 | T52: 3767.51 | U52: 6686.79 | V52: 63.96 | W52: No | Y52: No | Z52: 0 | AA52: =TRIM(PROPER(F52)) -> Chennai | AB52: =TRIM(PROPER(C52)) -> Physics Wallah | AC52: =IF(O52=0,"No Discount",IF(O52<=15,"Low (1-15%)",IF(O52<=30,"Medium (16-30%)","High (>30%)"))) -> Low (1-15%) | AD52: =IF(V52<0,"Loss Making",IF(V52<20,"Low Margin","Healthy Margin")) -> Healthy Margin | AE52: =TEXT(DATE(VALUE(RIGHT(B52,4)),VALUE(MID(B52,4,2)),VALUE(LEFT(B52,2))),"MMM-YYYY") -> Sep-2023 | AF52: =VALUE(RIGHT(B52,4)) -> 2023 | AG52: =CHOOSE(ROUNDUP(VALUE(MID(B52,4,2))/3,0),"Q1","Q2","Q3","Q4") -> Q3
A53: EDU01252 | B53: 01-04-2024 | C53: Meritnation | D53: Competitive Exams | E53: UPSC GS Foundation | F53: New Delhi | G53: Delhi NCR | H53: Tier 1 | I53: Other | J53: 45+ | K53: Instagram | L53: EMI | M53: Desktop | N53: 18999 | O53: 30 | P53: 5699.7 | Q53: 13299.3 | R53: 2393.87 | S53: 10905.43 | T53: 3801 | U53: 7104.43 | V53: 65.15 | W53: No | Y53: No | Z53: 0 | AA53: =TRIM(PROPER(F53)) -> New Delhi | AB53: =TRIM(PROPER(C53)) -> Meritnation | AC53: =IF(O53=0,"No Discount",IF(O53<=15,"Low (1-15%)",IF(O53<=30,"Medium (16-30%)","High (>30%)"))) -> Medium (16-30%) | AD53: =IF(V53<0,"Loss Making",IF(V53<20,"Low Margin","Healthy Margin")) -> Healthy Margin | AE53: =TEXT(DATE(VALUE(RIGHT(B53,4)),VALUE(MID(B53,4,2)),VALUE(LEFT(B53,2))),"MMM-YYYY") -> Apr-2024 | AF53: =VALUE(RIGHT(B53,4)) -> 2024 | AG53: =CHOOSE(ROUNDUP(VALUE(MID(B53,4,2))/3,0),"Q1","Q2","Q3","Q4") -> Q2
A54: EDU00064 | B54: 15-10-2024 | C54: BYJU'S | D54: K-12 Academics | E54: Class 11-12 PCB | F54: Hyderabad | G54: Telangana | H54: Tier 1 | I54: Male | J54: 25-34 | K54: Direct/Organic | L54: UPI | M54: Mobile | N54: 8499 | O54: 20 | P54: 1699.8 | Q54: 6799.2 | R54: 1223.86 | S54: 5575.34 | T54: 2054.91 | U54: 3520.43 | V54: 63.14 | W54: Yes | X54: 3.6 | Y54: No | Z54: 0 | AA54: =TRIM(PROPER(F54)) -> Hyderabad | AB54: =TRIM(PROPER(C54)) -> Byju'S | AC54: =IF(O54=0,"No Discount",IF(O54<=15,"Low (1-15%)",IF(O54<=30,"Medium (16-30%)","High (>30%)"))) -> Medium (16-30%) | AD54: =IF(V54<0,"Loss Making",IF(V54<20,"Low Margin","Healthy Margin")) -> Healthy Margin | AE54: =TEXT(DATE(VALUE(RIGHT(B54,4)),VALUE(MID(B54,4,2)),VALUE(LEFT(B54,2))),"MMM-YYYY") -> Oct-2024 | AF54: =VALUE(RIGHT(B54,4)) -> 2024 | AG54: =CHOOSE(ROUNDUP(VALUE(MID(B54,4,2))/3,0),"Q1","Q2","Q3","Q4") -> Q4
A55: EDU01716 | B55: 05-11-2023 | C55: Leverage Edu | D55: Competitive Exams | E55: NEET Complete Course | F55: Nagpur | G55: Maharashtra | H55: Tier 2 | I55: Male | J55: 35-44 | K55: YouTube | L55: UPI | M55: Mobile | N55: 22999 | O55: 15 | P55: 3449.85 | Q55: 19549.15 | R55: 3518.85 | S55: 16030.3 | T55: 7740.39 | U55: 8289.91 | V55: 51.71 | W55: Yes | X55: 4.5 | Y55: No | Z55: 0 | AA55: =TRIM(PROPER(F55)) -> Nagpur | AB55: =TRIM(PROPER(C55)) -> Leverage Edu | AC55: =IF(O55=0,"No Discount",IF(O55<=15,"Low (1-15%)",IF(O55<=30,"Medium (16-30%)","High (>30%)"))) -> Low (1-15%) | AD55: =IF(V55<0,"Loss Making",IF(V55<20,"Low Margin","Healthy Margin")) -> Healthy Margin | AE55: =TEXT(DATE(VALUE(RIGHT(B55,4)),VALUE(MID(B55,4,2)),VALUE(LEFT(B55,2))),"MMM-YYYY") -> Nov-2023 | AF55: =VALUE(RIGHT(B55,4)) -> 2023 | AG55: =CHOOSE(ROUNDUP(VALUE(MID(B55,4,2))/3,0),"Q1","Q2","Q3","Q4") -> Q4
A56: EDU00859 | B56: 09-07-2024 | C56: Extramarks | D56: Language Learning | E56: IELTS Preparation | F56: Jodhpur | G56: Rajasthan | H56: Tier 3 | I56: Other | J56: 35-44 | K56: YouTube | L56: Debit Card | M56: Desktop | N56: 8999 | O56: 0 | P56: 0 | Q56: 8999 | R56: 1619.82 | S56: 7379.18 | T56: 3525.06 | U56: 3854.12 | V56: 52.23 | W56: Yes | X56: 3.3 | Y56: No | Z56: 0 | AA56: =TRIM(PROPER(F56)) -> Jodhpur | AB56: =TRIM(PROPER(C56)) -> Extramarks | AC56: =IF(O56=0,"No Discount",IF(O56<=15,"Low (1-15%)",IF(O56<=30,"Medium (16-30%)","High (>30%)"))) -> No Discount | AD56: =IF(V56<0,"Loss Making",IF(V56<20,"Low Margin","Healthy Margin")) -> Healthy Margin | AE56: =TEXT(DATE(VALUE(RIGHT(B56,4)),VALUE(MID(B56,4,2)),VALUE(LEFT(B56,2))),"MMM-YYYY") -> Jul-2024 | AF56: =VALUE(RIGHT(B56,4)) -> 2024 | AG56: =CHOOSE(ROUNDUP(VALUE(MID(B56,4,2))/3,0),"Q1","Q2","Q3","Q4") -> Q3
A57: EDU00948 | B57: 11-07-2024 | C57: WhiteHat Jr | D57: Higher Education | E57: MBA Finance Prep | F57: Madurai | G57: Tamil Nadu | H57: Tier 3 | I57: Other | J57: 35-44 | K57: School/College Partnership | L57: Debit Card | M57: Mobile | N57: 11999 | O57: 40 | P57: 4799.6 | Q57: 7199.4 | R57: 1295.89 | S57: 5903.51 | T57: 3463.78 | U57: 2439.73 | V57: 41.33 | W57: Yes | X57: 3.3 | Y57: No | Z57: 0 | AA57: =TRIM(PROPER(F57)) -> Madurai | AB57: =TRIM(PROPER(C57)) -> Whitehat Jr | AC57: =IF(O57=0,"No Discount",IF(O57<=15,"Low (1-15%)",IF(O57<=30,"Medium (16-30%)","High (>30%)"))) -> High (>30%) | AD57: =IF(V57<0,"Loss Making",IF(V57<20,"Low Margin","Healthy Margin")) -> Healthy Margin | AE57: =TEXT(DATE(VALUE(RIGHT(B57,4)),VALUE(MID(B57,4,2)),VALUE(LEFT(B57,2))),"MMM-YYYY") -> Jul-2024 | AF57: =VALUE(RIGHT(B57,4)) -> 2024 | AG57: =CHOOSE(ROUNDUP(VALUE(MID(B57,4,2))/3,0),"Q1","Q2","Q3","Q4") -> Q3
A58: EDU02145 | B58: 03-04-2023 | C58: Scaler | D58: Higher Education | E58: MBA Finance Prep | F58: Madurai | G58: Tamil Nadu | H58: Tier 3 | I58: Female | J58: 45+ | K58: School/College Partnership | L58: Net Banking | M58: Tablet | N58: 11999 | O58: 0 | P58: 0 | Q58: 11999 | R58: 2159.82 | S58: 9839.18 | T58: 4296.21 | U58: 5542.97 | V58: 56.34 | W58: No | Y58: No | Z58: 0 | AA58: =TRIM(PROPER(F58)) -> Madurai | AB58: =TRIM(PROPER(C58)) -> Scaler | AC58: =IF(O58=0,"No Discount",IF(O58<=15,"Low (1-15%)",IF(O58<=30,"Medium (16-30%)","High (>30%)"))) -> No Discount | AD58: =IF(V58<0,"Loss Making",IF(V58<20,"Low Margin","Healthy Margin")) -> Healthy Margin | AE58: =TEXT(DATE(VALUE(RIGHT(B58,4)),VALUE(MID(B58,4,2)),VALUE(LEFT(B58,2))),"MMM-YYYY") -> Apr-2023 | AF58: =VALUE(RIGHT(B58,4)) -> 2023 | AG58: =CHOOSE(ROUNDUP(VALUE(MID(B58,4,2))/3,0),"Q1","Q2","Q3","Q4") -> Q2
A59: EDU00357 | B59: 15-09-2023 | C59: Leverage Edu | D59: Test Preparation | E59: SAT Complete Prep | F59: Pune | G59: Maharashtra | H59: Tier 1 | I59: Other | J59: 45+ | K59: Word of Mouth | L59: Wallet | M59: Mobile | N59: 12999 | O59: 40 | P59: 5199.6 | Q59: 7799.4 | R59: 1403.89 | S59: 6395.51 | T59: 3096.5 | U59: 3299.01 | V59: 51.58 | W59: No | Y59: No | Z59: 0 | AA59: =TRIM(PROPER(F59)) -> Pune | AB59: =TRIM(PROPER(C59)) -> Leverage Edu | AC59: =IF(O59=0,"No Discount",IF(O59<=15,"Low (1-15%)",IF(O59<=30,"Medium (16-30%)","High (>30%)"))) -> High (>30%) | AD59: =IF(V59<0,"Loss Making",IF(V59<20,"Low Margin","Healthy Margin")) -> Healthy Margin | AE59: =TEXT(DATE(VALUE(RIGHT(B59,4)),VALUE(MID(B59,4,2)),VALUE(LEFT(B59,2))),"MMM-YYYY") -> Sep-2023 | AF59: =VALUE(RIGHT(B59,4)) -> 2023 | AG59: =CHOOSE(ROUNDUP(VALUE(MID(B59,4,2))/3,0),"Q1","Q2","Q3","Q4") -> Q3
A60: EDU00271 | B60: 04-11-2024 | C60: Extramarks | D60: Coding & Tech | E60: Python for Beginners | F60: Chennai | G60: Tamil Nadu | H60: Tier 1 | I60: Female | J60: 13-17 | K60: YouTube | L60: Wallet | M60: Desktop | N60: 7999 | O60: 5 | P60: 399.95 | Q60: 7599.05 | R60: 1367.83 | S60: 6231.22 | T60: 2645.48 | U60: 3585.74 | V60: 57.54 | W60: Yes | X60: 4.5 | Y60: No | Z60: 0 | AA60: =TRIM(PROPER(F60)) -> Chennai | AB60: =TRIM(PROPER(C60)) -> Extramarks | AC60: =IF(O60=0,"No Discount",IF(O60<=15,"Low (1-15%)",IF(O60<=30,"Medium (16-30%)","High (>30%)"))) -> Low (1-15%) | AD60: =IF(V60<0,"Loss Making",IF(V60<20,"Low Margin","Healthy Margin")) -> Healthy Margin | AE60: =TEXT(DATE(VALUE(RIGHT(B60,4)),VALUE(MID(B60,4,2)),VALUE(LEFT(B60,2))),"MMM-YYYY") -> Nov-2024 | AF60: =VALUE(RIGHT(B60,4)) -> 2024 | AG60: =CHOOSE(ROUNDUP(VALUE(MID(B60,4,2))/3,0),"Q1","Q2","Q3","Q4") -> Q4
A61: EDU02112 | B61: 23-06-2023 | C61: Scaler | D61: Coding & Tech | E61: Full Stack Development | F61: Ahmedabad | G61: Gujarat | H61: Tier 1 | I61: Male | J61: 35-44 | K61: School/College Partnership | L61: Wallet | M61: Mobile | N61: 29999 | O61: 40 | P61: 11999.6 | Q61: 17999.4 | R61: 3239.89 | S61: 14759.51 | T61: 8037.87 | U61: 6721.64 | V61: 45.54 | W61: Yes | X61: 3.6 | Y61: No | Z61: 0 | AA61: =TRIM(PROPER(F61)) -> Ahmedabad | AB61: =TRIM(PROPER(C61)) -> Scaler | AC61: =IF(O61=0,"No Discount",IF(O61<=15,"Low (1-15%)",IF(O61<=30,"Medium (16-30%)","High (>30%)"))) -> High (>30%) | AD61: =IF(V61<0,"Loss Making",IF(V61<20,"Low Margin","Healthy Margin")) -> Healthy Margin | AE61: =TEXT(DATE(VALUE(RIGHT(B61,4)),VALUE(MID(B61,4,2)),VALUE(LEFT(B61,2))),"MMM-YYYY") -> Jun-2023 | AF61: =VALUE(RIGHT(B61,4)) -> 2023 | AG61: =CHOOSE(ROUNDUP(VALUE(MID(B61,4,2))/3,0),"Q1","Q2","Q3","Q4") -> Q2
A62: EDU01938 | B62: 07-12-2024 | C62: Physics Wallah | D62: Language Learning | E62: IELTS Preparation | F62: Faridabad | G62: Delhi NCR | H62: Tier 2 | I62: Male | J62: 25-34 | K62: Google Ads | L62: Wallet | M62: Mobile | N62: 8999 | O62: 50 | P62: 4499.5 | Q62: 4499.5 | R62: 809.91 | S62: 3689.59 | T62: 1907.33 | U62: 1782.26 | V62: 48.31 | W62: No | Y62: No | Z62: 1 | AA62: =TRIM(PROPER(F62)) -> Faridabad | AB62: =TRIM(PROPER(C62)) -> Physics Wallah | AC62: =IF(O62=0,"No Discount",IF(O62<=15,"Low (1-15%)",IF(O62<=30,"Medium (16-30%)","High (>30%)"))) -> High (>30%) | AD62: =IF(V62<0,"Loss Making",IF(V62<20,"Low Margin","Healthy Margin")) -> Healthy Margin | AE62: =TEXT(DATE(VALUE(RIGHT(B62,4)),VALUE(MID(B62,4,2)),VALUE(LEFT(B62,2))),"MMM-YYYY") -> Dec-2024 | AF62: =VALUE(RIGHT(B62,4)) -> 2024 | AG62: =CHOOSE(ROUNDUP(VALUE(MID(B62,4,2))/3,0),"Q1","Q2","Q3","Q4") -> Q4
A63: EDU00807 | B63: 11-02-2024 | C63: Toppr | D63: Higher Education | E63: BBA Business Basics | F63: Hyderabad | G63: Telangana | H63: Tier 1 | I63: Other | J63: 13-17 | K63: Direct/Organic | L63: Wallet | M63: Desktop | N63: 7499 | O63: 50 | P63: 3749.5 | Q63: 3749.5 | R63: 674.91 | S63: 3074.59 | T63: 1257.82 | U63: 1816.77 | V63: 59.09 | W63: Yes | X63: 3.7 | Y63: No | Z63: 0 | AA63: =TRIM(PROPER(F63)) -> Hyderabad | AB63: =TRIM(PROPER(C63)) -> Toppr | AC63: =IF(O63=0,"No Discount",IF(O63<=15,"Low (1-15%)",IF(O63<=30,"Medium (16-30%)","High (>30%)"))) -> High (>30%) | AD63: =IF(V63<0,"Loss Making",IF(V63<20,"Low Margin","Healthy Margin")) -> Healthy Margin | AE63: =TEXT(DATE(VALUE(RIGHT(B63,4)),VALUE(MID(B63,4,2)),VALUE(LEFT(B63,2))),"MMM-YYYY") -> Feb-2024 | AF63: =VALUE(RIGHT(B63,4)) -> 2024 | AG63: =CHOOSE(ROUNDUP(VALUE(MID(B63,4,2))/3,0),"Q1","Q2","Q3","Q4") -> Q1
A64: EDU00504 | B64: 07-07-2024 | C64: Unacademy | D64: Higher Education | E64: B.Tech CSE Support | F64: Madurai | G64: Tamil Nadu | H64: Tier 3 | I64: Female | J64: 13-17 | K64: Instagram | L64: Net Banking | M64: Desktop | N64: 9999 | O64: 20 | P64: 1999.8 | Q64: 7999.2 | R64: 1439.86 | S64: 6559.34 | T64: 2560.13 | U64: 3999.21 | V64: 60.97 | W64: No | Y64: Yes | Z64: 1 | AA64: =TRIM(PROPER(F64)) -> Madurai | AB64: =TRIM(PROPER(C64)) -> Unacademy | AC64: =IF(O64=0,"No Discount",IF(O64<=15,"Low (1-15%)",IF(O64<=30,"Medium (16-30%)","High (>30%)"))) -> Medium (16-30%) | AD64: =IF(V64<0,"Loss Making",IF(V64<20,"Low Margin","Healthy Margin")) -> Healthy Margin | AE64: =TEXT(DATE(VALUE(RIGHT(B64,4)),VALUE(MID(B64,4,2)),VALUE(LEFT(B64,2))),"MMM-YYYY") -> Jul-2024 | AF64: =VALUE(RIGHT(B64,4)) -> 2024 | AG64: =CHOOSE(ROUNDUP(VALUE(MID(B64,4,2))/3,0),"Q1","Q2","Q3","Q4") -> Q3
A65: EDU00122 | B65: 25-04-2024 | C65: Doubtnut | D65: Coding & Tech | E65: Data Science Masters | F65: Madurai | G65: Tamil Nadu | H65: Tier 3 | I65: Female | J65: 35-44 | K65: Direct/Organic | L65: UPI | M65: Mobile | N65: 34999 | O65: 30 | P65: 10499.7 | Q65: 24499.3 | R65: 4409.87 | S65: 20089.43 | T65: 7641.14 | U65: 12448.29 | V65: 61.96 | W65: Yes | X65: 3.9 | Y65: No | Z65: 0 | AA65: =TRIM(PROPER(F65)) -> Madurai | AB65: =TRIM(PROPER(C65)) -> Doubtnut | AC65: =IF(O65=0,"No Discount",IF(O65<=15,"Low (1-15%)",IF(O65<=30,"Medium (16-30%)","High (>30%)"))) -> Medium (16-30%) | AD65: =IF(V65<0,"Loss Making",IF(V65<20,"Low Margin","Healthy Margin")) -> Healthy Margin | AE65: =TEXT(DATE(VALUE(RIGHT(B65,4)),VALUE(MID(B65,4,2)),VALUE(LEFT(B65,2))),"MMM-YYYY") -> Apr-2024 | AF65: =VALUE(RIGHT(B65,4)) -> 2024 | AG65: =CHOOSE(ROUNDUP(VALUE(MID(B65,4,2))/3,0),"Q1","Q2","Q3","Q4") -> Q2
A66: EDU00197 | B66: 15-08-2023 | C66: Toppr | D66: Coding & Tech | E66: Python for Beginners | F66: Coimbatore | G66: Tamil Nadu | H66: Tier 2 | I66: Male | J66: 35-44 | K66: Direct/Organic | L66: UPI | M66: Desktop | N66: 7999 | O66: 25 | P66: 1999.75 | Q66: 5999.25 | R66: 1079.87 | S66: 4919.38 | T66: 1713.33 | U66: 3206.05 | V66: 65.17 | W66: No | Y66: No | Z66: 0 | AA66: =TRIM(PROPER(F66)) -> Coimbatore | AB66: =TRIM(PROPER(C66)) -> Toppr | AC66: =IF(O66=0,"No Discount",IF(O66<=15,"Low (1-15%)",IF(O66<=30,"Medium (16-30%)","High (>30%)"))) -> Medium (16-30%) | AD66: =IF(V66<0,"Loss Making",IF(V66<20,"Low Margin","Healthy Margin")) -> Healthy Margin | AE66: =TEXT(DATE(VALUE(RIGHT(B66,4)),VALUE(MID(B66,4,2)),VALUE(LEFT(B66,2))),"MMM-YYYY") -> Aug-2023 | AF66: =VALUE(RIGHT(B66,4)) -> 2023 | AG66: =CHOOSE(ROUNDUP(VALUE(MID(B66,4,2))/3,0),"Q1","Q2","Q3","Q4") -> Q3
A67: EDU01654 | B67: 03-11-2023 | C67: Scaler | D67: Professional Upskilling | E67: Financial Modelling | F67: Kolkata | G67: West Bengal | H67: Tier 1 | I67: Other | J67: 25-34 | K67: WhatsApp | L67: Credit Card | M67: Tablet | N67: 15999 | O67: 0 | P67: 0 | Q67: 15999 | R67: 2879.82 | S67: 13119.18 | T67: 4948.23 | U67: 8170.95 | V67: 62.28 | W67: Yes | X67: 4.5 | Y67: No | Z67: 0 | AA67: =TRIM(PROPER(F67)) -> Kolkata | AB67: =TRIM(PROPER(C67)) -> Scaler | AC67: =IF(O67=0,"No Discount",IF(O67<=15,"Low (1-15%)",IF(O67<=30,"Medium (16-30%)","High (>30%)"))) -> No Discount | AD67: =IF(V67<0,"Loss Making",IF(V67<20,"Low Margin","Healthy Margin")) -> Healthy Margin | AE67: =TEXT(DATE(VALUE(RIGHT(B67,4)),VALUE(MID(B67,4,2)),VALUE(LEFT(B67,2))),"MMM-YYYY") -> Nov-2023 | AF67: =VALUE(RIGHT(B67,4)) -> 2023 | AG67: =CHOOSE(ROUNDUP(VALUE(MID(B67,4,2))/3,0),"Q1","Q2","Q3","Q4") -> Q4
A68: EDU01140 | B68: 08-12-2023 | C68: BYJU'S | D68: Competitive Exams | E68: GATE CS Complete | F68: Surat | G68: Gujarat | H68: Tier 2 | I68: Other | J68: 18-24 | K68: Instagram | L68: EMI | M68: Desktop | N68: 12999 | O68: 0 | P68: 0 | Q68: 12999 | R68: 2339.82 | S68: 10659.18 | T68: 3905.05 | U68: 6754.13 | V68: 63.36 | W68: No | Y68: No | Z68: 3 | AA68: =TRIM(PROPER(F68)) -> Surat | AB68: =TRIM(PROPER(C68)) -> Byju'S | AC68: =IF(O68=0,"No Discount",IF(O68<=15,"Low (1-15%)",IF(O68<=30,"Medium (16-30%)","High (>30%)"))) -> No Discount | AD68: =IF(V68<0,"Loss Making",IF(V68<20,"Low Margin","Healthy Margin")) -> Healthy Margin | AE68: =TEXT(DATE(VALUE(RIGHT(B68,4)),VALUE(MID(B68,4,2)),VALUE(LEFT(B68,2))),"MMM-YYYY") -> Dec-2023 | AF68: =VALUE(RIGHT(B68,4)) -> 2023 | AG68: =CHOOSE(ROUNDUP(VALUE(MID(B68,4,2))/3,0),"Q1","Q2","Q3","Q4") -> Q4
A69: EDU01344 | B69: 18-04-2024 | C69: Great Learning | D69: Higher Education | E69: BBA Business Basics | F69: Nagpur | G69: Maharashtra | H69: Tier 2 | I69: Other | J69: 13-17 | K69: Instagram | L69: Net Banking | M69: Mobile | N69: 7499 | O69: 0 | P69: 0 | Q69: 7499 | R69: 1349.82 | S69: 6149.18 | T69: 2922.4 | U69: 3226.78 | V69: 52.47 | W69: Yes | X69: 3.8 | Y69: No | Z69: 1 | AA69: =TRIM(PROPER(F69)) -> Nagpur | AB69: =TRIM(PROPER(C69)) -> Great Learning | AC69: =IF(O69=0,"No Discount",IF(O69<=15,"Low (1-15%)",IF(O69<=30,"Medium (16-30%)","High (>30%)"))) -> No Discount | AD69: =IF(V69<0,"Loss Making",IF(V69<20,"Low Margin","Healthy Margin")) -> Healthy Margin | AE69: =TEXT(DATE(VALUE(RIGHT(B69,4)),VALUE(MID(B69,4,2)),VALUE(LEFT(B69,2))),"MMM-YYYY") -> Apr-2024 | AF69: =VALUE(RIGHT(B69,4)) -> 2024 | AG69: =CHOOSE(ROUNDUP(VALUE(MID(B69,4,2))/3,0),"Q1","Q2","Q3","Q4") -> Q2
A70: EDU00588 | B70: 12-08-2024 | C70: Extramarks | D70: Coding & Tech | E70: Full Stack Development | F70: New Delhi | G70: Delhi NCR | H70: Tier 1 | I70: Other | J70: 18-24 | K70: Email Campaign | L70: Credit Card | M70: Mobile | N70: 29999 | O70: 30 | P70: 8999.7 | Q70: 20999.3 | R70: 3779.87 | S70: 17219.43 | T70: 5854.24 | U70: 11365.19 | V70: 66 | W70: Yes | X70: 3.7 | Y70: No | Z70: 0 | AA70: =TRIM(PROPER(F70)) -> New Delhi | AB70: =TRIM(PROPER(C70)) -> Extramarks | AC70: =IF(O70=0,"No Discount",IF(O70<=15,"Low (1-15%)",IF(O70<=30,"Medium (16-30%)","High (>30%)"))) -> Medium (16-30%) | AD70: =IF(V70<0,"Loss Making",IF(V70<20,"Low Margin","Healthy Margin")) -> Healthy Margin | AE70: =TEXT(DATE(VALUE(RIGHT(B70,4)),VALUE(MID(B70,4,2)),VALUE(LEFT(B70,2))),"MMM-YYYY") -> Aug-2024 | AF70: =VALUE(RIGHT(B70,4)) -> 2024 | AG70: =CHOOSE(ROUNDUP(VALUE(MID(B70,4,2))/3,0),"Q1","Q2","Q3","Q4") -> Q3
A71: EDU00733 | B71: 14-05-2023 | C71: Physics Wallah | D71: Creative Arts | E71: UI/UX Design | F71: Pune | G71: Maharashtra | H71: Tier 1 | I71: Other | J71: 18-24 | K71: Google Ads | L71: EMI | M71: Tablet | N71: 14999 | O71: 10 | P71: 1499.9 | Q71: 13499.1 | R71: 2429.84 | S71: 11069.26 | T71: 3872 | U71: 7197.26 | V71: 65.02 | W71: Yes | Y71: No | Z71: 0 | AA71: =TRIM(PROPER(F71)) -> Pune | AB71: =TRIM(PROPER(C71)) -> Physics Wallah | AC71: =IF(O71=0,"No Discount",IF(O71<=15,"Low (1-15%)",IF(O71<=30,"Medium (16-30%)","High (>30%)"))) -> Low (1-15%) | AD71: =IF(V71<0,"Loss Making",IF(V71<20,"Low Margin","Healthy Margin")) -> Healthy Margin | AE71: =TEXT(DATE(VALUE(RIGHT(B71,4)),VALUE(MID(B71,4,2)),VALUE(LEFT(B71,2))),"MMM-YYYY") -> May-2023 | AF71: =VALUE(RIGHT(B71,4)) -> 2023 | AG71: =CHOOSE(ROUNDUP(VALUE(MID(B71,4,2))/3,0),"Q1","Q2","Q3","Q4") -> Q2
A72: EDU01607 | B72: 20-07-2023 | C72: Vedantu | D72: Language Learning | E72: Business English | F72: Noida | G72: Delhi NCR | H72: Tier 1 | I72: Male | J72: 35-44 | K72: School/College Partnership | L72: Credit Card | M72: Tablet | N72: 6999 | O72: 0 | P72: 0 | Q72: 6999 | R72: 1259.82 | S72: 5739.18 | T72: 2961.7 | U72: 2777.48 | V72: 48.4 | W72: No | Y72: No | Z72: 1 | AA72: =TRIM(PROPER(F72)) -> Noida | AB72: =TRIM(PROPER(C72)) -> Vedantu | AC72: =IF(O72=0,"No Discount",IF(O72<=15,"Low (1-15%)",IF(O72<=30,"Medium (16-30%)","High (>30%)"))) -> No Discount | AD72: =IF(V72<0,"Loss Making",IF(V72<20,"Low Margin","Healthy Margin")) -> Healthy Margin | AE72: =TEXT(DATE(VALUE(RIGHT(B72,4)),VALUE(MID(B72,4,2)),VALUE(LEFT(B72,2))),"MMM-YYYY") -> Jul-2023 | AF72: =VALUE(RIGHT(B72,4)) -> 2023 | AG72: =CHOOSE(ROUNDUP(VALUE(MID(B72,4,2))/3,0),"Q1","Q2","Q3","Q4") -> Q3
A73: EDU01390 | B73: 26-10-2024 | C73: upGrad | D73: K-12 Academics | E73: Class 11-12 PCB | F73: Mysuru | G73: Karnataka | H73: Tier 2 | I73: Other | J73: 45+ | K73: Instagram | L73: EMI | M73: Mobile | N73: 8499 | O73: 20 | P73: 1699.8 | Q73: 6799.2 | R73: 1223.86 | S73: 5575.34 | T73: 2840.94 | U73: 2734.4 | V73: 49.04 | W73: Yes | X73: 4.2 | Y73: No | Z73: 0 | AA73: =TRIM(PROPER(F73)) -> Mysuru | AB73: =TRIM(PROPER(C73)) -> Upgrad | AC73: =IF(O73=0,"No Discount",IF(O73<=15,"Low (1-15%)",IF(O73<=30,"Medium (16-30%)","High (>30%)"))) -> Medium (16-30%) | AD73: =IF(V73<0,"Loss Making",IF(V73<20,"Low Margin","Healthy Margin")) -> Healthy Margin | AE73: =TEXT(DATE(VALUE(RIGHT(B73,4)),VALUE(MID(B73,4,2)),VALUE(LEFT(B73,2))),"MMM-YYYY") -> Oct-2024 | AF73: =VALUE(RIGHT(B73,4)) -> 2024 | AG73: =CHOOSE(ROUNDUP(VALUE(MID(B73,4,2))/3,0),"Q1","Q2","Q3","Q4") -> Q4
A74: EDU01076 | B74: 14-05-2023 | C74: Simplilearn | D74: K-12 Academics | E74: Class 8-10 Science Pack | F74: Vadodara | G74: Gujarat | H74: Tier 3 | I74: Female | J74: 35-44 | K74: WhatsApp | L74: Credit Card | M74: Desktop | N74: 4999 | O74: 10 | P74: 499.9 | Q74: 4499.1 | R74: 809.84 | S74: 3689.26 | T74: 1459.22 | U74: 2230.04 | V74: 60.45 | W74: No | Y74: Yes | Z74: 0 | AA74: =TRIM(PROPER(F74)) -> Vadodara | AB74: =TRIM(PROPER(C74)) -> Simplilearn | AC74: =IF(O74=0,"No Discount",IF(O74<=15,"Low (1-15%)",IF(O74<=30,"Medium (16-30%)","High (>30%)"))) -> Low (1-15%) | AD74: =IF(V74<0,"Loss Making",IF(V74<20,"Low Margin","Healthy Margin")) -> Healthy Margin | AE74: =TEXT(DATE(VALUE(RIGHT(B74,4)),VALUE(MID(B74,4,2)),VALUE(LEFT(B74,2))),"MMM-YYYY") -> May-2023 | AF74: =VALUE(RIGHT(B74,4)) -> 2023 | AG74: =CHOOSE(ROUNDUP(VALUE(MID(B74,4,2))/3,0),"Q1","Q2","Q3","Q4") -> Q2
A75: EDU01766 | B75: 19-10-2024 | C75: Physics Wallah | D75: K-12 Academics | E75: Class 8-10 Science Pack | F75: MANGALURU | G75: Karnataka | H75: Tier 3 | I75: Other | J75: 25-34 | K75: Direct/Organic | L75: Credit Card | M75: Mobile | N75: 4999 | O75: 0 | P75: 0 | Q75: 4999 | R75: 899.82 | S75: 4099.18 | T75: 1644.12 | U75: 2455.06 | V75: 59.89 | W75: No | Y75: No | Z75: 0 | AA75: =TRIM(PROPER(F75)) -> Mangaluru | AB75: =TRIM(PROPER(C75)) -> Physics Wallah | AC75: =IF(O75=0,"No Discount",IF(O75<=15,"Low (1-15%)",IF(O75<=30,"Medium (16-30%)","High (>30%)"))) -> No Discount | AD75: =IF(V75<0,"Loss Making",IF(V75<20,"Low Margin","Healthy Margin")) -> Healthy Margin | AE75: =TEXT(DATE(VALUE(RIGHT(B75,4)),VALUE(MID(B75,4,2)),VALUE(LEFT(B75,2))),"MMM-YYYY") -> Oct-2024 | AF75: =VALUE(RIGHT(B75,4)) -> 2024 | AG75: =CHOOSE(ROUNDUP(VALUE(MID(B75,4,2))/3,0),"Q1","Q2","Q3","Q4") -> Q4
A76: EDU00242 | B76: 31-10-2024 | C76: Toppr | D76: K-12 Academics | E76: Foundation Course | F76: Nagpur | G76: Maharashtra | H76: Tier 2 | I76: Female | J76: 13-17 | K76: Word of Mouth | L76: Credit Card | M76: Tablet | N76: 6999 | O76: 10 | P76: 699.9 | Q76: 6299.1 | R76: 1133.84 | S76: 5165.26 | T76: 2396.43 | U76: 2768.83 | V76: 53.6 | W76: Yes | X76: 3.9 | Y76: No | Z76: 0 | AA76: =TRIM(PROPER(F76)) -> Nagpur | AB76: =TRIM(PROPER(C76)) -> Toppr | AC76: =IF(O76=0,"No Discount",IF(O76<=15,"Low (1-15%)",IF(O76<=30,"Medium (16-30%)","High (>30%)"))) -> Low (1-15%) | AD76: =IF(V76<0,"Loss Making",IF(V76<20,"Low Margin","Healthy Margin")) -> Healthy Margin | AE76: =TEXT(DATE(VALUE(RIGHT(B76,4)),VALUE(MID(B76,4,2)),VALUE(LEFT(B76,2))),"MMM-YYYY") -> Oct-2024 | AF76: =VALUE(RIGHT(B76,4)) -> 2024 | AG76: =CHOOSE(ROUNDUP(VALUE(MID(B76,4,2))/3,0),"Q1","Q2","Q3","Q4") -> Q4
A77: EDU00279 | B77: 08-03-2023 | C77: WhiteHat Jr | D77: Test Preparation | E77: SAT Complete Prep | F77: Pune | G77: Maharashtra | H77: Tier 1 | I77: Female | J77: 13-17 | K77: Google Ads | L77: Net Banking | M77: Mobile | N77: 12999 | O77: 0 | P77: 0 | Q77: 12999 | R77: 2339.82 | S77: 10659.18 | T77: 4236.8 | U77: 6422.38 | V77: 60.25 | W77: No | Y77: No | Z77: 1 | AA77: =TRIM(PROPER(F77)) -> Pune | AB77: =TRIM(PROPER(C77)) -> Whitehat Jr | AC77: =IF(O77=0,"No Discount",IF(O77<=15,"Low (1-15%)",IF(O77<=30,"Medium (16-30%)","High (>30%)"))) -> No Discount | AD77: =IF(V77<0,"Loss Making",IF(V77<20,"Low Margin","Healthy Margin")) -> Healthy Margin | AE77: =TEXT(DATE(VALUE(RIGHT(B77,4)),VALUE(MID(B77,4,2)),VALUE(LEFT(B77,2))),"MMM-YYYY") -> Mar-2023 | AF77: =VALUE(RIGHT(B77,4)) -> 2023 | AG77: =CHOOSE(ROUNDUP(VALUE(MID(B77,4,2))/3,0),"Q1","Q2","Q3","Q4") -> Q1
A78: EDU01932 | B78: 04-01-2023 | C78: Vedantu | D78: Test Preparation | E78: GMAT Focus Edition | F78: Hyderabad | G78: Telangana | H78: Tier 1 | I78: Female | J78: 13-17 | K78: WhatsApp | L78: UPI | M78: Tablet | N78: 16999 | O78: 0 | P78: 0 | Q78: 16999 | R78: 3059.82 | S78: 13939.18 | T78: 5518.11 | U78: 8421.07 | V78: 60.41 | W78: No | Y78: No | Z78: 1 | AA78: =TRIM(PROPER(F78)) -> Hyderabad | AB78: =TRIM(PROPER(C78)) -> Vedantu | AC78: =IF(O78=0,"No Discount",IF(O78<=15,"Low (1-15%)",IF(O78<=30,"Medium (16-30%)","High (>30%)"))) -> No Discount | AD78: =IF(V78<0,"Loss Making",IF(V78<20,"Low Margin","Healthy Margin")) -> Healthy Margin | AE78: =TEXT(DATE(VALUE(RIGHT(B78,4)),VALUE(MID(B78,4,2)),VALUE(LEFT(B78,2))),"MMM-YYYY") -> Jan-2023 | AF78: =VALUE(RIGHT(B78,4)) -> 2023 | AG78: =CHOOSE(ROUNDUP(VALUE(MID(B78,4,2))/3,0),"Q1","Q2","Q3","Q4") -> Q1
A79: EDU02287 | B79: 26-10-2023 | C79: Doubtnut | D79: K-12 Academics | E79: Foundation Course | F79: Jaipur | G79: Rajasthan | H79: Tier 2 | I79: Other | J79: 18-24 | K79: Instagram | L79: Debit Card | M79: Desktop | N79: 6999 | O79: 0 | P79: 0 | Q79: 6999 | R79: 1259.82 | S79: 5739.18 | T79: 2768.27 | U79: 2970.91 | V79: 51.77 | W79: Yes | X79: 3 | Y79: No | Z79: 1 | AA79: =TRIM(PROPER(F79)) -> Jaipur | AB79: =TRIM(PROPER(C79)) -> Doubtnut | AC79: =IF(O79=0,"No Discount",IF(O79<=15,"Low (1-15%)",IF(O79<=30,"Medium (16-30%)","High (>30%)"))) -> No Discount | AD79: =IF(V79<0,"Loss Making",IF(V79<20,"Low Margin","Healthy Margin")) -> Healthy Margin | AE79: =TEXT(DATE(VALUE(RIGHT(B79,4)),VALUE(MID(B79,4,2)),VALUE(LEFT(B79,2))),"MMM-YYYY") -> Oct-2023 | AF79: =VALUE(RIGHT(B79,4)) -> 2023 | AG79: =CHOOSE(ROUNDUP(VALUE(MID(B79,4,2))/3,0),"Q1","Q2","Q3","Q4") -> Q4
A80: EDU02382 | B80: 25-09-2024 | C80: BYJU'S | D80: Language Learning | E80: English Communication | F80: Jodhpur | G80: Rajasthan | H80: Tier 3 | I80: Male | J80: 18-24 | K80: Google Ads | L80: Credit Card | M80: Tablet | N80: 4999 | O80: 0 | P80: 0 | Q80: 4999 | R80: 899.82 | S80: 4099.18 | T80: 1718.76 | U80: 2380.42 | V80: 58.07 | W80: Yes | X80: 4.4 | Y80: No | Z80: 0 | AA80: =TRIM(PROPER(F80)) -> Jodhpur | AB80: =TRIM(PROPER(C80)) -> Byju'S | AC80: =IF(O80=0,"No Discount",IF(O80<=15,"Low (1-15%)",IF(O80<=30,"Medium (16-30%)","High (>30%)"))) -> No Discount | AD80: =IF(V80<0,"Loss Making",IF(V80<20,"Low Margin","Healthy Margin")) -> Healthy Margin | AE80: =TEXT(DATE(VALUE(RIGHT(B80,4)),VALUE(MID(B80,4,2)),VALUE(LEFT(B80,2))),"MMM-YYYY") -> Sep-2024 | AF80: =VALUE(RIGHT(B80,4)) -> 2024 | AG80: =CHOOSE(ROUNDUP(VALUE(MID(B80,4,2))/3,0),"Q1","Q2","Q3","Q4") -> Q3
A81: EDU02054 | B81: 08-06-2023 | C81: upGrad | D81: K-12 Academics | E81: Class 8-10 Science Pack | F81: Ghaziabad | G81: Delhi NCR | H81: Tier 2 | I81: Male | J81: 35-44 | K81: WhatsApp | L81: Credit Card | M81: Tablet | N81: 4999 | O81: 0 | P81: 0 | Q81: 4999 | R81: 899.82 | S81: 4099.18 | T81: 1761.8 | U81: 2337.38 | V81: 57.02 | W81: No | Y81: No | Z81: 0 | AA81: =TRIM(PROPER(F81)) -> Ghaziabad | AB81: =TRIM(PROPER(C81)) -> Upgrad | AC81: =IF(O81=0,"No Discount",IF(O81<=15,"Low (1-15%)",IF(O81<=30,"Medium (16-30%)","High (>30%)"))) -> No Discount | AD81: =IF(V81<0,"Loss Making",IF(V81<20,"Low Margin","Healthy Margin")) -> Healthy Margin | AE81: =TEXT(DATE(VALUE(RIGHT(B81,4)),VALUE(MID(B81,4,2)),VALUE(LEFT(B81,2))),"MMM-YYYY") -> Jun-2023 | AF81: =VALUE(RIGHT(B81,4)) -> 2023 | AG81: =CHOOSE(ROUNDUP(VALUE(MID(B81,4,2))/3,0),"Q1","Q2","Q3","Q4") -> Q2
A82: EDU01839 | B82: 29-03-2024 | C82: upGrad | D82: Higher Education | E82: BBA Business Basics | F82: Jodhpur | G82: Rajasthan | H82: Tier 3 | I82: Female | J82: 18-24 | K82: Word of Mouth | L82: Net Banking | M82: Mobile | N82: 7499 | O82: 15 | P82: 1124.85 | Q82: 6374.15 | R82: 1147.35 | S82: 5226.8 | T82: 2015.98 | U82: 3210.82 | V82: 61.43 | W82: No | Y82: Yes | Z82: 1 | AA82: =TRIM(PROPER(F82)) -> Jodhpur | AB82: =TRIM(PROPER(C82)) -> Upgrad | AC82: =IF(O82=0,"No Discount",IF(O82<=15,"Low (1-15%)",IF(O82<=30,"Medium (16-30%)","High (>30%)"))) -> Low (1-15%) | AD82: =IF(V82<0,"Loss Making",IF(V82<20,"Low Margin","Healthy Margin")) -> Healthy Margin | AE82: =TEXT(DATE(VALUE(RIGHT(B82,4)),VALUE(MID(B82,4,2)),VALUE(LEFT(B82,2))),"MMM-YYYY") -> Mar-2024 | AF82: =VALUE(RIGHT(B82,4)) -> 2024 | AG82: =CHOOSE(ROUNDUP(VALUE(MID(B82,4,2))/3,0),"Q1","Q2","Q3","Q4") -> Q1
A83: EDU00218 | B83: 29-12-2024 | C83: Vedantu | D83: Creative Arts | E83: Video Editing Basics | F83: Surat | G83: Gujarat | H83: Tier 2 | I83: Female | J83: 35-44 | K83: Email Campaign | L83: Debit Card | M83: Mobile | N83: 6999 | O83: 10 | P83: 699.9 | Q83: 6299.1 | R83: 1133.84 | S83: 5165.26 | T83: 2561.92 | U83: 2603.34 | V83: 50.4 | W83: Yes | Y83: Yes | Z83: 0 | AA83: =TRIM(PROPER(F83)) -> Surat | AB83: =TRIM(PROPER(C83)) -> Vedantu | AC83: =IF(O83=0,"No Discount",IF(O83<=15,"Low (1-15%)",IF(O83<=30,"Medium (16-30%)","High (>30%)"))) -> Low (1-15%) | AD83: =IF(V83<0,"Loss Making",IF(V83<20,"Low Margin","Healthy Margin")) -> Healthy Margin | AE83: =TEXT(DATE(VALUE(RIGHT(B83,4)),VALUE(MID(B83,4,2)),VALUE(LEFT(B83,2))),"MMM-YYYY") -> Dec-2024 | AF83: =VALUE(RIGHT(B83,4)) -> 2024 | AG83: =CHOOSE(ROUNDUP(VALUE(MID(B83,4,2))/3,0),"Q1","Q2","Q3","Q4") -> Q4
A84: EDU01537 | B84: 29-01-2023 | C84: Embibe | D84: Competitive Exams | E84: NEET Complete Course | F84: Vadodara | G84: Gujarat | H84: Tier 3 | I84: Male | J84: 45+ | K84: Word of Mouth | L84: Credit Card | M84: Mobile | N84: 22999 | O84: 10 | P84: 2299.9 | Q84: 20699.1 | R84: 3725.84 | S84: 16973.26 | T84: 7435.79 | U84: 9537.47 | V84: 56.19 | W84: Yes | X84: 2.6 | Y84: No | Z84: 1 | AA84: =TRIM(PROPER(F84)) -> Vadodara | AB84: =TRIM(PROPER(C84)) -> Embibe | AC84: =IF(O84=0,"No Discount",IF(O84<=15,"Low (1-15%)",IF(O84<=30,"Medium (16-30%)","High (>30%)"))) -> Low (1-15%) | AD84: =IF(V84<0,"Loss Making",IF(V84<20,"Low Margin","Healthy Margin")) -> Healthy Margin | AE84: =TEXT(DATE(VALUE(RIGHT(B84,4)),VALUE(MID(B84,4,2)),VALUE(LEFT(B84,2))),"MMM-YYYY") -> Jan-2023 | AF84: =VALUE(RIGHT(B84,4)) -> 2023 | AG84: =CHOOSE(ROUNDUP(VALUE(MID(B84,4,2))/3,0),"Q1","Q2","Q3","Q4") -> Q1
A85: EDU01443 | B85: 30-10-2023 | C85: Vedantu | D85: Coding & Tech | E85: AI/ML Fundamentals | F85: Jodhpur | G85: Rajasthan | H85: Tier 3 | I85: Female | J85: 18-24 | K85: Email Campaign | L85: Wallet | M85: Tablet | N85: 24999 | O85: 10 | P85: 2499.9 | Q85: 22499.1 | R85: 4049.84 | S85: 18449.26 | T85: 6447.62 | U85: 12001.64 | V85: 65.05 | W85: Yes | X85: 3.9 | Y85: No | Z85: 0 | AA85: =TRIM(PROPER(F85)) -> Jodhpur | AB85: =TRIM(PROPER(C85)) -> Vedantu | AC85: =IF(O85=0,"No Discount",IF(O85<=15,"Low (1-15%)",IF(O85<=30,"Medium (16-30%)","High (>30%)"))) -> Low (1-15%) | AD85: =IF(V85<0,"Loss Making",IF(V85<20,"Low Margin","Healthy Margin")) -> Healthy Margin | AE85: =TEXT(DATE(VALUE(RIGHT(B85,4)),VALUE(MID(B85,4,2)),VALUE(LEFT(B85,2))),"MMM-YYYY") -> Oct-2023 | AF85: =VALUE(RIGHT(B85,4)) -> 2023 | AG85: =CHOOSE(ROUNDUP(VALUE(MID(B85,4,2))/3,0),"Q1","Q2","Q3","Q4") -> Q4
A86: EDU01941 | B86: 23-10-2023 | C86: Extramarks | D86: Coding & Tech | E86: Python for Beginners | F86: Kolkata | G86: West Bengal | H86: Tier 1 | I86: Male | J86: 35-44 | K86: Instagram | L86: UPI | M86: Desktop | N86: 7999 | O86: 5 | P86: 399.95 | Q86: 7599.05 | R86: 1367.83 | S86: 6231.22 | T86: 2002.62 | U86: 4228.6 | V86: 67.86 | W86: Yes | Y86: No | Z86: 0 | AA86: =TRIM(PROPER(F86)) -> Kolkata | AB86: =TRIM(PROPER(C86)) -> Extramarks | AC86: =IF(O86=0,"No Discount",IF(O86<=15,"Low (1-15%)",IF(O86<=30,"Medium (16-30%)","High (>30%)"))) -> Low (1-15%) | AD86: =IF(V86<0,"Loss Making",IF(V86<20,"Low Margin","Healthy Margin")) -> Healthy Margin | AE86: =TEXT(DATE(VALUE(RIGHT(B86,4)),VALUE(MID(B86,4,2)),VALUE(LEFT(B86,2))),"MMM-YYYY") -> Oct-2023 | AF86: =VALUE(RIGHT(B86,4)) -> 2023 | AG86: =CHOOSE(ROUNDUP(VALUE(MID(B86,4,2))/3,0),"Q1","Q2","Q3","Q4") -> Q4
A87: EDU01498 | B87: 25-10-2024 | C87: Toppr | D87: Language Learning | E87: IELTS Preparation | F87: Ghaziabad | G87: Delhi NCR | H87: Tier 2 | I87: Other | J87: 13-17 | K87: School/College Partnership | L87: Debit Card | M87: Desktop | N87: 8999 | O87: 30 | P87: 2699.7 | Q87: 6299.3 | R87: 1133.87 | S87: 5165.43 | T87: 2326.66 | U87: 2838.77 | V87: 54.96 | W87: Yes | X87: 4.1 | Y87: No | Z87: 0 | AA87: =TRIM(PROPER(F87)) -> Ghaziabad | AB87: =TRIM(PROPER(C87)) -> Toppr | AC87: =IF(O87=0,"No Discount",IF(O87<=15,"Low (1-15%)",IF(O87<=30,"Medium (16-30%)","High (>30%)"))) -> Medium (16-30%) | AD87: =IF(V87<0,"Loss Making",IF(V87<20,"Low Margin","Healthy Margin")) -> Healthy Margin | AE87: =TEXT(DATE(VALUE(RIGHT(B87,4)),VALUE(MID(B87,4,2)),VALUE(LEFT(B87,2))),"MMM-YYYY") -> Oct-2024 | AF87: =VALUE(RIGHT(B87,4)) -> 2024 | AG87: =CHOOSE(ROUNDUP(VALUE(MID(B87,4,2))/3,0),"Q1","Q2","Q3","Q4") -> Q4
A88: EDU00464 | B88: 27-10-2023 | C88: upGrad | D88: Professional Upskilling | E88: HR Management | F88: Surat | G88: Gujarat | H88: Tier 2 | I88: Female | J88: 35-44 | K88: Instagram | L88: Credit Card | M88: Mobile | N88: 8999 | O88: 25 | P88: 2249.75 | Q88: 6749.25 | R88: 1214.87 | S88: 5534.38 | T88: 2300.11 | U88: 3234.27 | V88: 58.44 | W88: No | Y88: Yes | Z88: 1 | AA88: =TRIM(PROPER(F88)) -> Surat | AB88: =TRIM(PROPER(C88)) -> Upgrad | AC88: =IF(O88=0,"No Discount",IF(O88<=15,"Low (1-15%)",IF(O88<=30,"Medium (16-30%)","High (>30%)"))) -> Medium (16-30%) | AD88: =IF(V88<0,"Loss Making",IF(V88<20,"Low Margin","Healthy Margin")) -> Healthy Margin | AE88: =TEXT(DATE(VALUE(RIGHT(B88,4)),VALUE(MID(B88,4,2)),VALUE(LEFT(B88,2))),"MMM-YYYY") -> Oct-2023 | AF88: =VALUE(RIGHT(B88,4)) -> 2023 | AG88: =CHOOSE(ROUNDUP(VALUE(MID(B88,4,2))/3,0),"Q1","Q2","Q3","Q4") -> Q4
A89: EDU01693 | B89: 13-05-2024 | C89: Scaler | D89: K-12 Academics | E89: Class 11-12 PCB | F89: New Delhi | G89: Delhi NCR | H89: Tier 1 | I89: Female | J89: 35-44 | K89: Direct/Organic | L89: UPI | M89: Desktop | N89: 8499 | O89: 15 | P89: 1274.85 | Q89: 7224.15 | R89: 1300.35 | S89: 5923.8 | T89: 2318.67 | U89: 3605.13 | V89: 60.86 | W89: Yes | X89: 3.9 | Y89: No | Z89: 0 | AA89: =TRIM(PROPER(F89)) -> New Delhi | AB89: =TRIM(PROPER(C89)) -> Scaler | AC89: =IF(O89=0,"No Discount",IF(O89<=15,"Low (1-15%)",IF(O89<=30,"Medium (16-30%)","High (>30%)"))) -> Low (1-15%) | AD89: =IF(V89<0,"Loss Making",IF(V89<20,"Low Margin","Healthy Margin")) -> Healthy Margin | AE89: =TEXT(DATE(VALUE(RIGHT(B89,4)),VALUE(MID(B89,4,2)),VALUE(LEFT(B89,2))),"MMM-YYYY") -> May-2024 | AF89: =VALUE(RIGHT(B89,4)) -> 2024 | AG89: =CHOOSE(ROUNDUP(VALUE(MID(B89,4,2))/3,0),"Q1","Q2","Q3","Q4") -> Q2
A90: EDU00187 | B90: 06-06-2023 | C90: Meritnation | D90: Language Learning | E90: Business English | F90: Madurai | G90: Tamil Nadu | H90: Tier 3 | I90: Other | J90: 18-24 | K90: Word of Mouth | L90: Wallet | M90: Tablet | N90: 6999 | O90: 50 | P90: 3499.5 | Q90: 3499.5 | R90: 629.91 | S90: 2869.59 | T90: 1830.05 | U90: 1039.54 | V90: 36.23 | W90: No | Y90: No | Z90: 1 | AA90: =TRIM(PROPER(F90)) -> Madurai | AB90: =TRIM(PROPER(C90)) -> Meritnation | AC90: =IF(O90=0,"No Discount",IF(O90<=15,"Low (1-15%)",IF(O90<=30,"Medium (16-30%)","High (>30%)"))) -> High (>30%) | AD90: =IF(V90<0,"Loss Making",IF(V90<20,"Low Margin","Healthy Margin")) -> Healthy Margin | AE90: =TEXT(DATE(VALUE(RIGHT(B90,4)),VALUE(MID(B90,4,2)),VALUE(LEFT(B90,2))),"MMM-YYYY") -> Jun-2023 | AF90: =VALUE(RIGHT(B90,4)) -> 2023 | AG90: =CHOOSE(ROUNDUP(VALUE(MID(B90,4,2))/3,0),"Q1","Q2","Q3","Q4") -> Q2
A91: EDU00749 | B91: 06-11-2024 | C91: BYJU'S | D91: Test Preparation | E91: SAT Complete Prep | F91: Warangal | G91: Telangana | H91: Tier 3 | I91: Female | J91: 35-44 | K91: YouTube | L91: UPI | M91: Mobile | N91: 12999 | O91: 10 | P91: 1299.9 | Q91: 11699.1 | R91: 2105.84 | S91: 9593.26 | T91: 4011.27 | U91: 5581.99 | V91: 58.19 | W91: Yes | X91: 2.7 | Y91: No | Z91: 0 | AA91: =TRIM(PROPER(F91)) -> Warangal | AB91: =TRIM(PROPER(C91)) -> Byju'S | AC91: =IF(O91=0,"No Discount",IF(O91<=15,"Low (1-15%)",IF(O91<=30,"Medium (16-30%)","High (>30%)"))) -> Low (1-15%) | AD91: =IF(V91<0,"Loss Making",IF(V91<20,"Low Margin","Healthy Margin")) -> Healthy Margin | AE91: =TEXT(DATE(VALUE(RIGHT(B91,4)),VALUE(MID(B91,4,2)),VALUE(LEFT(B91,2))),"MMM-YYYY") -> Nov-2024 | AF91: =VALUE(RIGHT(B91,4)) -> 2024 | AG91: =CHOOSE(ROUNDUP(VALUE(MID(B91,4,2))/3,0),"Q1","Q2","Q3","Q4") -> Q4
A92: EDU00537 | B92: 07-02-2024 | C92: Doubtnut | D92: Test Preparation | E92: SAT Complete Prep | F92: Mumbai | G92: Maharashtra | H92: Tier 1 | I92: Other | J92: 13-17 | K92: Direct/Organic | L92: Wallet | M92: Desktop | N92: 12999 | O92: 0 | P92: 0 | Q92: 12999 | R92: 2339.82 | S92: 10659.18 | T92: 3286.58 | U92: 7372.6 | V92: 69.17 | W92: Yes | X92: 3.9 | Y92: No | Z92: 0 | AA92: =TRIM(PROPER(F92)) -> Mumbai | AB92: =TRIM(PROPER(C92)) -> Doubtnut | AC92: =IF(O92=0,"No Discount",IF(O92<=15,"Low (1-15%)",IF(O92<=30,"Medium (16-30%)","High (>30%)"))) -> No Discount | AD92: =IF(V92<0,"Loss Making",IF(V92<20,"Low Margin","Healthy Margin")) -> Healthy Margin | AE92: =TEXT(DATE(VALUE(RIGHT(B92,4)),VALUE(MID(B92,4,2)),VALUE(LEFT(B92,2))),"MMM-YYYY") -> Feb-2024 | AF92: =VALUE(RIGHT(B92,4)) -> 2024 | AG92: =CHOOSE(ROUNDUP(VALUE(MID(B92,4,2))/3,0),"Q1","Q2","Q3","Q4") -> Q1
A93: EDU01959 | B93: 12-06-2023 | C93: Extramarks | D93: Competitive Exams | E93: GATE CS Complete | F93: Coimbatore | G93: Tamil Nadu | H93: Tier 2 | I93: Other | J93: 25-34 | K93: YouTube | L93: Credit Card | M93: Desktop | N93: 12999 | O93: 50 | P93: 6499.5 | Q93: 6499.5 | R93: 1169.91 | S93: 5329.59 | T93: 3156.68 | U93: 2172.91 | V93: 40.77 | W93: No | Y93: No | Z93: 0 | AA93: =TRIM(PROPER(F93)) -> Coimbatore | AB93: =TRIM(PROPER(C93)) -> Extramarks | AC93: =IF(O93=0,"No Discount",IF(O93<=15,"Low (1-15%)",IF(O93<=30,"Medium (16-30%)","High (>30%)"))) -> High (>30%) | AD93: =IF(V93<0,"Loss Making",IF(V93<20,"Low Margin","Healthy Margin")) -> Healthy Margin | AE93: =TEXT(DATE(VALUE(RIGHT(B93,4)),VALUE(MID(B93,4,2)),VALUE(LEFT(B93,2))),"MMM-YYYY") -> Jun-2023 | AF93: =VALUE(RIGHT(B93,4)) -> 2023 | AG93: =CHOOSE(ROUNDUP(VALUE(MID(B93,4,2))/3,0),"Q1","Q2","Q3","Q4") -> Q2
A94: EDU02071 | B94: 21-02-2023 | C94: Unacademy | D94: Professional Upskilling | E94: Data Analytics Bootcamp | F94: BENGALURU | G94: Karnataka | H94: Tier 1 | I94: Male | J94: 45+ | K94: School/College Partnership | L94: UPI | M94: Mobile | N94: 19999 | O94: 50 | P94: 9999.5 | Q94: 9999.5 | R94: 1799.91 | S94: 8199.59 | T94: 4033.97 | U94: 4165.62 | V94: 50.8 | W94: Yes | X94: 4.2 | Y94: No | Z94: 0 | AA94: =TRIM(PROPER(F94)) -> Bengaluru | AB94: =TRIM(PROPER(C94)) -> Unacademy | AC94: =IF(O94=0,"No Discount",IF(O94<=15,"Low (1-15%)",IF(O94<=30,"Medium (16-30%)","High (>30%)"))) -> High (>30%) | AD94: =IF(V94<0,"Loss Making",IF(V94<20,"Low Margin","Healthy Margin")) -> Healthy Margin | AE94: =TEXT(DATE(VALUE(RIGHT(B94,4)),VALUE(MID(B94,4,2)),VALUE(LEFT(B94,2))),"MMM-YYYY") -> Feb-2023 | AF94: =VALUE(RIGHT(B94,4)) -> 2023 | AG94: =CHOOSE(ROUNDUP(VALUE(MID(B94,4,2))/3,0),"Q1","Q2","Q3","Q4") -> Q1
A95: EDU01776 | B95: 26-05-2023 | C95: upGrad | D95: Coding & Tech | E95: Full Stack Development | F95: Hyderabad | G95: Telangana | H95: Tier 1 | I95: Male | J95: 25-34 | K95: School/College Partnership | L95: Credit Card | M95: Mobile | N95: 29999 | O95: 5 | P95: 1499.95 | Q95: 28499.05 | R95: 5129.83 | S95: 23369.22 | T95: 8074.25 | U95: 15294.97 | V95: 65.45 | W95: Yes | Y95: No | Z95: 0 | AA95: =TRIM(PROPER(F95)) -> Hyderabad | AB95: =TRIM(PROPER(C95)) -> Upgrad | AC95: =IF(O95=0,"No Discount",IF(O95<=15,"Low (1-15%)",IF(O95<=30,"Medium (16-30%)","High (>30%)"))) -> Low (1-15%) | AD95: =IF(V95<0,"Loss Making",IF(V95<20,"Low Margin","Healthy Margin")) -> Healthy Margin | AE95: =TEXT(DATE(VALUE(RIGHT(B95,4)),VALUE(MID(B95,4,2)),VALUE(LEFT(B95,2))),"MMM-YYYY") -> May-2023 | AF95: =VALUE(RIGHT(B95,4)) -> 2023 | AG95: =CHOOSE(ROUNDUP(VALUE(MID(B95,4,2))/3,0),"Q1","Q2","Q3","Q4") -> Q2
A96: EDU00978 | B96: 07-09-2024 | C96: Simplilearn | D96: K-12 Academics | E96: Class 11-12 PCM | F96: Kolkata | G96: West Bengal | H96: Tier 1 | I96: Other | J96: 25-34 | K96: Instagram | L96: Credit Card | M96: Desktop | N96: 8999 | O96: 10 | P96: 899.9 | Q96: 8099.1 | R96: 1457.84 | S96: 6641.26 | T96: 2188.59 | U96: 4452.67 | V96: 67.05 | W96: No | Y96: No | Z96: 0 | AA96: =TRIM(PROPER(F96)) -> Kolkata | AB96: =TRIM(PROPER(C96)) -> Simplilearn | AC96: =IF(O96=0,"No Discount",IF(O96<=15,"Low (1-15%)",IF(O96<=30,"Medium (16-30%)","High (>30%)"))) -> Low (1-15%) | AD96: =IF(V96<0,"Loss Making",IF(V96<20,"Low Margin","Healthy Margin")) -> Healthy Margin | AE96: =TEXT(DATE(VALUE(RIGHT(B96,4)),VALUE(MID(B96,4,2)),VALUE(LEFT(B96,2))),"MMM-YYYY") -> Sep-2024 | AF96: =VALUE(RIGHT(B96,4)) -> 2024 | AG96: =CHOOSE(ROUNDUP(VALUE(MID(B96,4,2))/3,0),"Q1","Q2","Q3","Q4") -> Q3
A97: EDU00515 | B97: 18-02-2024 | C97: Extramarks | D97: Coding & Tech | E97: Python for Beginners | F97: Ghaziabad | G97: Delhi NCR | H97: Tier 2 | I97: Male | J97: 45+ | K97: Email Campaign | L97: UPI | M97: Desktop | N97: 7999 | O97: 10 | P97: 799.9 | Q97: 7199.1 | R97: 1295.84 | S97: 5903.26 | T97: 2230.62 | U97: 3672.64 | V97: 62.21 | W97: No | Y97: No | Z97: 1 | AA97: =TRIM(PROPER(F97)) -> Ghaziabad | AB97: =TRIM(PROPER(C97)) -> Extramarks | AC97: =IF(O97=0,"No Discount",IF(O97<=15,"Low (1-15%)",IF(O97<=30,"Medium (16-30%)","High (>30%)"))) -> Low (1-15%) | AD97: =IF(V97<0,"Loss Making",IF(V97<20,"Low Margin","Healthy Margin")) -> Healthy Margin | AE97: =TEXT(DATE(VALUE(RIGHT(B97,4)),VALUE(MID(B97,4,2)),VALUE(LEFT(B97,2))),"MMM-YYYY") -> Feb-2024 | AF97: =VALUE(RIGHT(B97,4)) -> 2024 | AG97: =CHOOSE(ROUNDUP(VALUE(MID(B97,4,2))/3,0),"Q1","Q2","Q3","Q4") -> Q1
A98: EDU02158 | B98: 14-01-2023 | C98: Great Learning | D98: Professional Upskilling | E98: Data Analytics Bootcamp | F98: Hyderabad | G98: Telangana | H98: Tier 1 | I98: Male | J98: 13-17 | K98: Email Campaign | L98: Debit Card | M98: Desktop | N98: 19999 | O98: 0 | P98: 0 | Q98: 19999 | R98: 3599.82 | S98: 16399.18 | T98: 5756.67 | U98: 10642.51 | V98: 64.9 | W98: No | Y98: No | Z98: 1 | AA98: =TRIM(PROPER(F98)) -> Hyderabad | AB98: =TRIM(PROPER(C98)) -> Great Learning | AC98: =IF(O98=0,"No Discount",IF(O98<=15,"Low (1-15%)",IF(O98<=30,"Medium (16-30%)","High (>30%)"))) -> No Discount | AD98: =IF(V98<0,"Loss Making",IF(V98<20,"Low Margin","Healthy Margin")) -> Healthy Margin | AE98: =TEXT(DATE(VALUE(RIGHT(B98,4)),VALUE(MID(B98,4,2)),VALUE(LEFT(B98,2))),"MMM-YYYY") -> Jan-2023 | AF98: =VALUE(RIGHT(B98,4)) -> 2023 | AG98: =CHOOSE(ROUNDUP(VALUE(MID(B98,4,2))/3,0),"Q1","Q2","Q3","Q4") -> Q1
A99: EDU00171 | B99: 20-08-2024 | C99: Vedantu | D99: Creative Arts | E99: Graphic Design Pro | F99: HYDERABAD | G99: Telangana | H99: Tier 1 | I99: Other | J99: 13-17 | K99: Word of Mouth | L99: UPI | M99: Desktop | N99: 9999 | O99: 40 | P99: 3999.6 | Q99: 5999.4 | R99: 1079.89 | S99: 4919.51 | T99: 2631 | U99: 2288.51 | V99: 46.52 | W99: Yes | Y99: No | Z99: 0 | AA99: =TRIM(PROPER(F99)) -> Hyderabad | AB99: =TRIM(PROPER(C99)) -> Vedantu | AC99: =IF(O99=0,"No Discount",IF(O99<=15,"Low (1-15%)",IF(O99<=30,"Medium (16-30%)","High (>30%)"))) -> High (>30%) | AD99: =IF(V99<0,"Loss Making",IF(V99<20,"Low Margin","Healthy Margin")) -> Healthy Margin | AE99: =TEXT(DATE(VALUE(RIGHT(B99,4)),VALUE(MID(B99,4,2)),VALUE(LEFT(B99,2))),"MMM-YYYY") -> Aug-2024 | AF99: =VALUE(RIGHT(B99,4)) -> 2024 | AG99: =CHOOSE(ROUNDUP(VALUE(MID(B99,4,2))/3,0),"Q1","Q2","Q3","Q4") -> Q3
A100: EDU00984 | B100: 16-03-2024 | C100: upGrad | D100: Higher Education | E100: B.Tech CSE Support | F100: Jaipur | G100: Rajasthan | H100: Tier 2 | I100: Female | J100: 25-34 | K100: Word of Mouth | L100: Debit Card | M100: Desktop | N100: 9999 | O100: 20 | P100: 1999.8 | Q100: 7999.2 | R100: 1439.86 | S100: 6559.34 | T100: 2882.03 | U100: 3677.31 | V100: 56.06 | W100: Yes | X100: 3.7 | Y100: No | Z100: 2 | AA100: =TRIM(PROPER(F100)) -> Jaipur | AB100: =TRIM(PROPER(C100)) -> Upgrad | AC100: =IF(O100=0,"No Discount",IF(O100<=15,"Low (1-15%)",IF(O100<=30,"Medium (16-30%)","High (>30%)"))) -> Medium (16-30%) | AD100: =IF(V100<0,"Loss Making",IF(V100<20,"Low Margin","Healthy Margin")) -> Healthy Margin | AE100: =TEXT(DATE(VALUE(RIGHT(B100,4)),VALUE(MID(B100,4,2)),VALUE(LEFT(B100,2))),"MMM-YYYY") -> Mar-2024 | AF100: =VALUE(RIGHT(B100,4)) -> 2024 | AG100: =CHOOSE(ROUNDUP(VALUE(MID(B100,4,2))/3,0),"Q1","Q2","Q3","Q4") -> Q1
...

Sheet Lookup Tables
A1: TABLE A: City → Tier & Regional Head Mapping | F1: TABLE B: GST Rate Reference
A2: City | B2: State | C2: City_Tier | D2: Regional_Head | F2: Price_Bracket | G2: GST_Rate_%
A3: New Delhi | B3: Delhi NCR | C3: Tier 1 | D3: Priya Sharma | F3: Below ₹1,000 | G3: 12%
A4: Gurugram | B4: Delhi NCR | C4: Tier 1 | D4: Priya Sharma | F4: ₹1,000 – ₹9,999 | G4: 18%
A5: Noida | B5: Delhi NCR | C5: Tier 1 | D5: Priya Sharma | F5: Above ₹10,000 | G5: 18%
A6: Faridabad | B6: Delhi NCR | C6: Tier 2 | D6: Arjun Mehta
A7: Ghaziabad | B7: Delhi NCR | C7: Tier 2 | D7: Arjun Mehta
A8: Mumbai | B8: Maharashtra | C8: Tier 1 | D8: Priya Sharma
A9: Pune | B9: Maharashtra | C9: Tier 1 | D9: Priya Sharma
A10: Nagpur | B10: Maharashtra | C10: Tier 2 | D10: Arjun Mehta
A11: Nashik | B11: Maharashtra | C11: Tier 2 | D11: Arjun Mehta
A12: Bengaluru | B12: Karnataka | C12: Tier 1 | D12: Priya Sharma
A13: Mysuru | B13: Karnataka | C13: Tier 2 | D13: Arjun Mehta
A14: Mangaluru | B14: Karnataka | C14: Tier 3 | D14: Kavita Iyer
A15: Chennai | B15: Tamil Nadu | C15: Tier 1 | D15: Priya Sharma
A16: Coimbatore | B16: Tamil Nadu | C16: Tier 2 | D16: Arjun Mehta
A17: Madurai | B17: Tamil Nadu | C17: Tier 3 | D17: Kavita Iyer
... A26: Jodhpur | B26: Rajasthan | C26: Tier 3 | D26: Kavita Iyer

Sheet KPI Summary
A1: EdTech India — KPI Summary (Formula-Based)
A3: SECTION 1: Performance by Course Category
A5: Course_Category | B5: Total_Enrollments | C5: Total_Net_Revenue_INR | D5: Total_Gross_Profit_INR | E5: Avg_Margin_% | F5: Completion_Rate_% | G5: Refund_Rate_% | H5: Avg_Rating
A6: K-12 Academics | B6: =COUNTIFS('Working Data'!D:D,A6) -> 311 | C6: =SUMIFS('Working Data'!S:S,'Working Data'!D:D,A6) -> 1535835.2 | D6: =SUMIFS('Working Data'!U:U,'Working Data'!D:D,A6) -> 861549.18 | E6: =IFERROR(D6/C6,0) -> 0.56096459 | F6: =IFERROR(COUNTIFS('Working Data'!D:D,A6,'Working Data'!W:W,"Yes")/B6,0) -> 0.60128617 | G6: =IFERROR(COUNTIFS('Working Data'!D:D,A6,'Working Data'!Y:Y,"Yes")/B6,0) -> 0.10610932 | H6: =IFERROR(AVERAGEIFS('Working Data'!X:X,'Working Data'!D:D,A6,'Working Data'!X:X,"<>"),"") -> 3.6691824
A7: Competitive Exams | B7: =COUNTIFS('Working Data'!D:D,A7) -> 322 | C7: =SUMIFS('Working Data'!S:S,'Working Data'!D:D,A7) -> 4154596.2 | D7: =SUMIFS('Working Data'!U:U,'Working Data'!D:D,A7) -> 2342879.5 | E7: =IFERROR(D7/C7,0) -> 0.56392471 | F7: =IFERROR(COUNTIFS('Working Data'!D:D,A7,'Working Data'!W:W,"Yes")/B7,0) -> 0.59006211 | G7: =IFERROR(COUNTIFS('Working Data'!D:D,A7,'Working Data'!Y:Y,"Yes")/B7,0) -> 0.080745342 | H7: =IFERROR(AVERAGEIFS('Working Data'!X:X,'Working Data'!D:D,A7,'Working Data'!X:X,"<>"),"") -> 3.6779874
A8: Higher Education | B8: =COUNTIFS('Working Data'!D:D,A8) -> 328 | C8: =SUMIFS('Working Data'!S:S,'Working Data'!D:D,A8) -> 2200349.6 | D8: =SUMIFS('Working Data'!U:U,'Working Data'!D:D,A8) -> 1230576.1 | E8: =IFERROR(D8/C8,0) -> 0.55926388 | F8: =IFERROR(COUNTIFS('Working Data'!D:D,A8,'Working Data'!W:W,"Yes")/B8,0) -> 0.59146341 | G8: =IFERROR(COUNTIFS('Working Data'!D:D,A8,'Working Data'!Y:Y,"Yes")/B8,0) -> 0.10060976 | H8: =IFERROR(AVERAGEIFS('Working Data'!X:X,'Working Data'!D:D,A8,'Working Data'!X:X,"<>"),"") -> 3.7288344
A9: Professional Upskilling | B9: =COUNTIFS('Working Data'!D:D,A9) -> 320 | C9: =SUMIFS('Working Data'!S:S,'Working Data'!D:D,A9) -> 3179253.1 | D9: =SUMIFS('Working Data'!U:U,'Working Data'!D:D,A9) -> 1794086.7 | E9: =IFERROR(D9/C9,0) -> 0.56431077 | F9: =IFERROR(COUNTIFS('Working Data'!D:D,A9,'Working Data'!W:W,"Yes")/B9,0) -> 0.63125 | G9: =IFERROR(COUNTIFS('Working Data'!D:D,A9,'Working Data'!Y:Y,"Yes")/B9,0) -> 0.075 | H9: =IFERROR(AVERAGEIFS('Working Data'!X:X,'Working Data'!D:D,A9,'Working Data'!X:X,"<>"),"") -> 3.9949153
A10: Coding & Tech | B10: =COUNTIFS('Working Data'!D:D,A10) -> 303 | C10: =SUMIFS('Working Data'!S:S,'Working Data'!D:D,A10) -> 5012087.2 | D10: =SUMIFS('Working Data'!U:U,'Working Data'!D:D,A10) -> 2949812.9 | E10: =IFERROR(D10/C10,0) -> 0.58853982 | F10: =IFERROR(COUNTIFS('Working Data'!D:D,A10,'Working Data'!W:W,"Yes")/B10,0) -> 0.66336634 | G10: =IFERROR(COUNTIFS('Working Data'!D:D,A10,'Working Data'!Y:Y,"Yes")/B10,0) -> 0.095709571 | H10: =IFERROR(AVERAGEIFS('Working Data'!X:X,'Working Data'!D:D,A10,'Working Data'!X:X,"<>"),"") -> 4.0131737
A11: Language Learning | B11: =COUNTIFS('Working Data'!D:D,A11) -> 293 | C11: =SUMIFS('Working Data'!S:S,'Working Data'!D:D,A11) -> 1398842.2 | D11: =SUMIFS('Working Data'!U:U,'Working Data'!D:D,A11) -> 776390.17 | E11: =IFERROR(D11/C11,0) -> 0.55502342 | F11: =IFERROR(COUNTIFS('Working Data'!D:D,A11,'Working Data'!W:W,"Yes")/B11,0) -> 0.58703072 | G11: =IFERROR(COUNTIFS('Working Data'!D:D,A11,'Working Data'!Y:Y,"Yes")/B11,0) -> 0.09556314 | H11: =IFERROR(AVERAGEIFS('Working Data'!X:X,'Working Data'!D:D,A11,'Working Data'!X:X,"<>"),"") -> 3.6386207
A12: Creative Arts | B12: =COUNTIFS('Working Data'!D:D,A12) -> 315 | C12: =SUMIFS('Working Data'!S:S,'Working Data'!D:D,A12) -> 2285702.8 | D12: =SUMIFS('Working Data'!U:U,'Working Data'!D:D,A12) -> 1273862.2 | E12: =IFERROR(D12/C12,0) -> 0.55731752 | F12: =IFERROR(COUNTIFS('Working Data'!D:D,A12,'Working Data'!W:W,"Yes")/B12,0) -> 0.63809524 | G12: =IFERROR(COUNTIFS('Working Data'!D:D,A12,'Working Data'!Y:Y,"Yes")/B12,0) -> 0.092063492 | H12: =IFERROR(AVERAGEIFS('Working Data'!X:X,'Working Data'!D:D,A12,'Working Data'!X:X,"<>"),"") -> 3.7011628
A13: Test Preparation | B13: =COUNTIFS('Working Data'!D:D,A13) -> 316 | C13: =SUMIFS('Working Data'!S:S,'Working Data'!D:D,A13) -> 3048418.5 | D13: =SUMIFS('Working Data'!U:U,'Working Data'!D:D,A13) -> 1698438.2 | E13: =IFERROR(D13/C13,0) -> 0.55715387 | F13: =IFERROR(COUNTIFS('Working Data'!D:D,A13,'Working Data'!W:W,"Yes")/B13,0) -> 0.67088608 | G13: =IFERROR(COUNTIFS('Working Data'!D:D,A13,'Working Data'!Y:Y,"Yes")/B13,0) -> 0.079113924 | H13: =IFERROR(AVERAGEIFS('Working Data'!X:X,'Working Data'!D:D,A13,'Working Data'!X:X,"<>"),"") -> 3.7032787
A16: SECTION 2: Performance by City Tier
A18: City_Tier | B18: Total_Enrollments | C18: Total_Net_Revenue_INR | D18: Total_Gross_Profit_INR | E18: Avg_Margin_% | F18: Completion_Rate_% | G18: Refund_Rate_% | H18: Avg_Rating
A19: Tier 1 | B19: =COUNTIFS('Working Data'!H:H,A19) -> 1055 | C19: =SUMIFS('Working Data'!S:S,'Working Data'!H:H,A19) -> 9501994.9 | D19: =SUMIFS('Working Data'!U:U,'Working Data'!H:H,A19) -> 5669036.1 | E19: =IFERROR(D19/C19,0) -> 0.59661536 | F19: =IFERROR(COUNTIFS('Working Data'!H:H,A19,'Working Data'!W:W,"Yes")/B19,0) -> 0.62559242 | G19: =IFERROR(COUNTIFS('Working Data'!H:H,A19,'Working Data'!Y:Y,"Yes")/B19,0) -> 0.090047393 | H19: =IFERROR(AVERAGEIFS('Working Data'!X:X,'Working Data'!H:H,A19,'Working Data'!X:X,"<>"),"") -> 3.7827338
A20: Tier 2 | B20: =COUNTIFS('Working Data'!H:H,A20) -> 819 | C20: =SUMIFS('Working Data'!S:S,'Working Data'!H:H,A20) -> 7450319.6 | D20: =SUMIFS('Working Data'!U:U,'Working Data'!H:H,A20) -> 4057538.7 | E20: =IFERROR(D20/C20,0) -> 0.54461271 | F20: =IFERROR(COUNTIFS('Working Data'!H:H,A20,'Working Data'!W:W,"Yes")/B20,0) -> 0.64102564 | G20: =IFERROR(COUNTIFS('Working Data'!H:H,A20,'Working Data'!Y:Y,"Yes")/B20,0) -> 0.073260073 | H20: =IFERROR(AVERAGEIFS('Working Data'!X:X,'Working Data'!H:H,A20,'Working Data'!X:X,"<>"),"") -> 3.7365044
A21: Tier 3 | B21: =COUNTIFS('Working Data'!H:H,A21) -> 634 | C21: =SUMIFS('Working Data'!S:S,'Working Data'!H:H,A21) -> 5862770.3 | D21: =SUMIFS('Working Data'!U:U,'Working Data'!H:H,A21) -> 3201020.1 | E21: =IFERROR(D21/C21,0) -> 0.54599105 | F21: =IFERROR(COUNTIFS('Working Data'!H:H,A21,'Working Data'!W:W,"Yes")/B21,0) -> 0.58990536 | G21: =IFERROR(COUNTIFS('Working Data'!H:H,A21,'Working Data'!Y:Y,"Yes")/B21,0) -> 0.11356467 | H21: =IFERROR(AVERAGEIFS('Working Data'!X:X,'Working Data'!H:H,A21,'Working Data'!X:X,"<>"),"") -> 3.7952681

Sheet Project Notes
A1: EdTech India Sales & Completion Analysis — Analyst Documentation
A3: Finding / Step | B3: Detail
A4: Dataset Overview | B4: Synthetic dataset of 2,508 rows (including 8 intentional duplicates) representing student enrollments across 15 EdTech companies, 24 Indian cities, and 8 course categories. Period: Jan 2023 – Dec 2024.
A5: Data Cleaning – Step 1 | B5: Checked for duplicate Enrollment_IDs using Remove Duplicates on column A. Result: 8 duplicates found and removed. Working Data tab used as clean copy; RAW DATA tab protected.
A6: Data Cleaning – Step 2 | B6: Applied TRIM(PROPER()) to City and Company columns to fix 3% upper-case city names and 2% trailing spaces in company names. Formula columns: Cleaned_City, Cleaned_Company.
A7: Missing Values | B7: Student_Rating is blank where: (a) Course_Completed = No, or (b) student opted not to rate (~15% of completers). Decision: left blank; excluded from AVERAGEIFS using '<>' criterion.
A8: Calculated Columns Added | B8: Discount_Category (IFS), Profit_Flag (IF), Month_Year (TEXT+DATEVALUE), Year (YEAR+DATEVALUE), Quarter (CHOOSE+ROUNDUP+MONTH+DATEVALUE).
A9: KPI Cross-Check | B9: SUMIFS-based KPI Summary sheet built independently of Pivot Tables to cross-validate pivot output. Any discrepancy >0.1% flagged for investigation.
A10: Analytical Finding 1 | B10: High-discount (>30%) enrollments show 12pp lower completion rates and negative or near-zero gross margins, suggesting aggressive discounting erodes both revenue quality and student commitment.
A11: Analytical Finding 2 | B11: Coding & Tech leads on margin (58.9%) and completion rate (66.3%), followed by Professional Upskilling (56.4% margin, 63.1% completion). K-12 Academics has the lowest completion rate (60.1%) among categories, though margins are broadly similar (54-59%) across all categories.
A12: Analytical Finding 3 | B12: Tier 2 and Tier 3 cities show 6-8% lower completion rates but comparable refund rates to Tier 1, suggesting infrastructure/connectivity may be a barrier rather than dissatisfaction.
A13: Data Source Note | B13: Dataset is synthetically generated to reflect realistic Indian EdTech market patterns (pricing, GST structure, city-tier distribution, course mix). Not proprietary data.
A14: KPI Formula Fix | B14: Corrected Section 1 (Performance by Course Category) formulas in KPI Summary: COUNTIFS/SUMIFS/AVERAGEIFS were referencing 'Working Data'!E:E (Course_Name) instead of 'Working Data'!D:D (Course_Category), causing all Section 1 totals to return 0. Updated to reference column D. Also removed 8 trailing blank rows from RAW DATA and Working Data tabs.
